Workbook

Sheet Source_Data
A1: EPS 1995 Arrears - Source Data
A3: Year | B3: Taxable Income before Arrears | C3: Arrears | D3: Taxable Income after Arrears | E3: Tax Regime | F3: Category | H3: Workbook note | I3: Edit this sheet only if source arrears/income data changes.
A4: 2014-15 | B4: 0 | C4: 0 | D4: =B4+C4 -> 0 | E4: OLD | F4: Resident-Normal Citizen | H4: Receipt year | I4: 2025-26
A5: 2015-16 | B5: 0 | C5: 0 | D5: =B5+C5 -> 0 | E5: OLD | F5: Resident-Normal Citizen | H5: Assessment year | I5: 2026-27
A6: 2016-17 | B6: 0 | C6: 0 | D6: =B6+C6 -> 0 | E6: OLD | F6: Resident-Senior Citizen | H6: Relief basis | I6: Section 89(1), Rule 21A, Form 10E Annexure I
A7: 2017-18 | B7: 0 | C7: 0 | D7: =B7+C7 -> 0 | E7: OLD | F7: Resident-Senior Citizen | H7: Receipt-year arrears check | I7: =SUM(C4:C14) -> 0
A8: 2018-19 | B8: 0 | C8: 0 | D8: =B8+C8 -> 0 | E8: OLD | F8: Resident-Normal Citizen | H8: Status | I8: =IF(I7=C15,"OK","Check receipt-year arrears") -> OK
A9: 2019-20 | B9: 0 | C9: 0 | D9: =B9+C9 -> 0 | E9: OLD | F9: Resident-Normal Citizen
A10: 2020-21 | B10: 0 | C10: 0 | D10: =B10+C10 -> 0 | E10: OLD | F10: Resident-Senior Citizen | H10: Form 10E details
A11: 2021-22 | B11: 0 | C11: 0 | D11: =B11+C11 -> 0 | E11: OLD | F11: Resident-Senior Citizen | H11: Name
A12: 2022-23 | B12: 0 | C12: 0 | D12: =B12+C12 -> 0 | E12: NEW | F12: Resident-Senior Citizen | H12: PAN
A13: 2023-24 | B13: 0 | C13: 0 | D13: =B13+C13 -> 0 | E13: NEW | F13: Resident-Senior Citizen | H13: Address
A14: 2024-25 | B14: 0 | C14: 0 | D14: =B14+C14 -> 0 | E14: NEW | F14: Resident-Senior Citizen | H14: Status | I14: RESIDENT - SR CITIZEN
A15: 2025-26 | B15: 0 | C15: =SUM(C4:C14) -> 0 | D15: =B15+C15 -> 0 | E15: NEW | F15: Resident-Senior Citizen
A17: Note : Taxable Income before Arrears excludes capital gains/special-rate income where normal slabs do not apply.

Sheet Relief_Calculation
A1: Section 89(1) Relief Calculation
A3: Financial Year | B3: Taxable income before arrears | C3: Arrears attributable | D3: Taxable income after arrears | E3: Regime | F3: Category | G3: Basic tax before | H3: Rebate before | I3: Surcharge before | J3: Cess before | K3: Tax before | L3: Basic tax after | M3: Rebate after | N3: Surcharge after | O3: Cess after | P3: Tax after | Q3: Extra tax due to arrears
A4: =Source_Data!A4 -> 2014-15 | B4: =Source_Data!B4 -> 0 | C4: =Source_Data!C4 -> 0 | D4: =Source_Data!D4 -> 0 | E4: =Source_Data!E4 -> OLD | F4: =Source_Data!F4 -> Resident-Normal Citizen | G4: =Tax_Engine!G4 -> 0 | H4: =Tax_Engine!H4 -> 0 | I4: =Tax_Engine!I4 -> 0 | J4: =Tax_Engine!J4 -> 0 | K4: =ROUND(G4-H4+I4+J4,2) -> 0 | L4: =Tax_Engine!L4 -> 0 | M4: =Tax_Engine!M4 -> 0 | N4: =Tax_Engine!N4 -> 0 | O4: =Tax_Engine!O4 -> 0 | P4: =ROUND(L4-M4+N4+O4,2) -> 0 | Q4: =ROUND(P4-K4,2) -> 0
A5: =Source_Data!A5 -> 2015-16 | B5: =Source_Data!B5 -> 0 | C5: =Source_Data!C5 -> 0 | D5: =Source_Data!D5 -> 0 | E5: =Source_Data!E5 -> OLD | F5: =Source_Data!F5 -> Resident-Normal Citizen | G5: =Tax_Engine!G5 -> 0 | H5: =Tax_Engine!H5 -> 0 | I5: =Tax_Engine!I5 -> 0 | J5: =Tax_Engine!J5 -> 0 | K5: =ROUND(G5-H5+I5+J5,2) -> 0 | L5: =Tax_Engine!L5 -> 0 | M5: =Tax_Engine!M5 -> 0 | N5: =Tax_Engine!N5 -> 0 | O5: =Tax_Engine!O5 -> 0 | P5: =ROUND(L5-M5+N5+O5,2) -> 0 | Q5: =ROUND(P5-K5,2) -> 0
A6: =Source_Data!A6 -> 2016-17 | B6: =Source_Data!B6 -> 0 | C6: =Source_Data!C6 -> 0 | D6: =Source_Data!D6 -> 0 | E6: =Source_Data!E6 -> OLD | F6: =Source_Data!F6 -> Resident-Senior Citizen | G6: =Tax_Engine!G6 -> 0 | H6: =Tax_Engine!H6 -> 0 | I6: =Tax_Engine!I6 -> 0 | J6: =Tax_Engine!J6 -> 0 | K6: =ROUND(G6-H6+I6+J6,2) -> 0 | L6: =Tax_Engine!L6 -> 0 | M6: =Tax_Engine!M6 -> 0 | N6: =Tax_Engine!N6 -> 0 | O6: =Tax_Engine!O6 -> 0 | P6: =ROUND(L6-M6+N6+O6,2) -> 0 | Q6: =ROUND(P6-K6,2) -> 0
A7: =Source_Data!A7 -> 2017-18 | B7: =Source_Data!B7 -> 0 | C7: =Source_Data!C7 -> 0 | D7: =Source_Data!D7 -> 0 | E7: =Source_Data!E7 -> OLD | F7: =Source_Data!F7 -> Resident-Senior Citizen | G7: =Tax_Engine!G7 -> 0 | H7: =Tax_Engine!H7 -> 0 | I7: =Tax_Engine!I7 -> 0 | J7: =Tax_Engine!J7 -> 0 | K7: =ROUND(G7-H7+I7+J7,2) -> 0 | L7: =Tax_Engine!L7 -> 0 | M7: =Tax_Engine!M7 -> 0 | N7: =Tax_Engine!N7 -> 0 | O7: =Tax_Engine!O7 -> 0 | P7: =ROUND(L7-M7+N7+O7,2) -> 0 | Q7: =ROUND(P7-K7,2) -> 0
A8: =Source_Data!A8 -> 2018-19 | B8: =Source_Data!B8 -> 0 | C8: =Source_Data!C8 -> 0 | D8: =Source_Data!D8 -> 0 | E8: =Source_Data!E8 -> OLD | F8: =Source_Data!F8 -> Resident-Normal Citizen | G8: =Tax_Engine!G8 -> 0 | H8: =Tax_Engine!H8 -> 0 | I8: =Tax_Engine!I8 -> 0 | J8: =Tax_Engine!J8 -> 0 | K8: =ROUND(G8-H8+I8+J8,2) -> 0 | L8: =Tax_Engine!L8 -> 0 | M8: =Tax_Engine!M8 -> 0 | N8: =Tax_Engine!N8 -> 0 | O8: =Tax_Engine!O8 -> 0 | P8: =ROUND(L8-M8+N8+O8,2) -> 0 | Q8: =ROUND(P8-K8,2) -> 0
A9: =Source_Data!A9 -> 2019-20 | B9: =Source_Data!B9 -> 0 | C9: =Source_Data!C9 -> 0 | D9: =Source_Data!D9 -> 0 | E9: =Source_Data!E9 -> OLD | F9: =Source_Data!F9 -> Resident-Normal Citizen | G9: =Tax_Engine!G9 -> 0 | H9: =Tax_Engine!H9 -> 0 | I9: =Tax_Engine!I9 -> 0 | J9: =Tax_Engine!J9 -> 0 | K9: =ROUND(G9-H9+I9+J9,2) -> 0 | L9: =Tax_Engine!L9 -> 0 | M9: =Tax_Engine!M9 -> 0 | N9: =Tax_Engine!N9 -> 0 | O9: =Tax_Engine!O9 -> 0 | P9: =ROUND(L9-M9+N9+O9,2) -> 0 | Q9: =ROUND(P9-K9,2) -> 0
A10: =Source_Data!A10 -> 2020-21 | B10: =Source_Data!B10 -> 0 | C10: =Source_Data!C10 -> 0 | D10: =Source_Data!D10 -> 0 | E10: =Source_Data!E10 -> OLD | F10: =Source_Data!F10 -> Resident-Senior Citizen | G10: =Tax_Engine!G10 -> 0 | H10: =Tax_Engine!H10 -> 0 | I10: =Tax_Engine!I10 -> 0 | J10: =Tax_Engine!J10 -> 0 | K10: =ROUND(G10-H10+I10+J10,2) -> 0 | L10: =Tax_Engine!L10 -> 0 | M10: =Tax_Engine!M10 -> 0 | N10: =Tax_Engine!N10 -> 0 | O10: =Tax_Engine!O10 -> 0 | P10: =ROUND(L10-M10+N10+O10,2) -> 0 | Q10: =ROUND(P10-K10,2) -> 0
A11: =Source_Data!A11 -> 2021-22 | B11: =Source_Data!B11 -> 0 | C11: =Source_Data!C11 -> 0 | D11: =Source_Data!D11 -> 0 | E11: =Source_Data!E11 -> OLD | F11: =Source_Data!F11 -> Resident-Senior Citizen | G11: =Tax_Engine!G11 -> 0 | H11: =Tax_Engine!H11 -> 0 | I11: =Tax_Engine!I11 -> 0 | J11: =Tax_Engine!J11 -> 0 | K11: =ROUND(G11-H11+I11+J11,2) -> 0 | L11: =Tax_Engine!L11 -> 0 | M11: =Tax_Engine!M11 -> 0 | N11: =Tax_Engine!N11 -> 0 | O11: =Tax_Engine!O11 -> 0 | P11: =ROUND(L11-M11+N11+O11,2) -> 0 | Q11: =ROUND(P11-K11,2) -> 0
A12: =Source_Data!A12 -> 2022-23 | B12: =Source_Data!B12 -> 0 | C12: =Source_Data!C12 -> 0 | D12: =Source_Data!D12 -> 0 | E12: =Source_Data!E12 -> NEW | F12: =Source_Data!F12 -> Resident-Senior Citizen | G12: =Tax_Engine!G12 -> 0 | H12: =Tax_Engine!H12 -> 0 | I12: =Tax_Engine!I12 -> 0 | J12: =Tax_Engine!J12 -> 0 | K12: =ROUND(G12-H12+I12+J12,2) -> 0 | L12: =Tax_Engine!L12 -> 0 | M12: =Tax_Engine!M12 -> 0 | N12: =Tax_Engine!N12 -> 0 | O12: =Tax_Engine!O12 -> 0 | P12: =ROUND(L12-M12+N12+O12,2) -> 0 | Q12: =ROUND(P12-K12,2) -> 0
A13: =Source_Data!A13 -> 2023-24 | B13: =Source_Data!B13 -> 0 | C13: =Source_Data!C13 -> 0 | D13: =Source_Data!D13 -> 0 | E13: =Source_Data!E13 -> NEW | F13: =Source_Data!F13 -> Resident-Senior Citizen | G13: =Tax_Engine!G13 -> 0 | H13: =Tax_Engine!H13 -> 0 | I13: =Tax_Engine!I13 -> 0 | J13: =Tax_Engine!J13 -> 0 | K13: =ROUND(G13-H13+I13+J13,2) -> 0 | L13: =Tax_Engine!L13 -> 0 | M13: =Tax_Engine!M13 -> 0 | N13: =Tax_Engine!N13 -> 0 | O13: =Tax_Engine!O13 -> 0 | P13: =ROUND(L13-M13+N13+O13,2) -> 0 | Q13: =ROUND(P13-K13,2) -> 0
A14: =Source_Data!A14 -> 2024-25 | B14: =Source_Data!B14 -> 0 | C14: =Source_Data!C14 -> 0 | D14: =Source_Data!D14 -> 0 | E14: =Source_Data!E14 -> NEW | F14: =Source_Data!F14 -> Resident-Senior Citizen | G14: =Tax_Engine!G14 -> 0 | H14: =Tax_Engine!H14 -> 0 | I14: =Tax_Engine!I14 -> 0 | J14: =Tax_Engine!J14 -> 0 | K14: =ROUND(G14-H14+I14+J14,2) -> 0 | L14: =Tax_Engine!L14 -> 0 | M14: =Tax_Engine!M14 -> 0 | N14: =Tax_Engine!N14 -> 0 | O14: =Tax_Engine!O14 -> 0 | P14: =ROUND(L14-M14+N14+O14,2) -> 0 | Q14: =ROUND(P14-K14,2) -> 0
A15: =Source_Data!A15 -> 2025-26 | B15: =Source_Data!B15 -> 0 | C15: =Source_Data!C15 -> 0 | D15: =Source_Data!D15 -> 0 | E15: =Source_Data!E15 -> NEW | F15: =Source_Data!F15 -> Resident-Senior Citizen | G15: =Tax_Engine!G15 -> 0 | H15: =Tax_Engine!H15 -> 0 | I15: =Tax_Engine!I15 -> 0 | J15: =Tax_Engine!J15 -> 0 | K15: =ROUND(G15-H15+I15+J15,2) -> 0 | L15: =Tax_Engine!L15 -> 0 | M15: =Tax_Engine!M15 -> 0 | N15: =Tax_Engine!N15 -> 0 | O15: =Tax_Engine!O15 -> 0 | P15: =ROUND(L15-M15+N15+O15,2) -> 0 | Q15: =ROUND(P15-K15,2) -> 0
A19: Relief Summary :
A20: Receipt financial year | B20: =Source_Data!I4 -> 2025-26
A21: Assessment year | B21: =Source_Data!I5 -> 2026-27
A22: Additional tax in receipt year | B22: =Q15 -> 0
A23: Additional tax attributable to earlier years | B23: =SUM(Q4:Q14) -> 0
A24: Section 89(1) relief | B24: =MAX(0,B22-B23) -> 0
A25: Net tax after relief in receipt year | B25: =P15-B24 -> 0

Sheet Form_10E
A1: Form 10E - Linked Working for Section 89(1) Relief
A3: Name | B3: =Source_Data!I11 -> 0
A4: PAN | B4: =Source_Data!I12 -> 0
A5: Address | B5: =Source_Data!I13 -> 0
A6: Status | B6: =Source_Data!I14 -> RESIDENT - SR CITIZEN
A7: Previous year in which arrears received | B7: =Relief_Calculation!B20 -> 2025-26
A8: Assessment year | B8: =Relief_Calculation!B21 -> 2026-27
A9: Relief claimed u/s 89(1) | B9: =ROUND(Relief_Calculation!B24,0) -> 0
A12: Annexure I - Arrears or Advance Salary
A13: Financial Year | B13: Arrears | C13: Total income excluding arrears | D13: Total income including arrears | E13: Tax on excluding arrears | F13: Tax on including arrears | G13: Additional tax | H13: Regime
A14: =Relief_Calculation!A4 -> 2014-15 | B14: =Relief_Calculation!C4 -> 0 | C14: =Relief_Calculation!B4 -> 0 | D14: =Relief_Calculation!D4 -> 0 | E14: =Relief_Calculation!K4 -> 0 | F14: =Relief_Calculation!P4 -> 0 | G14: =Relief_Calculation!Q4 -> 0 | H14: OLD
A15: =Relief_Calculation!A5 -> 2015-16 | B15: =Relief_Calculation!C5 -> 0 | C15: =Relief_Calculation!B5 -> 0 | D15: =Relief_Calculation!D5 -> 0 | E15: =Relief_Calculation!K5 -> 0 | F15: =Relief_Calculation!P5 -> 0 | G15: =Relief_Calculation!Q5 -> 0 | H15: OLD
A16: =Relief_Calculation!A6 -> 2016-17 | B16: =Relief_Calculation!C6 -> 0 | C16: =Relief_Calculation!B6 -> 0 | D16: =Relief_Calculation!D6 -> 0 | E16: =Relief_Calculation!K6 -> 0 | F16: =Relief_Calculation!P6 -> 0 | G16: =Relief_Calculation!Q6 -> 0 | H16: OLD
A17: =Relief_Calculation!A7 -> 2017-18 | B17: =Relief_Calculation!C7 -> 0 | C17: =Relief_Calculation!B7 -> 0 | D17: =Relief_Calculation!D7 -> 0 | E17: =Relief_Calculation!K7 -> 0 | F17: =Relief_Calculation!P7 -> 0 | G17: =Relief_Calculation!Q7 -> 0 | H17: OLD
A18: =Relief_Calculation!A8 -> 2018-19 | B18: =Relief_Calculation!C8 -> 0 | C18: =Relief_Calculation!B8 -> 0 | D18: =Relief_Calculation!D8 -> 0 | E18: =Relief_Calculation!K8 -> 0 | F18: =Relief_Calculation!P8 -> 0 | G18: =Relief_Calculation!Q8 -> 0 | H18: OLD
A19: =Relief_Calculation!A9 -> 2019-20 | B19: =Relief_Calculation!C9 -> 0 | C19: =Relief_Calculation!B9 -> 0 | D19: =Relief_Calculation!D9 -> 0 | E19: =Relief_Calculation!K9 -> 0 | F19: =Relief_Calculation!P9 -> 0 | G19: =Relief_Calculation!Q9 -> 0 | H19: OLD
A20: =Relief_Calculation!A10 -> 2020-21 | B20: =Relief_Calculation!C10 -> 0 | C20: =Relief_Calculation!B10 -> 0 | D20: =Relief_Calculation!D10 -> 0 | E20: =Relief_Calculation!K10 -> 0 | F20: =Relief_Calculation!P10 -> 0 | G20: =Relief_Calculation!Q10 -> 0 | H20: =Relief_Calculation!E10 -> OLD
A21: =Relief_Calculation!A11 -> 2021-22 | B21: =Relief_Calculation!C11 -> 0 | C21: =Relief_Calculation!B11 -> 0 | D21: =Relief_Calculation!D11 -> 0 | E21: =Relief_Calculation!K11 -> 0 | F21: =Relief_Calculation!P11 -> 0 | G21: =Relief_Calculation!Q11 -> 0 | H21: =Relief_Calculation!E11 -> OLD
A22: =Relief_Calculation!A12 -> 2022-23 | B22: =Relief_Calculation!C12 -> 0 | C22: =Relief_Calculation!B12 -> 0 | D22: =Relief_Calculation!D12 -> 0 | E22: =Relief_Calculation!K12 -> 0 | F22: =Relief_Calculation!P12 -> 0 | G22: =Relief_Calculation!Q12 -> 0 | H22: =Relief_Calculation!E12 -> NEW
A23: =Relief_Calculation!A13 -> 2023-24 | B23: =Relief_Calculation!C13 -> 0 | C23: =Relief_Calculation!B13 -> 0 | D23: =Relief_Calculation!D13 -> 0 | E23: =Relief_Calculation!K13 -> 0 | F23: =Relief_Calculation!P13 -> 0 | G23: =Relief_Calculation!Q13 -> 0 | H23: =Relief_Calculation!E13 -> NEW
A24: =Relief_Calculation!A14 -> 2024-25 | B24: =Relief_Calculation!C14 -> 0 | C24: =Relief_Calculation!B14 -> 0 | D24: =Relief_Calculation!D14 -> 0 | E24: =Relief_Calculation!K14 -> 0 | F24: =Relief_Calculation!P14 -> 0 | G24: =Relief_Calculation!Q14 -> 0 | H24: =Relief_Calculation!E14 -> NEW
A25: =Relief_Calculation!A15 -> 2025-26 | B25: =Relief_Calculation!C15 -> 0 | C25: =Relief_Calculation!B15 -> 0 | D25: =Relief_Calculation!D15 -> 0 | E25: =Relief_Calculation!K15 -> 0 | F25: =Relief_Calculation!P15 -> 0 | G25: =Relief_Calculation!Q15 -> 0 | H25: =Relief_Calculation!E15 -> NEW
A28: Computation of relief claimed in Form 10E
A29: Tax on income including arrears in year of receipt | B29: =Relief_Calculation!P15 -> 0
A30: Tax on income excluding arrears in year of receipt | B30: =Relief_Calculation!K15 -> 0
A31: Extra tax payable in year of receipt | B31: =Relief_Calculation!B22 -> 0
A32: Aggregate extra tax for earlier years | B32: =Relief_Calculation!B23 -> 0
A33: Relief under section 89(1) | B33: =Relief_Calculation!B24 -> 0

Sheet Checks
A1: Workbook Checks
A3: Check | B3: Formula | C3: Expected / meaning | D3: Status
A4: Receipt-year arrears equals total earlier arrears | B4: =Source_Data!C15-SUM(Source_Data!C4:C14) -> 0 | C4: OK | D4: =IF(B4=0,"OK","Check") -> OK
A5: Taxable after = before + arrears for every row | B5: =SUMPRODUCT(--(Source_Data!D4:D15<>Source_Data!B4:B15+Source_Data!C4:C15)) -> 0 | C5: OK | D5: =IF(B5=0,"OK","Check") -> OK
A6: Form relief equals calculation relief | B6: =Form_10E!B33-Relief_Calculation!B24 -> 0 | C6: OK | D6: =IF(ABS(B6)<1,"OK","Check") -> OK
A7: Relief is not negative | B7: =Relief_Calculation!B24 -> 0 | C7: OK | D7: =IF(B7>=0,"OK","Check") -> OK
A8: Receipt year used | B8: =Source_Data!I4 -> 2025-26
A9: Assessment year used | B9: =Source_Data!I5 -> 2026-27
A10: Tax regime dropdown present on Source_Data | B10: 0 | C10: OK | D10: OK
A11: Category dropdown present on Source_Data | B11: 0 | C11: OK | D11: OK
A12: Comparison selected tax equals relief calculation | B12: =SUMPRODUCT(--(ROUND(Tax_Regime_Comparison!G4:G15,0)<>ROUND(Relief_Calculation!K4:K15,0)))+SUMPRODUCT(--(ROUND(Tax_Regime_Comparison!H4:H15,0)<>ROUND(Relief_Calculation!P4:P15,0))) -> 0 | C12: OK | D12: =IF(B12=0,"OK","Check") -> OK
A13: FY 2014-15 added | B13: 2014-15 | C13: OK | D13: OK
A14: FY 2015-16 added | B14: 2015-16 | C14: OK | D14: OK

Sheet Tax_Rate_Assumptions
A1: Tax Rate Assumptions
A2: Rates are prefilled for resident individuals based on common slab structures. Review before filing if any surcharge, marginal relief, rebate, or special-rate income rule applies.
A4: Financial Year | B4: Regime | C4: Status | D4: Lower limit | E4: Upper limit | F4: Rate | H4: Named ranges used by formulas
A5: 2016-17 | B5: OLD | C5: Resident-Normal Citizen | D5: 0 | E5: 250000 | F5: 0 | H5: Slabs | I5: $A$5:$F$95 | J5: Tax slab brackets
A6: 2016-17 | B6: OLD | C6: Resident-Normal Citizen | D6: 250000 | E6: 500000 | F6: 0.1 | H6: Rebates | I6: $A$99:$E$108 | J6: Section 87A rebate inputs
A7: 2016-17 | B7: OLD | C7: Resident-Normal Citizen | D7: 500000 | E7: 1000000 | F7: 0.2 | H7: Surcharge | I7: $A$112:$F$180 | J7: Surcharge rates
A8: 2016-17 | B8: OLD | C8: Resident-Normal Citizen | D8: 1000000 | E8: 999999999 | F8: 0.3 | H8: Cess | I8: $A$184:$B$193 | J8: Cess rates
A9: 2016-17 | B9: OLD | C9: Resident-Senior Citizen | D9: 0 | E9: 300000 | F9: 0 | H9: Surcharge floor | I9: 5000000 | J9: Used for marginal relief
A10: 2016-17 | B10: OLD | C10: Resident-Senior Citizen | D10: 300000 | E10: 500000 | F10: 0.1 | H10: Formula style | I10: Editable assumptions | J10: No tax figures are hardcoded in calculation sheets
A11: 2016-17 | B11: OLD | C11: Resident-Senior Citizen | D11: 500000 | E11: 1000000 | F11: 0.2 | H11: Status match | I11: All/status text | J11: Specific status overrides All where supplied
A12: 2016-17 | B12: OLD | C12: Resident-Senior Citizen | D12: 1000000 | E12: 999999999 | F12: 0.3
A13: 2017-18 | B13: OLD | C13: Resident-Normal Citizen | D13: 0 | E13: 250000 | F13: 0
A14: 2017-18 | B14: OLD | C14: Resident-Normal Citizen | D14: 250000 | E14: 500000 | F14: 0.05
A15: 2017-18 | B15: OLD | C15: Resident-Normal Citizen | D15: 500000 | E15: 1000000 | F15: 0.2
A16: 2017-18 | B16: OLD | C16: Resident-Normal Citizen | D16: 1000000 | E16: 999999999 | F16: 0.3
A17: 2017-18 | B17: OLD | C17: Resident-Senior Citizen | D17: 0 | E17: 300000 | F17: 0
A18: 2017-18 | B18: OLD | C18: Resident-Senior Citizen | D18: 300000 | E18: 500000 | F18: 0.05
A19: 2017-18 | B19: OLD | C19: Resident-Senior Citizen | D19: 500000 | E19: 1000000 | F19: 0.2
A20: 2017-18 | B20: OLD | C20: Resident-Senior Citizen | D20: 1000000 | E20: 999999999 | F20: 0.3
A21: 2018-19 | B21: OLD | C21: Resident-Normal Citizen | D21: 0 | E21: 250000 | F21: 0
A22: 2018-19 | B22: OLD | C22: Resident-Normal Citizen | D22: 250000 | E22: 500000 | F22: 0.05
A23: 2018-19 | B23: OLD | C23: Resident-Normal Citizen | D23: 500000 | E23: 1000000 | F23: 0.2
... A79: 2025-26 | B79: NEW | C79: All | D79: 2400000 | E79: 999999999 | F79: 0.3
A98: Financial Year | B98: Regime | C98: Status | D98: Rebate threshold | E98: Maximum rebate
A99: 2016-17 | B99: OLD | C99: All | D99: 500000 | E99: 5000
A100: 2017-18 | B100: OLD | C100: All | D100: 350000 | E100: 2500
A101: 2018-19 | B101: OLD | C101: All | D101: 350000 | E101: 2500
A102: 2019-20 | B102: OLD | C102: All | D102: 500000 | E102: 12500
A103: 2020-21 | B103: OLD | C103: All | D103: 500000 | E103: 12500
A104: 2021-22 | B104: OLD | C104: All | D104: 500000 | E104: 12500
A105: 2022-23 | B105: OLD | C105: All | D105: 500000 | E105: 12500
A106: 2023-24 | B106: NEW | C106: All | D106: 700000 | E106: 25000
A107: 2024-25 | B107: NEW | C107: All | D107: 700000 | E107: 25000
A108: 2025-26 | B108: NEW | C108: All | D108: 1200000 | E108: 60000
A111: Financial Year | B111: Regime | C111: Status | D111: Lower threshold | E111: Upper threshold | F111: Surcharge rate
A112: 2016-17 | B112: OLD | C112: All | D112: 10000000 | E112: 999999999 | F112: 0.15
A113: 2017-18 | B113: OLD | C113: All | D113: 5000000 | E113: 10000000 | F113: 0.1
A114: 2017-18 | B114: OLD | C114: All | D114: 10000000 | E114: 999999999 | F114: 0.15
A115: 2018-19 | B115: OLD | C115: All | D115: 5000000 | E115: 10000000 | F115: 0.1
A116: 2018-19 | B116: OLD | C116: All | D116: 10000000 | E116: 999999999 | F116: 0.15
A117: 2019-20 | B117: OLD | C117: All | D117: 5000000 | E117: 10000000 | F117: 0.1
A118: 2019-20 | B118: OLD | C118: All | D118: 10000000 | E118: 20000000 | F118: 0.15
A119: 2019-20 | B119: OLD | C119: All | D119: 20000000 | E119: 50000000 | F119: 0.25
A120: 2019-20 | B120: OLD | C120: All | D120: 50000000 | E120: 999999999 | F120: 0.37
A121: 2020-21 | B121: OLD | C121: All | D121: 5000000 | E121: 10000000 | F121: 0.1
A122: 2020-21 | B122: OLD | C122: All | D122: 10000000 | E122: 20000000 | F122: 0.15
A123: 2020-21 | B123: OLD | C123: All | D123: 20000000 | E123: 50000000 | F123: 0.25
... A165: 2025-26 | B165: NEW | C165: All | D165: 20000000 | E165: 999999999 | F165: 0.25
A183: Financial Year | B183: Cess rate
A184: 2016-17 | B184: 0.03
A185: 2017-18 | B185: 0.03
A186: 2018-19 | B186: 0.04
A187: 2019-20 | B187: 0.04
A188: 2020-21 | B188: 0.04
A189: 2021-22 | B189: 0.04
A190: 2022-23 | B190: 0.04
A191: 2023-24 | B191: 0.04
A192: 2024-25 | B192: 0.04
A193: 2025-26 | B193: 0.04

Sheet Tax_Engine
A1: Tax Engine - Stepwise Old/New Regime Computation
A3: Source row | B3: Financial Year | C3: Regime | D3: Category | E3: Income before | F3: Income after | G3: Basic before | H3: Rebate before | I3: Surcharge before | J3: Cess before | K3: Tax before | L3: Basic after | M3: Rebate after | N3: Surcharge after | O3: Cess after | P3: Tax after | Q3: Extra tax
A4: =4 -> 4 | B4: =Source_Data!A4 -> 2014-15 | C4: =Source_Data!E4 -> OLD | D4: =Source_Data!F4 -> Resident-Normal Citizen | E4: =Source_Data!B4 -> 0 | F4: =Source_Data!D4 -> 0 | G4: =ROUND(IF(C4="OLD",MAX(0,MIN(E4,500000)-IF(D4="Resident-Senior Citizen",300000,250000))*IF(B4="2016-17",10%,10%)+MAX(0,MIN(E4,1000000)-500000)*20%+MAX(0,E4-1000000)*30%,IF(OR(B4="2020-21",B4="2021-22",B4="2022-23"),MAX(0,MIN(E4,500000)-250000)*5%+MAX(0,MIN(E4,750000)-500000)*10%+MAX(0,MIN(E4,1000000)-750000)*15%+MAX(0,MIN(E4,1250000)-1000000)*20%+MAX(0,MIN(E4,1500000)-1250000)*25%+MAX(0,E4-1500000)*30%,IF(B4="2023-24",MAX(0,MIN(E4,600000)-300000)*5%+MAX(0,MIN(E4,900000)-600000)*10%+MAX(0,MIN(E4,1200000)-900000)*15%+MAX(0,MIN(E4,1500000)-1200000)*20%+MAX(0,E4-1500000)*30%,IF(B4="2024-25",MAX(0,MIN(E4,700000)-300000)*5%+MAX(0,MIN(E4,1000000)-700000)*10%+MAX(0,MIN(E4,1200000)-1000000)*15%+MAX(0,MIN(E4,1500000)-1200000)*20%+MAX(0,E4-1500000)*30%,IF(B4="2025-26",MAX(0,MIN(E4,800000)-400000)*5%+MAX(0,MIN(E4,1200000)-800000)*10%+MAX(0,MIN(E4,1600000)-1200000)*15%+MAX(0,MIN(E4,2000000)-1600000)*20%+MAX(0,MIN(E4,2400000)-2000000)*25%+MAX(0,E4-2400000)*30%,0))))),2) -> 0 | H4: =ROUND(MAX(IF(C4="OLD",IF(E4<=IF(OR(B4="2014-15",B4="2015-16",B4="2016-17"),500000,IF(OR(B4="2017-18",B4="2018-19"),350000,500000)),MIN(G4,IF(OR(B4="2014-15",B4="2015-16"),2000,IF(B4="2016-17",5000,IF(OR(B4="2017-18",B4="2018-19"),2500,12500)))),0),IF(E4<=IF(OR(B4="2023-24",B4="2024-25"),700000,IF(B4="2025-26",1200000,500000)),MIN(G4,IF(OR(B4="2023-24",B4="2024-25"),25000,IF(B4="2025-26",60000,12500))),0)),IF(AND(C4="NEW",B4="2025-26",E4>1200000),MAX(0,G4-(E4-1200000)),0)),2) -> 0 | I4: =ROUND(IF(C4="OLD",IF(OR(B4="2014-15",B4="2016-17"),IF(E4<=10000000,0,MIN((G4-H4)*15%,MAX(0,(G4-H4)*0%+(E4-10000000)*(70%-30%*0%)))),IF(B4="2015-16",IF(E4<=10000000,0,MIN((G4-H4)*12%,MAX(0,(G4-H4)*0%+(E4-10000000)*(70%-30%*0%)))),IF(OR(B4="2017-18",B4="2018-19"),IF(E4<=5000000,0,IF(E4<=10000000,MIN((G4-H4)*10%,MAX(0,(G4-H4)*0%+(E4-5000000)*(70%-30%*0%))),MIN((G4-H4)*15%,MAX(0,(G4-H4)*10%+(E4-10000000)*(70%-30%*10%))))),IF(E4<=5000000,0,IF(E4<=10000000,MIN((G4-H4)*10%,MAX(0,(G4-H4)*0%+(E4-5000000)*(70%-30%*0%))),IF(E4<=20000000,MIN((G4-H4)*15%,MAX(0,(G4-H4)*10%+(E4-10000000)*(70%-30%*10%))),IF(E4<=50000000,MIN((G4-H4)*25%,MAX(0,(G4-H4)*15%+(E4-20000000)*(70%-30%*15%))),MIN((G4-H4)*37%,MAX(0,(G4-H4)*25%+(E4-50000000)*(70%-30%*25%)))))))))),IF(OR(B4="2023-24",B4="2024-25",B4="2025-26"),IF(E4<=5000000,0,IF(E4<=10000000,MIN((G4-H4)*10%,MAX(0,(G4-H4)*0%+(E4-5000000)*(70%-30%*0%))),IF(E4<=20000000,MIN((G4-H4)*15%,MAX(0,(G4-H4)*10%+(E4-10000000)*(70%-30%*10%))),MIN((G4-H4)*25%,MAX(0,(G4-H4)*15%+(E4-20000000)*(70%-30%*15%)))))),IF(E4<=5000000,0,IF(E4<=10000000,MIN((G4-H4)*10%,MAX(0,(G4-H4)*0%+(E4-5000000)*(70%-30%*0%))),IF(E4<=20000000,MIN((G4-H4)*15%,MAX(0,(G4-H4)*10%+(E4-10000000)*(70%-30%*10%))),IF(E4<=50000000,MIN((G4-H4)*25%,MAX(0,(G4-H4)*15%+(E4-20000000)*(70%-30%*15%))),MIN((G4-H4)*37%,MAX(0,(G4-H4)*25%+(E4-50000000)*(70%-30%*25%))))))))),2) -> 0 | J4: =ROUND((G4-H4+I4)*IF(OR(B4="2014-15",B4="2015-16",B4="2016-17",B4="2017-18"),3%,4%),2) -> 0 | K4: =ROUND(G4-H4+I4+J4,2) -> 0 | L4: =ROUND(IF(C4="OLD",MAX(0,MIN(F4,500000)-IF(D4="Resident-Senior Citizen",300000,250000))*IF(B4="2016-17",10%,10%)+MAX(0,MIN(F4,1000000)-500000)*20%+MAX(0,F4-1000000)*30%,IF(OR(B4="2020-21",B4="2021-22",B4="2022-23"),MAX(0,MIN(F4,500000)-250000)*5%+MAX(0,MIN(F4,750000)-500000)*10%+MAX(0,MIN(F4,1000000)-750000)*15%+MAX(0,MIN(F4,1250000)-1000000)*20%+MAX(0,MIN(F4,1500000)-1250000)*25%+MAX(0,F4-1500000)*30%,IF(B4="2023-24",MAX(0,MIN(F4,600000)-300000)*5%+MAX(0,MIN(F4,900000)-600000)*10%+MAX(0,MIN(F4,1200000)-900000)*15%+MAX(0,MIN(F4,1500000)-1200000)*20%+MAX(0,F4-1500000)*30%,IF(B4="2024-25",MAX(0,MIN(F4,700000)-300000)*5%+MAX(0,MIN(F4,1000000)-700000)*10%+MAX(0,MIN(F4,1200000)-1000000)*15%+MAX(0,MIN(F4,1500000)-1200000)*20%+MAX(0,F4-1500000)*30%,IF(B4="2025-26",MAX(0,MIN(F4,800000)-400000)*5%+MAX(0,MIN(F4,1200000)-800000)*10%+MAX(0,MIN(F4,1600000)-1200000)*15%+MAX(0,MIN(F4,2000000)-1600000)*20%+MAX(0,MIN(F4,2400000)-2000000)*25%+MAX(0,F4-2400000)*30%,0))))),2) -> 0 | M4: =ROUND(MAX(IF(C4="OLD",IF(F4<=IF(OR(B4="2014-15",B4="2015-16",B4="2016-17"),500000,IF(OR(B4="2017-18",B4="2018-19"),350000,500000)),MIN(L4,IF(OR(B4="2014-15",B4="2015-16"),2000,IF(B4="2016-17",5000,IF(OR(B4="2017-18",B4="2018-19"),2500,12500)))),0),IF(F4<=IF(OR(B4="2023-24",B4="2024-25"),700000,IF(B4="2025-26",1200000,500000)),MIN(L4,IF(OR(B4="2023-24",B4="2024-25"),25000,IF(B4="2025-26",60000,12500))),0)),IF(AND(C4="NEW",B4="2025-26",F4>1200000),MAX(0,L4-(F4-1200000)),0)),2) -> 0 | N4: =ROUND(IF(C4="OLD",IF(OR(B4="2014-15",B4="2016-17"),IF(F4<=10000000,0,MIN((L4-M4)*15%,MAX(0,(L4-M4)*0%+(F4-10000000)*(70%-30%*0%)))),IF(B4="2015-16",IF(F4<=10000000,0,MIN((L4-M4)*12%,MAX(0,(L4-M4)*0%+(F4-10000000)*(70%-30%*0%)))),IF(OR(B4="2017-18",B4="2018-19"),IF(F4<=5000000,0,IF(F4<=10000000,MIN((L4-M4)*10%,MAX(0,(L4-M4)*0%+(F4-5000000)*(70%-30%*0%))),MIN((L4-M4)*15%,MAX(0,(L4-M4)*10%+(F4-10000000)*(70%-30%*10%))))),IF(F4<=5000000,0,IF(F4<=10000000,MIN((L4-M4)*10%,MAX(0,(L4-M4)*0%+(F4-5000000)*(70%-30%*0%))),IF(F4<=20000000,MIN((L4-M4)*15%,MAX(0,(L4-M4)*10%+(F4-10000000)*(70%-30%*10%))),IF(F4<=50000000,MIN((L4-M4)*25%,MAX(0,(L4-M4)*15%+(F4-20000000)*(70%-30%*15%))),MIN((L4-M4)*37%,MAX(0,(L4-M4)*25%+(F4-50000000)*(70%-30%*25%)))))))))),IF(OR(B4="2023-24",B4="2024-25",B4="2025-26"),IF(F4<=5000000,0,IF(F4<=10000000,MIN((L4-M4)*10%,MAX(0,(L4-M4)*0%+(F4-5000000)*(70%-30%*0%))),IF(F4<=20000000,MIN((L4-M4)*15%,MAX(0,(L4-M4)*10%+(F4-10000000)*(70%-30%*10%))),MIN((L4-M4)*25%,MAX(0,(L4-M4)*15%+(F4-20000000)*(70%-30%*15%)))))),IF(F4<=5000000,0,IF(F4<=10000000,MIN((L4-M4)*10%,MAX(0,(L4-M4)*0%+(F4-5000000)*(70%-30%*0%))),IF(F4<=20000000,MIN((L4-M4)*15%,MAX(0,(L4-M4)*10%+(F4-10000000)*(70%-30%*10%))),IF(F4<=50000000,MIN((L4-M4)*25%,MAX(0,(L4-M4)*15%+(F4-20000000)*(70%-30%*15%))),MIN((L4-M4)*37%,MAX(0,(L4-M4)*25%+(F4-50000000)*(70%-30%*25%))))))))),2) -> 0 | O4: =ROUND((L4-M4+N4)*IF(OR(B4="2014-15",B4="2015-16",B4="2016-17",B4="2017-18"),3%,4%),2) -> 0 | P4: =ROUND(L4-M4+N4+O4,2) -> 0 | Q4: =ROUND(P4-K4,2) -> 0
A5: =5 -> 5 | B5: =Source_Data!A5 -> 2015-16 | C5: =Source_Data!E5 -> OLD | D5: =Source_Data!F5 -> Resident-Normal Citizen | E5: =Source_Data!B5 -> 0 | F5: =Source_Data!D5 -> 0 | G5: =ROUND(IF(C5="OLD",MAX(0,MIN(E5,500000)-IF(D5="Resident-Senior Citizen",300000,250000))*IF(B5="2016-17",10%,10%)+MAX(0,MIN(E5,1000000)-500000)*20%+MAX(0,E5-1000000)*30%,IF(OR(B5="2020-21",B5="2021-22",B5="2022-23"),MAX(0,MIN(E5,500000)-250000)*5%+MAX(0,MIN(E5,750000)-500000)*10%+MAX(0,MIN(E5,1000000)-750000)*15%+MAX(0,MIN(E5,1250000)-1000000)*20%+MAX(0,MIN(E5,1500000)-1250000)*25%+MAX(0,E5-1500000)*30%,IF(B5="2023-24",MAX(0,MIN(E5,600000)-300000)*5%+MAX(0,MIN(E5,900000)-600000)*10%+MAX(0,MIN(E5,1200000)-900000)*15%+MAX(0,MIN(E5,1500000)-1200000)*20%+MAX(0,E5-1500000)*30%,IF(B5="2024-25",MAX(0,MIN(E5,700000)-300000)*5%+MAX(0,MIN(E5,1000000)-700000)*10%+MAX(0,MIN(E5,1200000)-1000000)*15%+MAX(0,MIN(E5,1500000)-1200000)*20%+MAX(0,E5-1500000)*30%,IF(B5="2025-26",MAX(0,MIN(E5,800000)-400000)*5%+MAX(0,MIN(E5,1200000)-800000)*10%+MAX(0,MIN(E5,1600000)-1200000)*15%+MAX(0,MIN(E5,2000000)-1600000)*20%+MAX(0,MIN(E5,2400000)-2000000)*25%+MAX(0,E5-2400000)*30%,0))))),2) -> 0 | H5: =ROUND(MAX(IF(C5="OLD",IF(E5<=IF(OR(B5="2014-15",B5="2015-16",B5="2016-17"),500000,IF(OR(B5="2017-18",B5="2018-19"),350000,500000)),MIN(G5,IF(OR(B5="2014-15",B5="2015-16"),2000,IF(B5="2016-17",5000,IF(OR(B5="2017-18",B5="2018-19"),2500,12500)))),0),IF(E5<=IF(OR(B5="2023-24",B5="2024-25"),700000,IF(B5="2025-26",1200000,500000)),MIN(G5,IF(OR(B5="2023-24",B5="2024-25"),25000,IF(B5="2025-26",60000,12500))),0)),IF(AND(C5="NEW",B5="2025-26",E5>1200000),MAX(0,G5-(E5-1200000)),0)),2) -> 0 | I5: =ROUND(IF(C5="OLD",IF(OR(B5="2014-15",B5="2016-17"),IF(E5<=10000000,0,MIN((G5-H5)*15%,MAX(0,(G5-H5)*0%+(E5-10000000)*(70%-30%*0%)))),IF(B5="2015-16",IF(E5<=10000000,0,MIN((G5-H5)*12%,MAX(0,(G5-H5)*0%+(E5-10000000)*(70%-30%*0%)))),IF(OR(B5="2017-18",B5="2018-19"),IF(E5<=5000000,0,IF(E5<=10000000,MIN((G5-H5)*10%,MAX(0,(G5-H5)*0%+(E5-5000000)*(70%-30%*0%))),MIN((G5-H5)*15%,MAX(0,(G5-H5)*10%+(E5-10000000)*(70%-30%*10%))))),IF(E5<=5000000,0,IF(E5<=10000000,MIN((G5-H5)*10%,MAX(0,(G5-H5)*0%+(E5-5000000)*(70%-30%*0%))),IF(E5<=20000000,MIN((G5-H5)*15%,MAX(0,(G5-H5)*10%+(E5-10000000)*(70%-30%*10%))),IF(E5<=50000000,MIN((G5-H5)*25%,MAX(0,(G5-H5)*15%+(E5-20000000)*(70%-30%*15%))),MIN((G5-H5)*37%,MAX(0,(G5-H5)*25%+(E5-50000000)*(70%-30%*25%)))))))))),IF(OR(B5="2023-24",B5="2024-25",B5="2025-26"),IF(E5<=5000000,0,IF(E5<=10000000,MIN((G5-H5)*10%,MAX(0,(G5-H5)*0%+(E5-5000000)*(70%-30%*0%))),IF(E5<=20000000,MIN((G5-H5)*15%,MAX(0,(G5-H5)*10%+(E5-10000000)*(70%-30%*10%))),MIN((G5-H5)*25%,MAX(0,(G5-H5)*15%+(E5-20000000)*(70%-30%*15%)))))),IF(E5<=5000000,0,IF(E5<=10000000,MIN((G5-H5)*10%,MAX(0,(G5-H5)*0%+(E5-5000000)*(70%-30%*0%))),IF(E5<=20000000,MIN((G5-H5)*15%,MAX(0,(G5-H5)*10%+(E5-10000000)*(70%-30%*10%))),IF(E5<=50000000,MIN((G5-H5)*25%,MAX(0,(G5-H5)*15%+(E5-20000000)*(70%-30%*15%))),MIN((G5-H5)*37%,MAX(0,(G5-H5)*25%+(E5-50000000)*(70%-30%*25%))))))))),2) -> 0 | J5: =ROUND((G5-H5+I5)*IF(OR(B5="2014-15",B5="2015-16",B5="2016-17",B5="2017-18"),3%,4%),2) -> 0 | K5: =ROUND(G5-H5+I5+J5,2) -> 0 | L5: =ROUND(IF(C5="OLD",MAX(0,MIN(F5,500000)-IF(D5="Resident-Senior Citizen",300000,250000))*IF(B5="2016-17",10%,10%)+MAX(0,MIN(F5,1000000)-500000)*20%+MAX(0,F5-1000000)*30%,IF(OR(B5="2020-21",B5="2021-22",B5="2022-23"),MAX(0,MIN(F5,500000)-250000)*5%+MAX(0,MIN(F5,750000)-500000)*10%+MAX(0,MIN(F5,1000000)-750000)*15%+MAX(0,MIN(F5,1250000)-1000000)*20%+MAX(0,MIN(F5,1500000)-1250000)*25%+MAX(0,F5-1500000)*30%,IF(B5="2023-24",MAX(0,MIN(F5,600000)-300000)*5%+MAX(0,MIN(F5,900000)-600000)*10%+MAX(0,MIN(F5,1200000)-900000)*15%+MAX(0,MIN(F5,1500000)-1200000)*20%+MAX(0,F5-1500000)*30%,IF(B5="2024-25",MAX(0,MIN(F5,700000)-300000)*5%+MAX(0,MIN(F5,1000000)-700000)*10%+MAX(0,MIN(F5,1200000)-1000000)*15%+MAX(0,MIN(F5,1500000)-1200000)*20%+MAX(0,F5-1500000)*30%,IF(B5="2025-26",MAX(0,MIN(F5,800000)-400000)*5%+MAX(0,MIN(F5,1200000)-800000)*10%+MAX(0,MIN(F5,1600000)-1200000)*15%+MAX(0,MIN(F5,2000000)-1600000)*20%+MAX(0,MIN(F5,2400000)-2000000)*25%+MAX(0,F5-2400000)*30%,0))))),2) -> 0 | M5: =ROUND(MAX(IF(C5="OLD",IF(F5<=IF(OR(B5="2014-15",B5="2015-16",B5="2016-17"),500000,IF(OR(B5="2017-18",B5="2018-19"),350000,500000)),MIN(L5,IF(OR(B5="2014-15",B5="2015-16"),2000,IF(B5="2016-17",5000,IF(OR(B5="2017-18",B5="2018-19"),2500,12500)))),0),IF(F5<=IF(OR(B5="2023-24",B5="2024-25"),700000,IF(B5="2025-26",1200000,500000)),MIN(L5,IF(OR(B5="2023-24",B5="2024-25"),25000,IF(B5="2025-26",60000,12500))),0)),IF(AND(C5="NEW",B5="2025-26",F5>1200000),MAX(0,L5-(F5-1200000)),0)),2) -> 0 | N5: =ROUND(IF(C5="OLD",IF(OR(B5="2014-15",B5="2016-17"),IF(F5<=10000000,0,MIN((L5-M5)*15%,MAX(0,(L5-M5)*0%+(F5-10000000)*(70%-30%*0%)))),IF(B5="2015-16",IF(F5<=10000000,0,MIN((L5-M5)*12%,MAX(0,(L5-M5)*0%+(F5-10000000)*(70%-30%*0%)))),IF(OR(B5="2017-18",B5="2018-19"),IF(F5<=5000000,0,IF(F5<=10000000,MIN((L5-M5)*10%,MAX(0,(L5-M5)*0%+(F5-5000000)*(70%-30%*0%))),MIN((L5-M5)*15%,MAX(0,(L5-M5)*10%+(F5-10000000)*(70%-30%*10%))))),IF(F5<=5000000,0,IF(F5<=10000000,MIN((L5-M5)*10%,MAX(0,(L5-M5)*0%+(F5-5000000)*(70%-30%*0%))),IF(F5<=20000000,MIN((L5-M5)*15%,MAX(0,(L5-M5)*10%+(F5-10000000)*(70%-30%*10%))),IF(F5<=50000000,MIN((L5-M5)*25%,MAX(0,(L5-M5)*15%+(F5-20000000)*(70%-30%*15%))),MIN((L5-M5)*37%,MAX(0,(L5-M5)*25%+(F5-50000000)*(70%-30%*25%)))))))))),IF(OR(B5="2023-24",B5="2024-25",B5="2025-26"),IF(F5<=5000000,0,IF(F5<=10000000,MIN((L5-M5)*10%,MAX(0,(L5-M5)*0%+(F5-5000000)*(70%-30%*0%))),IF(F5<=20000000,MIN((L5-M5)*15%,MAX(0,(L5-M5)*10%+(F5-10000000)*(70%-30%*10%))),MIN((L5-M5)*25%,MAX(0,(L5-M5)*15%+(F5-20000000)*(70%-30%*15%)))))),IF(F5<=5000000,0,IF(F5<=10000000,MIN((L5-M5)*10%,MAX(0,(L5-M5)*0%+(F5-5000000)*(70%-30%*0%))),IF(F5<=20000000,MIN((L5-M5)*15%,MAX(0,(L5-M5)*10%+(F5-10000000)*(70%-30%*10%))),IF(F5<=50000000,MIN((L5-M5)*25%,MAX(0,(L5-M5)*15%+(F5-20000000)*(70%-30%*15%))),MIN((L5-M5)*37%,MAX(0,(L5-M5)*25%+(F5-50000000)*(70%-30%*25%))))))))),2) -> 0 | O5: =ROUND((L5-M5+N5)*IF(OR(B5="2014-15",B5="2015-16",B5="2016-17",B5="2017-18"),3%,4%),2) -> 0 | P5: =ROUND(L5-M5+N5+O5,2) -> 0 | Q5: =ROUND(P5-K5,2) -> 0
A6: =6 -> 6 | B6: =Source_Data!A6 -> 2016-17 | C6: =Source_Data!E6 -> OLD | D6: =Source_Data!F6 -> Resident-Senior Citizen | E6: =Source_Data!B6 -> 0 | F6: =Source_Data!D6 -> 0 | G6: =ROUND(IF(C6="OLD",MAX(0,MIN(E6,500000)-IF(D6="Resident-Senior Citizen",300000,250000))*IF(B6="2016-17",10%,5%)+MAX(0,MIN(E6,1000000)-500000)*20%+MAX(0,E6-1000000)*30%,IF(OR(B6="2020-21",B6="2021-22",B6="2022-23"),MAX(0,MIN(E6,500000)-250000)*5%+MAX(0,MIN(E6,750000)-500000)*10%+MAX(0,MIN(E6,1000000)-750000)*15%+MAX(0,MIN(E6,1250000)-1000000)*20%+MAX(0,MIN(E6,1500000)-1250000)*25%+MAX(0,E6-1500000)*30%,IF(B6="2023-24",MAX(0,MIN(E6,600000)-300000)*5%+MAX(0,MIN(E6,900000)-600000)*10%+MAX(0,MIN(E6,1200000)-900000)*15%+MAX(0,MIN(E6,1500000)-1200000)*20%+MAX(0,E6-1500000)*30%,IF(B6="2024-25",MAX(0,MIN(E6,700000)-300000)*5%+MAX(0,MIN(E6,1000000)-700000)*10%+MAX(0,MIN(E6,1200000)-1000000)*15%+MAX(0,MIN(E6,1500000)-1200000)*20%+MAX(0,E6-1500000)*30%,IF(B6="2025-26",MAX(0,MIN(E6,800000)-400000)*5%+MAX(0,MIN(E6,1200000)-800000)*10%+MAX(0,MIN(E6,1600000)-1200000)*15%+MAX(0,MIN(E6,2000000)-1600000)*20%+MAX(0,MIN(E6,2400000)-2000000)*25%+MAX(0,E6-2400000)*30%,0))))),2) -> 0 | H6: =ROUND(MAX(IF(C6="OLD",IF(E6<=IF(OR(B6="2014-15",B6="2015-16",B6="2016-17"),500000,IF(OR(B6="2017-18",B6="2018-19"),350000,500000)),MIN(G6,IF(OR(B6="2014-15",B6="2015-16"),2000,IF(B6="2016-17",5000,IF(OR(B6="2017-18",B6="2018-19"),2500,12500)))),0),IF(E6<=IF(OR(B6="2023-24",B6="2024-25"),700000,IF(B6="2025-26",1200000,500000)),MIN(G6,IF(OR(B6="2023-24",B6="2024-25"),25000,IF(B6="2025-26",60000,12500))),0)),IF(AND(C6="NEW",B6="2025-26",E6>1200000),MAX(0,G6-(E6-1200000)),0)),2) -> 0 | I6: =ROUND(IF(C6="OLD",IF(OR(B6="2014-15",B6="2016-17"),IF(E6<=10000000,0,MIN((G6-H6)*15%,MAX(0,(G6-H6)*0%+(E6-10000000)*(70%-30%*0%)))),IF(B6="2015-16",IF(E6<=10000000,0,MIN((G6-H6)*12%,MAX(0,(G6-H6)*0%+(E6-10000000)*(70%-30%*0%)))),IF(OR(B6="2017-18",B6="2018-19"),IF(E6<=5000000,0,IF(E6<=10000000,MIN((G6-H6)*10%,MAX(0,(G6-H6)*0%+(E6-5000000)*(70%-30%*0%))),MIN((G6-H6)*15%,MAX(0,(G6-H6)*10%+(E6-10000000)*(70%-30%*10%))))),IF(E6<=5000000,0,IF(E6<=10000000,MIN((G6-H6)*10%,MAX(0,(G6-H6)*0%+(E6-5000000)*(70%-30%*0%))),IF(E6<=20000000,MIN((G6-H6)*15%,MAX(0,(G6-H6)*10%+(E6-10000000)*(70%-30%*10%))),IF(E6<=50000000,MIN((G6-H6)*25%,MAX(0,(G6-H6)*15%+(E6-20000000)*(70%-30%*15%))),MIN((G6-H6)*37%,MAX(0,(G6-H6)*25%+(E6-50000000)*(70%-30%*25%)))))))))),IF(OR(B6="2023-24",B6="2024-25",B6="2025-26"),IF(E6<=5000000,0,IF(E6<=10000000,MIN((G6-H6)*10%,MAX(0,(G6-H6)*0%+(E6-5000000)*(70%-30%*0%))),IF(E6<=20000000,MIN((G6-H6)*15%,MAX(0,(G6-H6)*10%+(E6-10000000)*(70%-30%*10%))),MIN((G6-H6)*25%,MAX(0,(G6-H6)*15%+(E6-20000000)*(70%-30%*15%)))))),IF(E6<=5000000,0,IF(E6<=10000000,MIN((G6-H6)*10%,MAX(0,(G6-H6)*0%+(E6-5000000)*(70%-30%*0%))),IF(E6<=20000000,MIN((G6-H6)*15%,MAX(0,(G6-H6)*10%+(E6-10000000)*(70%-30%*10%))),IF(E6<=50000000,MIN((G6-H6)*25%,MAX(0,(G6-H6)*15%+(E6-20000000)*(70%-30%*15%))),MIN((G6-H6)*37%,MAX(0,(G6-H6)*25%+(E6-50000000)*(70%-30%*25%))))))))),2) -> 0 | J6: =ROUND((G6-H6+I6)*IF(OR(B6="2014-15",B6="2015-16",B6="2016-17",B6="2017-18"),3%,4%),2) -> 0 | K6: =ROUND(G6-H6+I6+J6,2) -> 0 | L6: =ROUND(IF(C6="OLD",MAX(0,MIN(F6,500000)-IF(D6="Resident-Senior Citizen",300000,250000))*IF(B6="2016-17",10%,5%)+MAX(0,MIN(F6,1000000)-500000)*20%+MAX(0,F6-1000000)*30%,IF(OR(B6="2020-21",B6="2021-22",B6="2022-23"),MAX(0,MIN(F6,500000)-250000)*5%+MAX(0,MIN(F6,750000)-500000)*10%+MAX(0,MIN(F6,1000000)-750000)*15%+MAX(0,MIN(F6,1250000)-1000000)*20%+MAX(0,MIN(F6,1500000)-1250000)*25%+MAX(0,F6-1500000)*30%,IF(B6="2023-24",MAX(0,MIN(F6,600000)-300000)*5%+MAX(0,MIN(F6,900000)-600000)*10%+MAX(0,MIN(F6,1200000)-900000)*15%+MAX(0,MIN(F6,1500000)-1200000)*20%+MAX(0,F6-1500000)*30%,IF(B6="2024-25",MAX(0,MIN(F6,700000)-300000)*5%+MAX(0,MIN(F6,1000000)-700000)*10%+MAX(0,MIN(F6,1200000)-1000000)*15%+MAX(0,MIN(F6,1500000)-1200000)*20%+MAX(0,F6-1500000)*30%,IF(B6="2025-26",MAX(0,MIN(F6,800000)-400000)*5%+MAX(0,MIN(F6,1200000)-800000)*10%+MAX(0,MIN(F6,1600000)-1200000)*15%+MAX(0,MIN(F6,2000000)-1600000)*20%+MAX(0,MIN(F6,2400000)-2000000)*25%+MAX(0,F6-2400000)*30%,0))))),2) -> 0 | M6: =ROUND(MAX(IF(C6="OLD",IF(F6<=IF(OR(B6="2014-15",B6="2015-16",B6="2016-17"),500000,IF(OR(B6="2017-18",B6="2018-19"),350000,500000)),MIN(L6,IF(OR(B6="2014-15",B6="2015-16"),2000,IF(B6="2016-17",5000,IF(OR(B6="2017-18",B6="2018-19"),2500,12500)))),0),IF(F6<=IF(OR(B6="2023-24",B6="2024-25"),700000,IF(B6="2025-26",1200000,500000)),MIN(L6,IF(OR(B6="2023-24",B6="2024-25"),25000,IF(B6="2025-26",60000,12500))),0)),IF(AND(C6="NEW",B6="2025-26",F6>1200000),MAX(0,L6-(F6-1200000)),0)),2) -> 0 | N6: =ROUND(IF(C6="OLD",IF(OR(B6="2014-15",B6="2016-17"),IF(F6<=10000000,0,MIN((L6-M6)*15%,MAX(0,(L6-M6)*0%+(F6-10000000)*(70%-30%*0%)))),IF(B6="2015-16",IF(F6<=10000000,0,MIN((L6-M6)*12%,MAX(0,(L6-M6)*0%+(F6-10000000)*(70%-30%*0%)))),IF(OR(B6="2017-18",B6="2018-19"),IF(F6<=5000000,0,IF(F6<=10000000,MIN((L6-M6)*10%,MAX(0,(L6-M6)*0%+(F6-5000000)*(70%-30%*0%))),MIN((L6-M6)*15%,MAX(0,(L6-M6)*10%+(F6-10000000)*(70%-30%*10%))))),IF(F6<=5000000,0,IF(F6<=10000000,MIN((L6-M6)*10%,MAX(0,(L6-M6)*0%+(F6-5000000)*(70%-30%*0%))),IF(F6<=20000000,MIN((L6-M6)*15%,MAX(0,(L6-M6)*10%+(F6-10000000)*(70%-30%*10%))),IF(F6<=50000000,MIN((L6-M6)*25%,MAX(0,(L6-M6)*15%+(F6-20000000)*(70%-30%*15%))),MIN((L6-M6)*37%,MAX(0,(L6-M6)*25%+(F6-50000000)*(70%-30%*25%)))))))))),IF(OR(B6="2023-24",B6="2024-25",B6="2025-26"),IF(F6<=5000000,0,IF(F6<=10000000,MIN((L6-M6)*10%,MAX(0,(L6-M6)*0%+(F6-5000000)*(70%-30%*0%))),IF(F6<=20000000,MIN((L6-M6)*15%,MAX(0,(L6-M6)*10%+(F6-10000000)*(70%-30%*10%))),MIN((L6-M6)*25%,MAX(0,(L6-M6)*15%+(F6-20000000)*(70%-30%*15%)))))),IF(F6<=5000000,0,IF(F6<=10000000,MIN((L6-M6)*10%,MAX(0,(L6-M6)*0%+(F6-5000000)*(70%-30%*0%))),IF(F6<=20000000,MIN((L6-M6)*15%,MAX(0,(L6-M6)*10%+(F6-10000000)*(70%-30%*10%))),IF(F6<=50000000,MIN((L6-M6)*25%,MAX(0,(L6-M6)*15%+(F6-20000000)*(70%-30%*15%))),MIN((L6-M6)*37%,MAX(0,(L6-M6)*25%+(F6-50000000)*(70%-30%*25%))))))))),2) -> 0 | O6: =ROUND((L6-M6+N6)*IF(OR(B6="2014-15",B6="2015-16",B6="2016-17",B6="2017-18"),3%,4%),2) -> 0 | P6: =ROUND(L6-M6+N6+O6,2) -> 0 | Q6: =ROUND(P6-K6,2) -> 0
A7: =7 -> 7 | B7: =Source_Data!A7 -> 2017-18 | C7: =Source_Data!E7 -> OLD | D7: =Source_Data!F7 -> Resident-Senior Citizen | E7: =Source_Data!B7 -> 0 | F7: =Source_Data!D7 -> 0 | G7: =ROUND(IF(C7="OLD",MAX(0,MIN(E7,500000)-IF(D7="Resident-Senior Citizen",300000,250000))*IF(B7="2016-17",10%,5%)+MAX(0,MIN(E7,1000000)-500000)*20%+MAX(0,E7-1000000)*30%,IF(OR(B7="2020-21",B7="2021-22",B7="2022-23"),MAX(0,MIN(E7,500000)-250000)*5%+MAX(0,MIN(E7,750000)-500000)*10%+MAX(0,MIN(E7,1000000)-750000)*15%+MAX(0,MIN(E7,1250000)-1000000)*20%+MAX(0,MIN(E7,1500000)-1250000)*25%+MAX(0,E7-1500000)*30%,IF(B7="2023-24",MAX(0,MIN(E7,600000)-300000)*5%+MAX(0,MIN(E7,900000)-600000)*10%+MAX(0,MIN(E7,1200000)-900000)*15%+MAX(0,MIN(E7,1500000)-1200000)*20%+MAX(0,E7-1500000)*30%,IF(B7="2024-25",MAX(0,MIN(E7,700000)-300000)*5%+MAX(0,MIN(E7,1000000)-700000)*10%+MAX(0,MIN(E7,1200000)-1000000)*15%+MAX(0,MIN(E7,1500000)-1200000)*20%+MAX(0,E7-1500000)*30%,IF(B7="2025-26",MAX(0,MIN(E7,800000)-400000)*5%+MAX(0,MIN(E7,1200000)-800000)*10%+MAX(0,MIN(E7,1600000)-1200000)*15%+MAX(0,MIN(E7,2000000)-1600000)*20%+MAX(0,MIN(E7,2400000)-2000000)*25%+MAX(0,E7-2400000)*30%,0))))),2) -> 0 | H7: =ROUND(MAX(IF(C7="OLD",IF(E7<=IF(OR(B7="2014-15",B7="2015-16",B7="2016-17"),500000,IF(OR(B7="2017-18",B7="2018-19"),350000,500000)),MIN(G7,IF(OR(B7="2014-15",B7="2015-16"),2000,IF(B7="2016-17",5000,IF(OR(B7="2017-18",B7="2018-19"),2500,12500)))),0),IF(E7<=IF(OR(B7="2023-24",B7="2024-25"),700000,IF(B7="2025-26",1200000,500000)),MIN(G7,IF(OR(B7="2023-24",B7="2024-25"),25000,IF(B7="2025-26",60000,12500))),0)),IF(AND(C7="NEW",B7="2025-26",E7>1200000),MAX(0,G7-(E7-1200000)),0)),2) -> 0 | I7: =ROUND(IF(C7="OLD",IF(OR(B7="2014-15",B7="2016-17"),IF(E7<=10000000,0,MIN((G7-H7)*15%,MAX(0,(G7-H7)*0%+(E7-10000000)*(70%-30%*0%)))),IF(B7="2015-16",IF(E7<=10000000,0,MIN((G7-H7)*12%,MAX(0,(G7-H7)*0%+(E7-10000000)*(70%-30%*0%)))),IF(OR(B7="2017-18",B7="2018-19"),IF(E7<=5000000,0,IF(E7<=10000000,MIN((G7-H7)*10%,MAX(0,(G7-H7)*0%+(E7-5000000)*(70%-30%*0%))),MIN((G7-H7)*15%,MAX(0,(G7-H7)*10%+(E7-10000000)*(70%-30%*10%))))),IF(E7<=5000000,0,IF(E7<=10000000,MIN((G7-H7)*10%,MAX(0,(G7-H7)*0%+(E7-5000000)*(70%-30%*0%))),IF(E7<=20000000,MIN((G7-H7)*15%,MAX(0,(G7-H7)*10%+(E7-10000000)*(70%-30%*10%))),IF(E7<=50000000,MIN((G7-H7)*25%,MAX(0,(G7-H7)*15%+(E7-20000000)*(70%-30%*15%))),MIN((G7-H7)*37%,MAX(0,(G7-H7)*25%+(E7-50000000)*(70%-30%*25%)))))))))),IF(OR(B7="2023-24",B7="2024-25",B7="2025-26"),IF(E7<=5000000,0,IF(E7<=10000000,MIN((G7-H7)*10%,MAX(0,(G7-H7)*0%+(E7-5000000)*(70%-30%*0%))),IF(E7<=20000000,MIN((G7-H7)*15%,MAX(0,(G7-H7)*10%+(E7-10000000)*(70%-30%*10%))),MIN((G7-H7)*25%,MAX(0,(G7-H7)*15%+(E7-20000000)*(70%-30%*15%)))))),IF(E7<=5000000,0,IF(E7<=10000000,MIN((G7-H7)*10%,MAX(0,(G7-H7)*0%+(E7-5000000)*(70%-30%*0%))),IF(E7<=20000000,MIN((G7-H7)*15%,MAX(0,(G7-H7)*10%+(E7-10000000)*(70%-30%*10%))),IF(E7<=50000000,MIN((G7-H7)*25%,MAX(0,(G7-H7)*15%+(E7-20000000)*(70%-30%*15%))),MIN((G7-H7)*37%,MAX(0,(G7-H7)*25%+(E7-50000000)*(70%-30%*25%))))))))),2) -> 0 | J7: =ROUND((G7-H7+I7)*IF(OR(B7="2014-15",B7="2015-16",B7="2016-17",B7="2017-18"),3%,4%),2) -> 0 | K7: =ROUND(G7-H7+I7+J7,2) -> 0 | L7: =ROUND(IF(C7="OLD",MAX(0,MIN(F7,500000)-IF(D7="Resident-Senior Citizen",300000,250000))*IF(B7="2016-17",10%,5%)+MAX(0,MIN(F7,1000000)-500000)*20%+MAX(0,F7-1000000)*30%,IF(OR(B7="2020-21",B7="2021-22",B7="2022-23"),MAX(0,MIN(F7,500000)-250000)*5%+MAX(0,MIN(F7,750000)-500000)*10%+MAX(0,MIN(F7,1000000)-750000)*15%+MAX(0,MIN(F7,1250000)-1000000)*20%+MAX(0,MIN(F7,1500000)-1250000)*25%+MAX(0,F7-1500000)*30%,IF(B7="2023-24",MAX(0,MIN(F7,600000)-300000)*5%+MAX(0,MIN(F7,900000)-600000)*10%+MAX(0,MIN(F7,1200000)-900000)*15%+MAX(0,MIN(F7,1500000)-1200000)*20%+MAX(0,F7-1500000)*30%,IF(B7="2024-25",MAX(0,MIN(F7,700000)-300000)*5%+MAX(0,MIN(F7,1000000)-700000)*10%+MAX(0,MIN(F7,1200000)-1000000)*15%+MAX(0,MIN(F7,1500000)-1200000)*20%+MAX(0,F7-1500000)*30%,IF(B7="2025-26",MAX(0,MIN(F7,800000)-400000)*5%+MAX(0,MIN(F7,1200000)-800000)*10%+MAX(0,MIN(F7,1600000)-1200000)*15%+MAX(0,MIN(F7,2000000)-1600000)*20%+MAX(0,MIN(F7,2400000)-2000000)*25%+MAX(0,F7-2400000)*30%,0))))),2) -> 0 | M7: =ROUND(MAX(IF(C7="OLD",IF(F7<=IF(OR(B7="2014-15",B7="2015-16",B7="2016-17"),500000,IF(OR(B7="2017-18",B7="2018-19"),350000,500000)),MIN(L7,IF(OR(B7="2014-15",B7="2015-16"),2000,IF(B7="2016-17",5000,IF(OR(B7="2017-18",B7="2018-19"),2500,12500)))),0),IF(F7<=IF(OR(B7="2023-24",B7="2024-25"),700000,IF(B7="2025-26",1200000,500000)),MIN(L7,IF(OR(B7="2023-24",B7="2024-25"),25000,IF(B7="2025-26",60000,12500))),0)),IF(AND(C7="NEW",B7="2025-26",F7>1200000),MAX(0,L7-(F7-1200000)),0)),2) -> 0 | N7: =ROUND(IF(C7="OLD",IF(OR(B7="2014-15",B7="2016-17"),IF(F7<=10000000,0,MIN((L7-M7)*15%,MAX(0,(L7-M7)*0%+(F7-10000000)*(70%-30%*0%)))),IF(B7="2015-16",IF(F7<=10000000,0,MIN((L7-M7)*12%,MAX(0,(L7-M7)*0%+(F7-10000000)*(70%-30%*0%)))),IF(OR(B7="2017-18",B7="2018-19"),IF(F7<=5000000,0,IF(F7<=10000000,MIN((L7-M7)*10%,MAX(0,(L7-M7)*0%+(F7-5000000)*(70%-30%*0%))),MIN((L7-M7)*15%,MAX(0,(L7-M7)*10%+(F7-10000000)*(70%-30%*10%))))),IF(F7<=5000000,0,IF(F7<=10000000,MIN((L7-M7)*10%,MAX(0,(L7-M7)*0%+(F7-5000000)*(70%-30%*0%))),IF(F7<=20000000,MIN((L7-M7)*15%,MAX(0,(L7-M7)*10%+(F7-10000000)*(70%-30%*10%))),IF(F7<=50000000,MIN((L7-M7)*25%,MAX(0,(L7-M7)*15%+(F7-20000000)*(70%-30%*15%))),MIN((L7-M7)*37%,MAX(0,(L7-M7)*25%+(F7-50000000)*(70%-30%*25%)))))))))),IF(OR(B7="2023-24",B7="2024-25",B7="2025-26"),IF(F7<=5000000,0,IF(F7<=10000000,MIN((L7-M7)*10%,MAX(0,(L7-M7)*0%+(F7-5000000)*(70%-30%*0%))),IF(F7<=20000000,MIN((L7-M7)*15%,MAX(0,(L7-M7)*10%+(F7-10000000)*(70%-30%*10%))),MIN((L7-M7)*25%,MAX(0,(L7-M7)*15%+(F7-20000000)*(70%-30%*15%)))))),IF(F7<=5000000,0,IF(F7<=10000000,MIN((L7-M7)*10%,MAX(0,(L7-M7)*0%+(F7-5000000)*(70%-30%*0%))),IF(F7<=20000000,MIN((L7-M7)*15%,MAX(0,(L7-M7)*10%+(F7-10000000)*(70%-30%*10%))),IF(F7<=50000000,MIN((L7-M7)*25%,MAX(0,(L7-M7)*15%+(F7-20000000)*(70%-30%*15%))),MIN((L7-M7)*37%,MAX(0,(L7-M7)*25%+(F7-50000000)*(70%-30%*25%))))))))),2) -> 0 | O7: =ROUND((L7-M7+N7)*IF(OR(B7="2014-15",B7="2015-16",B7="2016-17",B7="2017-18"),3%,4%),2) -> 0 | P7: =ROUND(L7-M7+N7+O7,2) -> 0 | Q7: =ROUND(P7-K7,2) -> 0
A8: =8 -> 8 | B8: =Source_Data!A8 -> 2018-19 | C8: =Source_Data!E8 -> OLD | D8: =Source_Data!F8 -> Resident-Normal Citizen | E8: =Source_Data!B8 -> 0 | F8: =Source_Data!D8 -> 0 | G8: =ROUND(IF(C8="OLD",MAX(0,MIN(E8,500000)-IF(D8="Resident-Senior Citizen",300000,250000))*IF(B8="2016-17",10%,5%)+MAX(0,MIN(E8,1000000)-500000)*20%+MAX(0,E8-1000000)*30%,IF(OR(B8="2020-21",B8="2021-22",B8="2022-23"),MAX(0,MIN(E8,500000)-250000)*5%+MAX(0,MIN(E8,750000)-500000)*10%+MAX(0,MIN(E8,1000000)-750000)*15%+MAX(0,MIN(E8,1250000)-1000000)*20%+MAX(0,MIN(E8,1500000)-1250000)*25%+MAX(0,E8-1500000)*30%,IF(B8="2023-24",MAX(0,MIN(E8,600000)-300000)*5%+MAX(0,MIN(E8,900000)-600000)*10%+MAX(0,MIN(E8,1200000)-900000)*15%+MAX(0,MIN(E8,1500000)-1200000)*20%+MAX(0,E8-1500000)*30%,IF(B8="2024-25",MAX(0,MIN(E8,700000)-300000)*5%+MAX(0,MIN(E8,1000000)-700000)*10%+MAX(0,MIN(E8,1200000)-1000000)*15%+MAX(0,MIN(E8,1500000)-1200000)*20%+MAX(0,E8-1500000)*30%,IF(B8="2025-26",MAX(0,MIN(E8,800000)-400000)*5%+MAX(0,MIN(E8,1200000)-800000)*10%+MAX(0,MIN(E8,1600000)-1200000)*15%+MAX(0,MIN(E8,2000000)-1600000)*20%+MAX(0,MIN(E8,2400000)-2000000)*25%+MAX(0,E8-2400000)*30%,0))))),2) -> 0 | H8: =ROUND(MAX(IF(C8="OLD",IF(E8<=IF(OR(B8="2014-15",B8="2015-16",B8="2016-17"),500000,IF(OR(B8="2017-18",B8="2018-19"),350000,500000)),MIN(G8,IF(OR(B8="2014-15",B8="2015-16"),2000,IF(B8="2016-17",5000,IF(OR(B8="2017-18",B8="2018-19"),2500,12500)))),0),IF(E8<=IF(OR(B8="2023-24",B8="2024-25"),700000,IF(B8="2025-26",1200000,500000)),MIN(G8,IF(OR(B8="2023-24",B8="2024-25"),25000,IF(B8="2025-26",60000,12500))),0)),IF(AND(C8="NEW",B8="2025-26",E8>1200000),MAX(0,G8-(E8-1200000)),0)),2) -> 0 | I8: =ROUND(IF(C8="OLD",IF(OR(B8="2014-15",B8="2016-17"),IF(E8<=10000000,0,MIN((G8-H8)*15%,MAX(0,(G8-H8)*0%+(E8-10000000)*(70%-30%*0%)))),IF(B8="2015-16",IF(E8<=10000000,0,MIN((G8-H8)*12%,MAX(0,(G8-H8)*0%+(E8-10000000)*(70%-30%*0%)))),IF(OR(B8="2017-18",B8="2018-19"),IF(E8<=5000000,0,IF(E8<=10000000,MIN((G8-H8)*10%,MAX(0,(G8-H8)*0%+(E8-5000000)*(70%-30%*0%))),MIN((G8-H8)*15%,MAX(0,(G8-H8)*10%+(E8-10000000)*(70%-30%*10%))))),IF(E8<=5000000,0,IF(E8<=10000000,MIN((G8-H8)*10%,MAX(0,(G8-H8)*0%+(E8-5000000)*(70%-30%*0%))),IF(E8<=20000000,MIN((G8-H8)*15%,MAX(0,(G8-H8)*10%+(E8-10000000)*(70%-30%*10%))),IF(E8<=50000000,MIN((G8-H8)*25%,MAX(0,(G8-H8)*15%+(E8-20000000)*(70%-30%*15%))),MIN((G8-H8)*37%,MAX(0,(G8-H8)*25%+(E8-50000000)*(70%-30%*25%)))))))))),IF(OR(B8="2023-24",B8="2024-25",B8="2025-26"),IF(E8<=5000000,0,IF(E8<=10000000,MIN((G8-H8)*10%,MAX(0,(G8-H8)*0%+(E8-5000000)*(70%-30%*0%))),IF(E8<=20000000,MIN((G8-H8)*15%,MAX(0,(G8-H8)*10%+(E8-10000000)*(70%-30%*10%))),MIN((G8-H8)*25%,MAX(0,(G8-H8)*15%+(E8-20000000)*(70%-30%*15%)))))),IF(E8<=5000000,0,IF(E8<=10000000,MIN((G8-H8)*10%,MAX(0,(G8-H8)*0%+(E8-5000000)*(70%-30%*0%))),IF(E8<=20000000,MIN((G8-H8)*15%,MAX(0,(G8-H8)*10%+(E8-10000000)*(70%-30%*10%))),IF(E8<=50000000,MIN((G8-H8)*25%,MAX(0,(G8-H8)*15%+(E8-20000000)*(70%-30%*15%))),MIN((G8-H8)*37%,MAX(0,(G8-H8)*25%+(E8-50000000)*(70%-30%*25%))))))))),2) -> 0 | J8: =ROUND((G8-H8+I8)*IF(OR(B8="2014-15",B8="2015-16",B8="2016-17",B8="2017-18"),3%,4%),2) -> 0 | K8: =ROUND(G8-H8+I8+J8,2) -> 0 | L8: =ROUND(IF(C8="OLD",MAX(0,MIN(F8,500000)-IF(D8="Resident-Senior Citizen",300000,250000))*IF(B8="2016-17",10%,5%)+MAX(0,MIN(F8,1000000)-500000)*20%+MAX(0,F8-1000000)*30%,IF(OR(B8="2020-21",B8="2021-22",B8="2022-23"),MAX(0,MIN(F8,500000)-250000)*5%+MAX(0,MIN(F8,750000)-500000)*10%+MAX(0,MIN(F8,1000000)-750000)*15%+MAX(0,MIN(F8,1250000)-1000000)*20%+MAX(0,MIN(F8,1500000)-1250000)*25%+MAX(0,F8-1500000)*30%,IF(B8="2023-24",MAX(0,MIN(F8,600000)-300000)*5%+MAX(0,MIN(F8,900000)-600000)*10%+MAX(0,MIN(F8,1200000)-900000)*15%+MAX(0,MIN(F8,1500000)-1200000)*20%+MAX(0,F8-1500000)*30%,IF(B8="2024-25",MAX(0,MIN(F8,700000)-300000)*5%+MAX(0,MIN(F8,1000000)-700000)*10%+MAX(0,MIN(F8,1200000)-1000000)*15%+MAX(0,MIN(F8,1500000)-1200000)*20%+MAX(0,F8-1500000)*30%,IF(B8="2025-26",MAX(0,MIN(F8,800000)-400000)*5%+MAX(0,MIN(F8,1200000)-800000)*10%+MAX(0,MIN(F8,1600000)-1200000)*15%+MAX(0,MIN(F8,2000000)-1600000)*20%+MAX(0,MIN(F8,2400000)-2000000)*25%+MAX(0,F8-2400000)*30%,0))))),2) -> 0 | M8: =ROUND(MAX(IF(C8="OLD",IF(F8<=IF(OR(B8="2014-15",B8="2015-16",B8="2016-17"),500000,IF(OR(B8="2017-18",B8="2018-19"),350000,500000)),MIN(L8,IF(OR(B8="2014-15",B8="2015-16"),2000,IF(B8="2016-17",5000,IF(OR(B8="2017-18",B8="2018-19"),2500,12500)))),0),IF(F8<=IF(OR(B8="2023-24",B8="2024-25"),700000,IF(B8="2025-26",1200000,500000)),MIN(L8,IF(OR(B8="2023-24",B8="2024-25"),25000,IF(B8="2025-26",60000,12500))),0)),IF(AND(C8="NEW",B8="2025-26",F8>1200000),MAX(0,L8-(F8-1200000)),0)),2) -> 0 | N8: =ROUND(IF(C8="OLD",IF(OR(B8="2014-15",B8="2016-17"),IF(F8<=10000000,0,MIN((L8-M8)*15%,MAX(0,(L8-M8)*0%+(F8-10000000)*(70%-30%*0%)))),IF(B8="2015-16",IF(F8<=10000000,0,MIN((L8-M8)*12%,MAX(0,(L8-M8)*0%+(F8-10000000)*(70%-30%*0%)))),IF(OR(B8="2017-18",B8="2018-19"),IF(F8<=5000000,0,IF(F8<=10000000,MIN((L8-M8)*10%,MAX(0,(L8-M8)*0%+(F8-5000000)*(70%-30%*0%))),MIN((L8-M8)*15%,MAX(0,(L8-M8)*10%+(F8-10000000)*(70%-30%*10%))))),IF(F8<=5000000,0,IF(F8<=10000000,MIN((L8-M8)*10%,MAX(0,(L8-M8)*0%+(F8-5000000)*(70%-30%*0%))),IF(F8<=20000000,MIN((L8-M8)*15%,MAX(0,(L8-M8)*10%+(F8-10000000)*(70%-30%*10%))),IF(F8<=50000000,MIN((L8-M8)*25%,MAX(0,(L8-M8)*15%+(F8-20000000)*(70%-30%*15%))),MIN((L8-M8)*37%,MAX(0,(L8-M8)*25%+(F8-50000000)*(70%-30%*25%)))))))))),IF(OR(B8="2023-24",B8="2024-25",B8="2025-26"),IF(F8<=5000000,0,IF(F8<=10000000,MIN((L8-M8)*10%,MAX(0,(L8-M8)*0%+(F8-5000000)*(70%-30%*0%))),IF(F8<=20000000,MIN((L8-M8)*15%,MAX(0,(L8-M8)*10%+(F8-10000000)*(70%-30%*10%))),MIN((L8-M8)*25%,MAX(0,(L8-M8)*15%+(F8-20000000)*(70%-30%*15%)))))),IF(F8<=5000000,0,IF(F8<=10000000,MIN((L8-M8)*10%,MAX(0,(L8-M8)*0%+(F8-5000000)*(70%-30%*0%))),IF(F8<=20000000,MIN((L8-M8)*15%,MAX(0,(L8-M8)*10%+(F8-10000000)*(70%-30%*10%))),IF(F8<=50000000,MIN((L8-M8)*25%,MAX(0,(L8-M8)*15%+(F8-20000000)*(70%-30%*15%))),MIN((L8-M8)*37%,MAX(0,(L8-M8)*25%+(F8-50000000)*(70%-30%*25%))))))))),2) -> 0 | O8: =ROUND((L8-M8+N8)*IF(OR(B8="2014-15",B8="2015-16",B8="2016-17",B8="2017-18"),3%,4%),2) -> 0 | P8: =ROUND(L8-M8+N8+O8,2) -> 0 | Q8: =ROUND(P8-K8,2) -> 0
A9: =9 -> 9 | B9: =Source_Data!A9 -> 2019-20 | C9: =Source_Data!E9 -> OLD | D9: =Source_Data!F9 -> Resident-Normal Citizen | E9: =Source_Data!B9 -> 0 | F9: =Source_Data!D9 -> 0 | G9: =ROUND(IF(C9="OLD",MAX(0,MIN(E9,500000)-IF(D9="Resident-Senior Citizen",300000,250000))*IF(B9="2016-17",10%,5%)+MAX(0,MIN(E9,1000000)-500000)*20%+MAX(0,E9-1000000)*30%,IF(OR(B9="2020-21",B9="2021-22",B9="2022-23"),MAX(0,MIN(E9,500000)-250000)*5%+MAX(0,MIN(E9,750000)-500000)*10%+MAX(0,MIN(E9,1000000)-750000)*15%+MAX(0,MIN(E9,1250000)-1000000)*20%+MAX(0,MIN(E9,1500000)-1250000)*25%+MAX(0,E9-1500000)*30%,IF(B9="2023-24",MAX(0,MIN(E9,600000)-300000)*5%+MAX(0,MIN(E9,900000)-600000)*10%+MAX(0,MIN(E9,1200000)-900000)*15%+MAX(0,MIN(E9,1500000)-1200000)*20%+MAX(0,E9-1500000)*30%,IF(B9="2024-25",MAX(0,MIN(E9,700000)-300000)*5%+MAX(0,MIN(E9,1000000)-700000)*10%+MAX(0,MIN(E9,1200000)-1000000)*15%+MAX(0,MIN(E9,1500000)-1200000)*20%+MAX(0,E9-1500000)*30%,IF(B9="2025-26",MAX(0,MIN(E9,800000)-400000)*5%+MAX(0,MIN(E9,1200000)-800000)*10%+MAX(0,MIN(E9,1600000)-1200000)*15%+MAX(0,MIN(E9,2000000)-1600000)*20%+MAX(0,MIN(E9,2400000)-2000000)*25%+MAX(0,E9-2400000)*30%,0))))),2) -> 0 | H9: =ROUND(MAX(IF(C9="OLD",IF(E9<=IF(OR(B9="2014-15",B9="2015-16",B9="2016-17"),500000,IF(OR(B9="2017-18",B9="2018-19"),350000,500000)),MIN(G9,IF(OR(B9="2014-15",B9="2015-16"),2000,IF(B9="2016-17",5000,IF(OR(B9="2017-18",B9="2018-19"),2500,12500)))),0),IF(E9<=IF(OR(B9="2023-24",B9="2024-25"),700000,IF(B9="2025-26",1200000,500000)),MIN(G9,IF(OR(B9="2023-24",B9="2024-25"),25000,IF(B9="2025-26",60000,12500))),0)),IF(AND(C9="NEW",B9="2025-26",E9>1200000),MAX(0,G9-(E9-1200000)),0)),2) -> 0 | I9: =ROUND(IF(C9="OLD",IF(OR(B9="2014-15",B9="2016-17"),IF(E9<=10000000,0,MIN((G9-H9)*15%,MAX(0,(G9-H9)*0%+(E9-10000000)*(70%-30%*0%)))),IF(B9="2015-16",IF(E9<=10000000,0,MIN((G9-H9)*12%,MAX(0,(G9-H9)*0%+(E9-10000000)*(70%-30%*0%)))),IF(OR(B9="2017-18",B9="2018-19"),IF(E9<=5000000,0,IF(E9<=10000000,MIN((G9-H9)*10%,MAX(0,(G9-H9)*0%+(E9-5000000)*(70%-30%*0%))),MIN((G9-H9)*15%,MAX(0,(G9-H9)*10%+(E9-10000000)*(70%-30%*10%))))),IF(E9<=5000000,0,IF(E9<=10000000,MIN((G9-H9)*10%,MAX(0,(G9-H9)*0%+(E9-5000000)*(70%-30%*0%))),IF(E9<=20000000,MIN((G9-H9)*15%,MAX(0,(G9-H9)*10%+(E9-10000000)*(70%-30%*10%))),IF(E9<=50000000,MIN((G9-H9)*25%,MAX(0,(G9-H9)*15%+(E9-20000000)*(70%-30%*15%))),MIN((G9-H9)*37%,MAX(0,(G9-H9)*25%+(E9-50000000)*(70%-30%*25%)))))))))),IF(OR(B9="2023-24",B9="2024-25",B9="2025-26"),IF(E9<=5000000,0,IF(E9<=10000000,MIN((G9-H9)*10%,MAX(0,(G9-H9)*0%+(E9-5000000)*(70%-30%*0%))),IF(E9<=20000000,MIN((G9-H9)*15%,MAX(0,(G9-H9)*10%+(E9-10000000)*(70%-30%*10%))),MIN((G9-H9)*25%,MAX(0,(G9-H9)*15%+(E9-20000000)*(70%-30%*15%)))))),IF(E9<=5000000,0,IF(E9<=10000000,MIN((G9-H9)*10%,MAX(0,(G9-H9)*0%+(E9-5000000)*(70%-30%*0%))),IF(E9<=20000000,MIN((G9-H9)*15%,MAX(0,(G9-H9)*10%+(E9-10000000)*(70%-30%*10%))),IF(E9<=50000000,MIN((G9-H9)*25%,MAX(0,(G9-H9)*15%+(E9-20000000)*(70%-30%*15%))),MIN((G9-H9)*37%,MAX(0,(G9-H9)*25%+(E9-50000000)*(70%-30%*25%))))))))),2) -> 0 | J9: =ROUND((G9-H9+I9)*IF(OR(B9="2014-15",B9="2015-16",B9="2016-17",B9="2017-18"),3%,4%),2) -> 0 | K9: =ROUND(G9-H9+I9+J9,2) -> 0 | L9: =ROUND(IF(C9="OLD",MAX(0,MIN(F9,500000)-IF(D9="Resident-Senior Citizen",300000,250000))*IF(B9="2016-17",10%,5%)+MAX(0,MIN(F9,1000000)-500000)*20%+MAX(0,F9-1000000)*30%,IF(OR(B9="2020-21",B9="2021-22",B9="2022-23"),MAX(0,MIN(F9,500000)-250000)*5%+MAX(0,MIN(F9,750000)-500000)*10%+MAX(0,MIN(F9,1000000)-750000)*15%+MAX(0,MIN(F9,1250000)-1000000)*20%+MAX(0,MIN(F9,1500000)-1250000)*25%+MAX(0,F9-1500000)*30%,IF(B9="2023-24",MAX(0,MIN(F9,600000)-300000)*5%+MAX(0,MIN(F9,900000)-600000)*10%+MAX(0,MIN(F9,1200000)-900000)*15%+MAX(0,MIN(F9,1500000)-1200000)*20%+MAX(0,F9-1500000)*30%,IF(B9="2024-25",MAX(0,MIN(F9,700000)-300000)*5%+MAX(0,MIN(F9,1000000)-700000)*10%+MAX(0,MIN(F9,1200000)-1000000)*15%+MAX(0,MIN(F9,1500000)-1200000)*20%+MAX(0,F9-1500000)*30%,IF(B9="2025-26",MAX(0,MIN(F9,800000)-400000)*5%+MAX(0,MIN(F9,1200000)-800000)*10%+MAX(0,MIN(F9,1600000)-1200000)*15%+MAX(0,MIN(F9,2000000)-1600000)*20%+MAX(0,MIN(F9,2400000)-2000000)*25%+MAX(0,F9-2400000)*30%,0))))),2) -> 0 | M9: =ROUND(MAX(IF(C9="OLD",IF(F9<=IF(OR(B9="2014-15",B9="2015-16",B9="2016-17"),500000,IF(OR(B9="2017-18",B9="2018-19"),350000,500000)),MIN(L9,IF(OR(B9="2014-15",B9="2015-16"),2000,IF(B9="2016-17",5000,IF(OR(B9="2017-18",B9="2018-19"),2500,12500)))),0),IF(F9<=IF(OR(B9="2023-24",B9="2024-25"),700000,IF(B9="2025-26",1200000,500000)),MIN(L9,IF(OR(B9="2023-24",B9="2024-25"),25000,IF(B9="2025-26",60000,12500))),0)),IF(AND(C9="NEW",B9="2025-26",F9>1200000),MAX(0,L9-(F9-1200000)),0)),2) -> 0 | N9: =ROUND(IF(C9="OLD",IF(OR(B9="2014-15",B9="2016-17"),IF(F9<=10000000,0,MIN((L9-M9)*15%,MAX(0,(L9-M9)*0%+(F9-10000000)*(70%-30%*0%)))),IF(B9="2015-16",IF(F9<=10000000,0,MIN((L9-M9)*12%,MAX(0,(L9-M9)*0%+(F9-10000000)*(70%-30%*0%)))),IF(OR(B9="2017-18",B9="2018-19"),IF(F9<=5000000,0,IF(F9<=10000000,MIN((L9-M9)*10%,MAX(0,(L9-M9)*0%+(F9-5000000)*(70%-30%*0%))),MIN((L9-M9)*15%,MAX(0,(L9-M9)*10%+(F9-10000000)*(70%-30%*10%))))),IF(F9<=5000000,0,IF(F9<=10000000,MIN((L9-M9)*10%,MAX(0,(L9-M9)*0%+(F9-5000000)*(70%-30%*0%))),IF(F9<=20000000,MIN((L9-M9)*15%,MAX(0,(L9-M9)*10%+(F9-10000000)*(70%-30%*10%))),IF(F9<=50000000,MIN((L9-M9)*25%,MAX(0,(L9-M9)*15%+(F9-20000000)*(70%-30%*15%))),MIN((L9-M9)*37%,MAX(0,(L9-M9)*25%+(F9-50000000)*(70%-30%*25%)))))))))),IF(OR(B9="2023-24",B9="2024-25",B9="2025-26"),IF(F9<=5000000,0,IF(F9<=10000000,MIN((L9-M9)*10%,MAX(0,(L9-M9)*0%+(F9-5000000)*(70%-30%*0%))),IF(F9<=20000000,MIN((L9-M9)*15%,MAX(0,(L9-M9)*10%+(F9-10000000)*(70%-30%*10%))),MIN((L9-M9)*25%,MAX(0,(L9-M9)*15%+(F9-20000000)*(70%-30%*15%)))))),IF(F9<=5000000,0,IF(F9<=10000000,MIN((L9-M9)*10%,MAX(0,(L9-M9)*0%+(F9-5000000)*(70%-30%*0%))),IF(F9<=20000000,MIN((L9-M9)*15%,MAX(0,(L9-M9)*10%+(F9-10000000)*(70%-30%*10%))),IF(F9<=50000000,MIN((L9-M9)*25%,MAX(0,(L9-M9)*15%+(F9-20000000)*(70%-30%*15%))),MIN((L9-M9)*37%,MAX(0,(L9-M9)*25%+(F9-50000000)*(70%-30%*25%))))))))),2) -> 0 | O9: =ROUND((L9-M9+N9)*IF(OR(B9="2014-15",B9="2015-16",B9="2016-17",B9="2017-18"),3%,4%),2) -> 0 | P9: =ROUND(L9-M9+N9+O9,2) -> 0 | Q9: =ROUND(P9-K9,2) -> 0
A10: =10 -> 10 | B10: =Source_Data!A10 -> 2020-21 | C10: =Source_Data!E10 -> OLD | D10: =Source_Data!F10 -> Resident-Senior Citizen | E10: =Source_Data!B10 -> 0 | F10: =Source_Data!D10 -> 0 | G10: =ROUND(IF(C10="OLD",MAX(0,MIN(E10,500000)-IF(D10="Resident-Senior Citizen",300000,250000))*IF(B10="2016-17",10%,5%)+MAX(0,MIN(E10,1000000)-500000)*20%+MAX(0,E10-1000000)*30%,IF(OR(B10="2020-21",B10="2021-22",B10="2022-23"),MAX(0,MIN(E10,500000)-250000)*5%+MAX(0,MIN(E10,750000)-500000)*10%+MAX(0,MIN(E10,1000000)-750000)*15%+MAX(0,MIN(E10,1250000)-1000000)*20%+MAX(0,MIN(E10,1500000)-1250000)*25%+MAX(0,E10-1500000)*30%,IF(B10="2023-24",MAX(0,MIN(E10,600000)-300000)*5%+MAX(0,MIN(E10,900000)-600000)*10%+MAX(0,MIN(E10,1200000)-900000)*15%+MAX(0,MIN(E10,1500000)-1200000)*20%+MAX(0,E10-1500000)*30%,IF(B10="2024-25",MAX(0,MIN(E10,700000)-300000)*5%+MAX(0,MIN(E10,1000000)-700000)*10%+MAX(0,MIN(E10,1200000)-1000000)*15%+MAX(0,MIN(E10,1500000)-1200000)*20%+MAX(0,E10-1500000)*30%,IF(B10="2025-26",MAX(0,MIN(E10,800000)-400000)*5%+MAX(0,MIN(E10,1200000)-800000)*10%+MAX(0,MIN(E10,1600000)-1200000)*15%+MAX(0,MIN(E10,2000000)-1600000)*20%+MAX(0,MIN(E10,2400000)-2000000)*25%+MAX(0,E10-2400000)*30%,0))))),2) -> 0 | H10: =ROUND(MAX(IF(C10="OLD",IF(E10<=IF(OR(B10="2014-15",B10="2015-16",B10="2016-17"),500000,IF(OR(B10="2017-18",B10="2018-19"),350000,500000)),MIN(G10,IF(OR(B10="2014-15",B10="2015-16"),2000,IF(B10="2016-17",5000,IF(OR(B10="2017-18",B10="2018-19"),2500,12500)))),0),IF(E10<=IF(OR(B10="2023-24",B10="2024-25"),700000,IF(B10="2025-26",1200000,500000)),MIN(G10,IF(OR(B10="2023-24",B10="2024-25"),25000,IF(B10="2025-26",60000,12500))),0)),IF(AND(C10="NEW",B10="2025-26",E10>1200000),MAX(0,G10-(E10-1200000)),0)),2) -> 0 | I10: =ROUND(IF(C10="OLD",IF(OR(B10="2014-15",B10="2016-17"),IF(E10<=10000000,0,MIN((G10-H10)*15%,MAX(0,(G10-H10)*0%+(E10-10000000)*(70%-30%*0%)))),IF(B10="2015-16",IF(E10<=10000000,0,MIN((G10-H10)*12%,MAX(0,(G10-H10)*0%+(E10-10000000)*(70%-30%*0%)))),IF(OR(B10="2017-18",B10="2018-19"),IF(E10<=5000000,0,IF(E10<=10000000,MIN((G10-H10)*10%,MAX(0,(G10-H10)*0%+(E10-5000000)*(70%-30%*0%))),MIN((G10-H10)*15%,MAX(0,(G10-H10)*10%+(E10-10000000)*(70%-30%*10%))))),IF(E10<=5000000,0,IF(E10<=10000000,MIN((G10-H10)*10%,MAX(0,(G10-H10)*0%+(E10-5000000)*(70%-30%*0%))),IF(E10<=20000000,MIN((G10-H10)*15%,MAX(0,(G10-H10)*10%+(E10-10000000)*(70%-30%*10%))),IF(E10<=50000000,MIN((G10-H10)*25%,MAX(0,(G10-H10)*15%+(E10-20000000)*(70%-30%*15%))),MIN((G10-H10)*37%,MAX(0,(G10-H10)*25%+(E10-50000000)*(70%-30%*25%)))))))))),IF(OR(B10="2023-24",B10="2024-25",B10="2025-26"),IF(E10<=5000000,0,IF(E10<=10000000,MIN((G10-H10)*10%,MAX(0,(G10-H10)*0%+(E10-5000000)*(70%-30%*0%))),IF(E10<=20000000,MIN((G10-H10)*15%,MAX(0,(G10-H10)*10%+(E10-10000000)*(70%-30%*10%))),MIN((G10-H10)*25%,MAX(0,(G10-H10)*15%+(E10-20000000)*(70%-30%*15%)))))),IF(E10<=5000000,0,IF(E10<=10000000,MIN((G10-H10)*10%,MAX(0,(G10-H10)*0%+(E10-5000000)*(70%-30%*0%))),IF(E10<=20000000,MIN((G10-H10)*15%,MAX(0,(G10-H10)*10%+(E10-10000000)*(70%-30%*10%))),IF(E10<=50000000,MIN((G10-H10)*25%,MAX(0,(G10-H10)*15%+(E10-20000000)*(70%-30%*15%))),MIN((G10-H10)*37%,MAX(0,(G10-H10)*25%+(E10-50000000)*(70%-30%*25%))))))))),2) -> 0 | J10: =ROUND((G10-H10+I10)*IF(OR(B10="2014-15",B10="2015-16",B10="2016-17",B10="2017-18"),3%,4%),2) -> 0 | K10: =ROUND(G10-H10+I10+J10,2) -> 0 | L10: =ROUND(IF(C10="OLD",MAX(0,MIN(F10,500000)-IF(D10="Resident-Senior Citizen",300000,250000))*IF(B10="2016-17",10%,5%)+MAX(0,MIN(F10,1000000)-500000)*20%+MAX(0,F10-1000000)*30%,IF(OR(B10="2020-21",B10="2021-22",B10="2022-23"),MAX(0,MIN(F10,500000)-250000)*5%+MAX(0,MIN(F10,750000)-500000)*10%+MAX(0,MIN(F10,1000000)-750000)*15%+MAX(0,MIN(F10,1250000)-1000000)*20%+MAX(0,MIN(F10,1500000)-1250000)*25%+MAX(0,F10-1500000)*30%,IF(B10="2023-24",MAX(0,MIN(F10,600000)-300000)*5%+MAX(0,MIN(F10,900000)-600000)*10%+MAX(0,MIN(F10,1200000)-900000)*15%+MAX(0,MIN(F10,1500000)-1200000)*20%+MAX(0,F10-1500000)*30%,IF(B10="2024-25",MAX(0,MIN(F10,700000)-300000)*5%+MAX(0,MIN(F10,1000000)-700000)*10%+MAX(0,MIN(F10,1200000)-1000000)*15%+MAX(0,MIN(F10,1500000)-1200000)*20%+MAX(0,F10-1500000)*30%,IF(B10="2025-26",MAX(0,MIN(F10,800000)-400000)*5%+MAX(0,MIN(F10,1200000)-800000)*10%+MAX(0,MIN(F10,1600000)-1200000)*15%+MAX(0,MIN(F10,2000000)-1600000)*20%+MAX(0,MIN(F10,2400000)-2000000)*25%+MAX(0,F10-2400000)*30%,0))))),2) -> 0 | M10: =ROUND(MAX(IF(C10="OLD",IF(F10<=IF(OR(B10="2014-15",B10="2015-16",B10="2016-17"),500000,IF(OR(B10="2017-18",B10="2018-19"),350000,500000)),MIN(L10,IF(OR(B10="2014-15",B10="2015-16"),2000,IF(B10="2016-17",5000,IF(OR(B10="2017-18",B10="2018-19"),2500,12500)))),0),IF(F10<=IF(OR(B10="2023-24",B10="2024-25"),700000,IF(B10="2025-26",1200000,500000)),MIN(L10,IF(OR(B10="2023-24",B10="2024-25"),25000,IF(B10="2025-26",60000,12500))),0)),IF(AND(C10="NEW",B10="2025-26",F10>1200000),MAX(0,L10-(F10-1200000)),0)),2) -> 0 | N10: =ROUND(IF(C10="OLD",IF(OR(B10="2014-15",B10="2016-17"),IF(F10<=10000000,0,MIN((L10-M10)*15%,MAX(0,(L10-M10)*0%+(F10-10000000)*(70%-30%*0%)))),IF(B10="2015-16",IF(F10<=10000000,0,MIN((L10-M10)*12%,MAX(0,(L10-M10)*0%+(F10-10000000)*(70%-30%*0%)))),IF(OR(B10="2017-18",B10="2018-19"),IF(F10<=5000000,0,IF(F10<=10000000,MIN((L10-M10)*10%,MAX(0,(L10-M10)*0%+(F10-5000000)*(70%-30%*0%))),MIN((L10-M10)*15%,MAX(0,(L10-M10)*10%+(F10-10000000)*(70%-30%*10%))))),IF(F10<=5000000,0,IF(F10<=10000000,MIN((L10-M10)*10%,MAX(0,(L10-M10)*0%+(F10-5000000)*(70%-30%*0%))),IF(F10<=20000000,MIN((L10-M10)*15%,MAX(0,(L10-M10)*10%+(F10-10000000)*(70%-30%*10%))),IF(F10<=50000000,MIN((L10-M10)*25%,MAX(0,(L10-M10)*15%+(F10-20000000)*(70%-30%*15%))),MIN((L10-M10)*37%,MAX(0,(L10-M10)*25%+(F10-50000000)*(70%-30%*25%)))))))))),IF(OR(B10="2023-24",B10="2024-25",B10="2025-26"),IF(F10<=5000000,0,IF(F10<=10000000,MIN((L10-M10)*10%,MAX(0,(L10-M10)*0%+(F10-5000000)*(70%-30%*0%))),IF(F10<=20000000,MIN((L10-M10)*15%,MAX(0,(L10-M10)*10%+(F10-10000000)*(70%-30%*10%))),MIN((L10-M10)*25%,MAX(0,(L10-M10)*15%+(F10-20000000)*(70%-30%*15%)))))),IF(F10<=5000000,0,IF(F10<=10000000,MIN((L10-M10)*10%,MAX(0,(L10-M10)*0%+(F10-5000000)*(70%-30%*0%))),IF(F10<=20000000,MIN((L10-M10)*15%,MAX(0,(L10-M10)*10%+(F10-10000000)*(70%-30%*10%))),IF(F10<=50000000,MIN((L10-M10)*25%,MAX(0,(L10-M10)*15%+(F10-20000000)*(70%-30%*15%))),MIN((L10-M10)*37%,MAX(0,(L10-M10)*25%+(F10-50000000)*(70%-30%*25%))))))))),2) -> 0 | O10: =ROUND((L10-M10+N10)*IF(OR(B10="2014-15",B10="2015-16",B10="2016-17",B10="2017-18"),3%,4%),2) -> 0 | P10: =ROUND(L10-M10+N10+O10,2) -> 0 | Q10: =ROUND(P10-K10,2) -> 0
A11: =11 -> 11 | B11: =Source_Data!A11 -> 2021-22 | C11: =Source_Data!E11 -> OLD | D11: =Source_Data!F11 -> Resident-Senior Citizen | E11: =Source_Data!B11 -> 0 | F11: =Source_Data!D11 -> 0 | G11: =ROUND(IF(C11="OLD",MAX(0,MIN(E11,500000)-IF(D11="Resident-Senior Citizen",300000,250000))*IF(B11="2016-17",10%,5%)+MAX(0,MIN(E11,1000000)-500000)*20%+MAX(0,E11-1000000)*30%,IF(OR(B11="2020-21",B11="2021-22",B11="2022-23"),MAX(0,MIN(E11,500000)-250000)*5%+MAX(0,MIN(E11,750000)-500000)*10%+MAX(0,MIN(E11,1000000)-750000)*15%+MAX(0,MIN(E11,1250000)-1000000)*20%+MAX(0,MIN(E11,1500000)-1250000)*25%+MAX(0,E11-1500000)*30%,IF(B11="2023-24",MAX(0,MIN(E11,600000)-300000)*5%+MAX(0,MIN(E11,900000)-600000)*10%+MAX(0,MIN(E11,1200000)-900000)*15%+MAX(0,MIN(E11,1500000)-1200000)*20%+MAX(0,E11-1500000)*30%,IF(B11="2024-25",MAX(0,MIN(E11,700000)-300000)*5%+MAX(0,MIN(E11,1000000)-700000)*10%+MAX(0,MIN(E11,1200000)-1000000)*15%+MAX(0,MIN(E11,1500000)-1200000)*20%+MAX(0,E11-1500000)*30%,IF(B11="2025-26",MAX(0,MIN(E11,800000)-400000)*5%+MAX(0,MIN(E11,1200000)-800000)*10%+MAX(0,MIN(E11,1600000)-1200000)*15%+MAX(0,MIN(E11,2000000)-1600000)*20%+MAX(0,MIN(E11,2400000)-2000000)*25%+MAX(0,E11-2400000)*30%,0))))),2) -> 0 | H11: =ROUND(MAX(IF(C11="OLD",IF(E11<=IF(OR(B11="2014-15",B11="2015-16",B11="2016-17"),500000,IF(OR(B11="2017-18",B11="2018-19"),350000,500000)),MIN(G11,IF(OR(B11="2014-15",B11="2015-16"),2000,IF(B11="2016-17",5000,IF(OR(B11="2017-18",B11="2018-19"),2500,12500)))),0),IF(E11<=IF(OR(B11="2023-24",B11="2024-25"),700000,IF(B11="2025-26",1200000,500000)),MIN(G11,IF(OR(B11="2023-24",B11="2024-25"),25000,IF(B11="2025-26",60000,12500))),0)),IF(AND(C11="NEW",B11="2025-26",E11>1200000),MAX(0,G11-(E11-1200000)),0)),2) -> 0 | I11: =ROUND(IF(C11="OLD",IF(OR(B11="2014-15",B11="2016-17"),IF(E11<=10000000,0,MIN((G11-H11)*15%,MAX(0,(G11-H11)*0%+(E11-10000000)*(70%-30%*0%)))),IF(B11="2015-16",IF(E11<=10000000,0,MIN((G11-H11)*12%,MAX(0,(G11-H11)*0%+(E11-10000000)*(70%-30%*0%)))),IF(OR(B11="2017-18",B11="2018-19"),IF(E11<=5000000,0,IF(E11<=10000000,MIN((G11-H11)*10%,MAX(0,(G11-H11)*0%+(E11-5000000)*(70%-30%*0%))),MIN((G11-H11)*15%,MAX(0,(G11-H11)*10%+(E11-10000000)*(70%-30%*10%))))),IF(E11<=5000000,0,IF(E11<=10000000,MIN((G11-H11)*10%,MAX(0,(G11-H11)*0%+(E11-5000000)*(70%-30%*0%))),IF(E11<=20000000,MIN((G11-H11)*15%,MAX(0,(G11-H11)*10%+(E11-10000000)*(70%-30%*10%))),IF(E11<=50000000,MIN((G11-H11)*25%,MAX(0,(G11-H11)*15%+(E11-20000000)*(70%-30%*15%))),MIN((G11-H11)*37%,MAX(0,(G11-H11)*25%+(E11-50000000)*(70%-30%*25%)))))))))),IF(OR(B11="2023-24",B11="2024-25",B11="2025-26"),IF(E11<=5000000,0,IF(E11<=10000000,MIN((G11-H11)*10%,MAX(0,(G11-H11)*0%+(E11-5000000)*(70%-30%*0%))),IF(E11<=20000000,MIN((G11-H11)*15%,MAX(0,(G11-H11)*10%+(E11-10000000)*(70%-30%*10%))),MIN((G11-H11)*25%,MAX(0,(G11-H11)*15%+(E11-20000000)*(70%-30%*15%)))))),IF(E11<=5000000,0,IF(E11<=10000000,MIN((G11-H11)*10%,MAX(0,(G11-H11)*0%+(E11-5000000)*(70%-30%*0%))),IF(E11<=20000000,MIN((G11-H11)*15%,MAX(0,(G11-H11)*10%+(E11-10000000)*(70%-30%*10%))),IF(E11<=50000000,MIN((G11-H11)*25%,MAX(0,(G11-H11)*15%+(E11-20000000)*(70%-30%*15%))),MIN((G11-H11)*37%,MAX(0,(G11-H11)*25%+(E11-50000000)*(70%-30%*25%))))))))),2) -> 0 | J11: =ROUND((G11-H11+I11)*IF(OR(B11="2014-15",B11="2015-16",B11="2016-17",B11="2017-18"),3%,4%),2) -> 0 | K11: =ROUND(G11-H11+I11+J11,2) -> 0 | L11: =ROUND(IF(C11="OLD",MAX(0,MIN(F11,500000)-IF(D11="Resident-Senior Citizen",300000,250000))*IF(B11="2016-17",10%,5%)+MAX(0,MIN(F11,1000000)-500000)*20%+MAX(0,F11-1000000)*30%,IF(OR(B11="2020-21",B11="2021-22",B11="2022-23"),MAX(0,MIN(F11,500000)-250000)*5%+MAX(0,MIN(F11,750000)-500000)*10%+MAX(0,MIN(F11,1000000)-750000)*15%+MAX(0,MIN(F11,1250000)-1000000)*20%+MAX(0,MIN(F11,1500000)-1250000)*25%+MAX(0,F11-1500000)*30%,IF(B11="2023-24",MAX(0,MIN(F11,600000)-300000)*5%+MAX(0,MIN(F11,900000)-600000)*10%+MAX(0,MIN(F11,1200000)-900000)*15%+MAX(0,MIN(F11,1500000)-1200000)*20%+MAX(0,F11-1500000)*30%,IF(B11="2024-25",MAX(0,MIN(F11,700000)-300000)*5%+MAX(0,MIN(F11,1000000)-700000)*10%+MAX(0,MIN(F11,1200000)-1000000)*15%+MAX(0,MIN(F11,1500000)-1200000)*20%+MAX(0,F11-1500000)*30%,IF(B11="2025-26",MAX(0,MIN(F11,800000)-400000)*5%+MAX(0,MIN(F11,1200000)-800000)*10%+MAX(0,MIN(F11,1600000)-1200000)*15%+MAX(0,MIN(F11,2000000)-1600000)*20%+MAX(0,MIN(F11,2400000)-2000000)*25%+MAX(0,F11-2400000)*30%,0))))),2) -> 0 | M11: =ROUND(MAX(IF(C11="OLD",IF(F11<=IF(OR(B11="2014-15",B11="2015-16",B11="2016-17"),500000,IF(OR(B11="2017-18",B11="2018-19"),350000,500000)),MIN(L11,IF(OR(B11="2014-15",B11="2015-16"),2000,IF(B11="2016-17",5000,IF(OR(B11="2017-18",B11="2018-19"),2500,12500)))),0),IF(F11<=IF(OR(B11="2023-24",B11="2024-25"),700000,IF(B11="2025-26",1200000,500000)),MIN(L11,IF(OR(B11="2023-24",B11="2024-25"),25000,IF(B11="2025-26",60000,12500))),0)),IF(AND(C11="NEW",B11="2025-26",F11>1200000),MAX(0,L11-(F11-1200000)),0)),2) -> 0 | N11: =ROUND(IF(C11="OLD",IF(OR(B11="2014-15",B11="2016-17"),IF(F11<=10000000,0,MIN((L11-M11)*15%,MAX(0,(L11-M11)*0%+(F11-10000000)*(70%-30%*0%)))),IF(B11="2015-16",IF(F11<=10000000,0,MIN((L11-M11)*12%,MAX(0,(L11-M11)*0%+(F11-10000000)*(70%-30%*0%)))),IF(OR(B11="2017-18",B11="2018-19"),IF(F11<=5000000,0,IF(F11<=10000000,MIN((L11-M11)*10%,MAX(0,(L11-M11)*0%+(F11-5000000)*(70%-30%*0%))),MIN((L11-M11)*15%,MAX(0,(L11-M11)*10%+(F11-10000000)*(70%-30%*10%))))),IF(F11<=5000000,0,IF(F11<=10000000,MIN((L11-M11)*10%,MAX(0,(L11-M11)*0%+(F11-5000000)*(70%-30%*0%))),IF(F11<=20000000,MIN((L11-M11)*15%,MAX(0,(L11-M11)*10%+(F11-10000000)*(70%-30%*10%))),IF(F11<=50000000,MIN((L11-M11)*25%,MAX(0,(L11-M11)*15%+(F11-20000000)*(70%-30%*15%))),MIN((L11-M11)*37%,MAX(0,(L11-M11)*25%+(F11-50000000)*(70%-30%*25%)))))))))),IF(OR(B11="2023-24",B11="2024-25",B11="2025-26"),IF(F11<=5000000,0,IF(F11<=10000000,MIN((L11-M11)*10%,MAX(0,(L11-M11)*0%+(F11-5000000)*(70%-30%*0%))),IF(F11<=20000000,MIN((L11-M11)*15%,MAX(0,(L11-M11)*10%+(F11-10000000)*(70%-30%*10%))),MIN((L11-M11)*25%,MAX(0,(L11-M11)*15%+(F11-20000000)*(70%-30%*15%)))))),IF(F11<=5000000,0,IF(F11<=10000000,MIN((L11-M11)*10%,MAX(0,(L11-M11)*0%+(F11-5000000)*(70%-30%*0%))),IF(F11<=20000000,MIN((L11-M11)*15%,MAX(0,(L11-M11)*10%+(F11-10000000)*(70%-30%*10%))),IF(F11<=50000000,MIN((L11-M11)*25%,MAX(0,(L11-M11)*15%+(F11-20000000)*(70%-30%*15%))),MIN((L11-M11)*37%,MAX(0,(L11-M11)*25%+(F11-50000000)*(70%-30%*25%))))))))),2) -> 0 | O11: =ROUND((L11-M11+N11)*IF(OR(B11="2014-15",B11="2015-16",B11="2016-17",B11="2017-18"),3%,4%),2) -> 0 | P11: =ROUND(L11-M11+N11+O11,2) -> 0 | Q11: =ROUND(P11-K11,2) -> 0
A12: =12 -> 12 | B12: =Source_Data!A12 -> 2022-23 | C12: =Source_Data!E12 -> NEW | D12: =Source_Data!F12 -> Resident-Senior Citizen | E12: =Source_Data!B12 -> 0 | F12: =Source_Data!D12 -> 0 | G12: =ROUND(IF(C12="OLD",MAX(0,MIN(E12,500000)-IF(D12="Resident-Senior Citizen",300000,250000))*IF(B12="2016-17",10%,5%)+MAX(0,MIN(E12,1000000)-500000)*20%+MAX(0,E12-1000000)*30%,IF(OR(B12="2020-21",B12="2021-22",B12="2022-23"),MAX(0,MIN(E12,500000)-250000)*5%+MAX(0,MIN(E12,750000)-500000)*10%+MAX(0,MIN(E12,1000000)-750000)*15%+MAX(0,MIN(E12,1250000)-1000000)*20%+MAX(0,MIN(E12,1500000)-1250000)*25%+MAX(0,E12-1500000)*30%,IF(B12="2023-24",MAX(0,MIN(E12,600000)-300000)*5%+MAX(0,MIN(E12,900000)-600000)*10%+MAX(0,MIN(E12,1200000)-900000)*15%+MAX(0,MIN(E12,1500000)-1200000)*20%+MAX(0,E12-1500000)*30%,IF(B12="2024-25",MAX(0,MIN(E12,700000)-300000)*5%+MAX(0,MIN(E12,1000000)-700000)*10%+MAX(0,MIN(E12,1200000)-1000000)*15%+MAX(0,MIN(E12,1500000)-1200000)*20%+MAX(0,E12-1500000)*30%,IF(B12="2025-26",MAX(0,MIN(E12,800000)-400000)*5%+MAX(0,MIN(E12,1200000)-800000)*10%+MAX(0,MIN(E12,1600000)-1200000)*15%+MAX(0,MIN(E12,2000000)-1600000)*20%+MAX(0,MIN(E12,2400000)-2000000)*25%+MAX(0,E12-2400000)*30%,0))))),2) -> 0 | H12: =ROUND(MAX(IF(C12="OLD",IF(E12<=IF(OR(B12="2014-15",B12="2015-16",B12="2016-17"),500000,IF(OR(B12="2017-18",B12="2018-19"),350000,500000)),MIN(G12,IF(OR(B12="2014-15",B12="2015-16"),2000,IF(B12="2016-17",5000,IF(OR(B12="2017-18",B12="2018-19"),2500,12500)))),0),IF(E12<=IF(OR(B12="2023-24",B12="2024-25"),700000,IF(B12="2025-26",1200000,500000)),MIN(G12,IF(OR(B12="2023-24",B12="2024-25"),25000,IF(B12="2025-26",60000,12500))),0)),IF(AND(C12="NEW",B12="2025-26",E12>1200000),MAX(0,G12-(E12-1200000)),0)),2) -> 0 | I12: =ROUND(IF(C12="OLD",IF(OR(B12="2014-15",B12="2016-17"),IF(E12<=10000000,0,MIN((G12-H12)*15%,MAX(0,(G12-H12)*0%+(E12-10000000)*(70%-30%*0%)))),IF(B12="2015-16",IF(E12<=10000000,0,MIN((G12-H12)*12%,MAX(0,(G12-H12)*0%+(E12-10000000)*(70%-30%*0%)))),IF(OR(B12="2017-18",B12="2018-19"),IF(E12<=5000000,0,IF(E12<=10000000,MIN((G12-H12)*10%,MAX(0,(G12-H12)*0%+(E12-5000000)*(70%-30%*0%))),MIN((G12-H12)*15%,MAX(0,(G12-H12)*10%+(E12-10000000)*(70%-30%*10%))))),IF(E12<=5000000,0,IF(E12<=10000000,MIN((G12-H12)*10%,MAX(0,(G12-H12)*0%+(E12-5000000)*(70%-30%*0%))),IF(E12<=20000000,MIN((G12-H12)*15%,MAX(0,(G12-H12)*10%+(E12-10000000)*(70%-30%*10%))),IF(E12<=50000000,MIN((G12-H12)*25%,MAX(0,(G12-H12)*15%+(E12-20000000)*(70%-30%*15%))),MIN((G12-H12)*37%,MAX(0,(G12-H12)*25%+(E12-50000000)*(70%-30%*25%)))))))))),IF(OR(B12="2023-24",B12="2024-25",B12="2025-26"),IF(E12<=5000000,0,IF(E12<=10000000,MIN((G12-H12)*10%,MAX(0,(G12-H12)*0%+(E12-5000000)*(70%-30%*0%))),IF(E12<=20000000,MIN((G12-H12)*15%,MAX(0,(G12-H12)*10%+(E12-10000000)*(70%-30%*10%))),MIN((G12-H12)*25%,MAX(0,(G12-H12)*15%+(E12-20000000)*(70%-30%*15%)))))),IF(E12<=5000000,0,IF(E12<=10000000,MIN((G12-H12)*10%,MAX(0,(G12-H12)*0%+(E12-5000000)*(70%-30%*0%))),IF(E12<=20000000,MIN((G12-H12)*15%,MAX(0,(G12-H12)*10%+(E12-10000000)*(70%-30%*10%))),IF(E12<=50000000,MIN((G12-H12)*25%,MAX(0,(G12-H12)*15%+(E12-20000000)*(70%-30%*15%))),MIN((G12-H12)*37%,MAX(0,(G12-H12)*25%+(E12-50000000)*(70%-30%*25%))))))))),2) -> 0 | J12: =ROUND((G12-H12+I12)*IF(OR(B12="2014-15",B12="2015-16",B12="2016-17",B12="2017-18"),3%,4%),2) -> 0 | K12: =ROUND(G12-H12+I12+J12,2) -> 0 | L12: =ROUND(IF(C12="OLD",MAX(0,MIN(F12,500000)-IF(D12="Resident-Senior Citizen",300000,250000))*IF(B12="2016-17",10%,5%)+MAX(0,MIN(F12,1000000)-500000)*20%+MAX(0,F12-1000000)*30%,IF(OR(B12="2020-21",B12="2021-22",B12="2022-23"),MAX(0,MIN(F12,500000)-250000)*5%+MAX(0,MIN(F12,750000)-500000)*10%+MAX(0,MIN(F12,1000000)-750000)*15%+MAX(0,MIN(F12,1250000)-1000000)*20%+MAX(0,MIN(F12,1500000)-1250000)*25%+MAX(0,F12-1500000)*30%,IF(B12="2023-24",MAX(0,MIN(F12,600000)-300000)*5%+MAX(0,MIN(F12,900000)-600000)*10%+MAX(0,MIN(F12,1200000)-900000)*15%+MAX(0,MIN(F12,1500000)-1200000)*20%+MAX(0,F12-1500000)*30%,IF(B12="2024-25",MAX(0,MIN(F12,700000)-300000)*5%+MAX(0,MIN(F12,1000000)-700000)*10%+MAX(0,MIN(F12,1200000)-1000000)*15%+MAX(0,MIN(F12,1500000)-1200000)*20%+MAX(0,F12-1500000)*30%,IF(B12="2025-26",MAX(0,MIN(F12,800000)-400000)*5%+MAX(0,MIN(F12,1200000)-800000)*10%+MAX(0,MIN(F12,1600000)-1200000)*15%+MAX(0,MIN(F12,2000000)-1600000)*20%+MAX(0,MIN(F12,2400000)-2000000)*25%+MAX(0,F12-2400000)*30%,0))))),2) -> 0 | M12: =ROUND(MAX(IF(C12="OLD",IF(F12<=IF(OR(B12="2014-15",B12="2015-16",B12="2016-17"),500000,IF(OR(B12="2017-18",B12="2018-19"),350000,500000)),MIN(L12,IF(OR(B12="2014-15",B12="2015-16"),2000,IF(B12="2016-17",5000,IF(OR(B12="2017-18",B12="2018-19"),2500,12500)))),0),IF(F12<=IF(OR(B12="2023-24",B12="2024-25"),700000,IF(B12="2025-26",1200000,500000)),MIN(L12,IF(OR(B12="2023-24",B12="2024-25"),25000,IF(B12="2025-26",60000,12500))),0)),IF(AND(C12="NEW",B12="2025-26",F12>1200000),MAX(0,L12-(F12-1200000)),0)),2) -> 0 | N12: =ROUND(IF(C12="OLD",IF(OR(B12="2014-15",B12="2016-17"),IF(F12<=10000000,0,MIN((L12-M12)*15%,MAX(0,(L12-M12)*0%+(F12-10000000)*(70%-30%*0%)))),IF(B12="2015-16",IF(F12<=10000000,0,MIN((L12-M12)*12%,MAX(0,(L12-M12)*0%+(F12-10000000)*(70%-30%*0%)))),IF(OR(B12="2017-18",B12="2018-19"),IF(F12<=5000000,0,IF(F12<=10000000,MIN((L12-M12)*10%,MAX(0,(L12-M12)*0%+(F12-5000000)*(70%-30%*0%))),MIN((L12-M12)*15%,MAX(0,(L12-M12)*10%+(F12-10000000)*(70%-30%*10%))))),IF(F12<=5000000,0,IF(F12<=10000000,MIN((L12-M12)*10%,MAX(0,(L12-M12)*0%+(F12-5000000)*(70%-30%*0%))),IF(F12<=20000000,MIN((L12-M12)*15%,MAX(0,(L12-M12)*10%+(F12-10000000)*(70%-30%*10%))),IF(F12<=50000000,MIN((L12-M12)*25%,MAX(0,(L12-M12)*15%+(F12-20000000)*(70%-30%*15%))),MIN((L12-M12)*37%,MAX(0,(L12-M12)*25%+(F12-50000000)*(70%-30%*25%)))))))))),IF(OR(B12="2023-24",B12="2024-25",B12="2025-26"),IF(F12<=5000000,0,IF(F12<=10000000,MIN((L12-M12)*10%,MAX(0,(L12-M12)*0%+(F12-5000000)*(70%-30%*0%))),IF(F12<=20000000,MIN((L12-M12)*15%,MAX(0,(L12-M12)*10%+(F12-10000000)*(70%-30%*10%))),MIN((L12-M12)*25%,MAX(0,(L12-M12)*15%+(F12-20000000)*(70%-30%*15%)))))),IF(F12<=5000000,0,IF(F12<=10000000,MIN((L12-M12)*10%,MAX(0,(L12-M12)*0%+(F12-5000000)*(70%-30%*0%))),IF(F12<=20000000,MIN((L12-M12)*15%,MAX(0,(L12-M12)*10%+(F12-10000000)*(70%-30%*10%))),IF(F12<=50000000,MIN((L12-M12)*25%,MAX(0,(L12-M12)*15%+(F12-20000000)*(70%-30%*15%))),MIN((L12-M12)*37%,MAX(0,(L12-M12)*25%+(F12-50000000)*(70%-30%*25%))))))))),2) -> 0 | O12: =ROUND((L12-M12+N12)*IF(OR(B12="2014-15",B12="2015-16",B12="2016-17",B12="2017-18"),3%,4%),2) -> 0 | P12: =ROUND(L12-M12+N12+O12,2) -> 0 | Q12: =ROUND(P12-K12,2) -> 0
A13: =13 -> 13 | B13: =Source_Data!A13 -> 2023-24 | C13: =Source_Data!E13 -> NEW | D13: =Source_Data!F13 -> Resident-Senior Citizen | E13: =Source_Data!B13 -> 0 | F13: =Source_Data!D13 -> 0 | G13: =ROUND(IF(C13="OLD",MAX(0,MIN(E13,500000)-IF(D13="Resident-Senior Citizen",300000,250000))*IF(B13="2016-17",10%,5%)+MAX(0,MIN(E13,1000000)-500000)*20%+MAX(0,E13-1000000)*30%,IF(OR(B13="2020-21",B13="2021-22",B13="2022-23"),MAX(0,MIN(E13,500000)-250000)*5%+MAX(0,MIN(E13,750000)-500000)*10%+MAX(0,MIN(E13,1000000)-750000)*15%+MAX(0,MIN(E13,1250000)-1000000)*20%+MAX(0,MIN(E13,1500000)-1250000)*25%+MAX(0,E13-1500000)*30%,IF(B13="2023-24",MAX(0,MIN(E13,600000)-300000)*5%+MAX(0,MIN(E13,900000)-600000)*10%+MAX(0,MIN(E13,1200000)-900000)*15%+MAX(0,MIN(E13,1500000)-1200000)*20%+MAX(0,E13-1500000)*30%,IF(B13="2024-25",MAX(0,MIN(E13,700000)-300000)*5%+MAX(0,MIN(E13,1000000)-700000)*10%+MAX(0,MIN(E13,1200000)-1000000)*15%+MAX(0,MIN(E13,1500000)-1200000)*20%+MAX(0,E13-1500000)*30%,IF(B13="2025-26",MAX(0,MIN(E13,800000)-400000)*5%+MAX(0,MIN(E13,1200000)-800000)*10%+MAX(0,MIN(E13,1600000)-1200000)*15%+MAX(0,MIN(E13,2000000)-1600000)*20%+MAX(0,MIN(E13,2400000)-2000000)*25%+MAX(0,E13-2400000)*30%,0))))),2) -> 0 | H13: =ROUND(MAX(IF(C13="OLD",IF(E13<=IF(OR(B13="2014-15",B13="2015-16",B13="2016-17"),500000,IF(OR(B13="2017-18",B13="2018-19"),350000,500000)),MIN(G13,IF(OR(B13="2014-15",B13="2015-16"),2000,IF(B13="2016-17",5000,IF(OR(B13="2017-18",B13="2018-19"),2500,12500)))),0),IF(E13<=IF(OR(B13="2023-24",B13="2024-25"),700000,IF(B13="2025-26",1200000,500000)),MIN(G13,IF(OR(B13="2023-24",B13="2024-25"),25000,IF(B13="2025-26",60000,12500))),0)),IF(AND(C13="NEW",B13="2025-26",E13>1200000),MAX(0,G13-(E13-1200000)),0)),2) -> 0 | I13: =ROUND(IF(C13="OLD",IF(OR(B13="2014-15",B13="2016-17"),IF(E13<=10000000,0,MIN((G13-H13)*15%,MAX(0,(G13-H13)*0%+(E13-10000000)*(70%-30%*0%)))),IF(B13="2015-16",IF(E13<=10000000,0,MIN((G13-H13)*12%,MAX(0,(G13-H13)*0%+(E13-10000000)*(70%-30%*0%)))),IF(OR(B13="2017-18",B13="2018-19"),IF(E13<=5000000,0,IF(E13<=10000000,MIN((G13-H13)*10%,MAX(0,(G13-H13)*0%+(E13-5000000)*(70%-30%*0%))),MIN((G13-H13)*15%,MAX(0,(G13-H13)*10%+(E13-10000000)*(70%-30%*10%))))),IF(E13<=5000000,0,IF(E13<=10000000,MIN((G13-H13)*10%,MAX(0,(G13-H13)*0%+(E13-5000000)*(70%-30%*0%))),IF(E13<=20000000,MIN((G13-H13)*15%,MAX(0,(G13-H13)*10%+(E13-10000000)*(70%-30%*10%))),IF(E13<=50000000,MIN((G13-H13)*25%,MAX(0,(G13-H13)*15%+(E13-20000000)*(70%-30%*15%))),MIN((G13-H13)*37%,MAX(0,(G13-H13)*25%+(E13-50000000)*(70%-30%*25%)))))))))),IF(OR(B13="2023-24",B13="2024-25",B13="2025-26"),IF(E13<=5000000,0,IF(E13<=10000000,MIN((G13-H13)*10%,MAX(0,(G13-H13)*0%+(E13-5000000)*(70%-30%*0%))),IF(E13<=20000000,MIN((G13-H13)*15%,MAX(0,(G13-H13)*10%+(E13-10000000)*(70%-30%*10%))),MIN((G13-H13)*25%,MAX(0,(G13-H13)*15%+(E13-20000000)*(70%-30%*15%)))))),IF(E13<=5000000,0,IF(E13<=10000000,MIN((G13-H13)*10%,MAX(0,(G13-H13)*0%+(E13-5000000)*(70%-30%*0%))),IF(E13<=20000000,MIN((G13-H13)*15%,MAX(0,(G13-H13)*10%+(E13-10000000)*(70%-30%*10%))),IF(E13<=50000000,MIN((G13-H13)*25%,MAX(0,(G13-H13)*15%+(E13-20000000)*(70%-30%*15%))),MIN((G13-H13)*37%,MAX(0,(G13-H13)*25%+(E13-50000000)*(70%-30%*25%))))))))),2) -> 0 | J13: =ROUND((G13-H13+I13)*IF(OR(B13="2014-15",B13="2015-16",B13="2016-17",B13="2017-18"),3%,4%),2) -> 0 | K13: =ROUND(G13-H13+I13+J13,2) -> 0 | L13: =ROUND(IF(C13="OLD",MAX(0,MIN(F13,500000)-IF(D13="Resident-Senior Citizen",300000,250000))*IF(B13="2016-17",10%,5%)+MAX(0,MIN(F13,1000000)-500000)*20%+MAX(0,F13-1000000)*30%,IF(OR(B13="2020-21",B13="2021-22",B13="2022-23"),MAX(0,MIN(F13,500000)-250000)*5%+MAX(0,MIN(F13,750000)-500000)*10%+MAX(0,MIN(F13,1000000)-750000)*15%+MAX(0,MIN(F13,1250000)-1000000)*20%+MAX(0,MIN(F13,1500000)-1250000)*25%+MAX(0,F13-1500000)*30%,IF(B13="2023-24",MAX(0,MIN(F13,600000)-300000)*5%+MAX(0,MIN(F13,900000)-600000)*10%+MAX(0,MIN(F13,1200000)-900000)*15%+MAX(0,MIN(F13,1500000)-1200000)*20%+MAX(0,F13-1500000)*30%,IF(B13="2024-25",MAX(0,MIN(F13,700000)-300000)*5%+MAX(0,MIN(F13,1000000)-700000)*10%+MAX(0,MIN(F13,1200000)-1000000)*15%+MAX(0,MIN(F13,1500000)-1200000)*20%+MAX(0,F13-1500000)*30%,IF(B13="2025-26",MAX(0,MIN(F13,800000)-400000)*5%+MAX(0,MIN(F13,1200000)-800000)*10%+MAX(0,MIN(F13,1600000)-1200000)*15%+MAX(0,MIN(F13,2000000)-1600000)*20%+MAX(0,MIN(F13,2400000)-2000000)*25%+MAX(0,F13-2400000)*30%,0))))),2) -> 0 | M13: =ROUND(MAX(IF(C13="OLD",IF(F13<=IF(OR(B13="2014-15",B13="2015-16",B13="2016-17"),500000,IF(OR(B13="2017-18",B13="2018-19"),350000,500000)),MIN(L13,IF(OR(B13="2014-15",B13="2015-16"),2000,IF(B13="2016-17",5000,IF(OR(B13="2017-18",B13="2018-19"),2500,12500)))),0),IF(F13<=IF(OR(B13="2023-24",B13="2024-25"),700000,IF(B13="2025-26",1200000,500000)),MIN(L13,IF(OR(B13="2023-24",B13="2024-25"),25000,IF(B13="2025-26",60000,12500))),0)),IF(AND(C13="NEW",B13="2025-26",F13>1200000),MAX(0,L13-(F13-1200000)),0)),2) -> 0 | N13: =ROUND(IF(C13="OLD",IF(OR(B13="2014-15",B13="2016-17"),IF(F13<=10000000,0,MIN((L13-M13)*15%,MAX(0,(L13-M13)*0%+(F13-10000000)*(70%-30%*0%)))),IF(B13="2015-16",IF(F13<=10000000,0,MIN((L13-M13)*12%,MAX(0,(L13-M13)*0%+(F13-10000000)*(70%-30%*0%)))),IF(OR(B13="2017-18",B13="2018-19"),IF(F13<=5000000,0,IF(F13<=10000000,MIN((L13-M13)*10%,MAX(0,(L13-M13)*0%+(F13-5000000)*(70%-30%*0%))),MIN((L13-M13)*15%,MAX(0,(L13-M13)*10%+(F13-10000000)*(70%-30%*10%))))),IF(F13<=5000000,0,IF(F13<=10000000,MIN((L13-M13)*10%,MAX(0,(L13-M13)*0%+(F13-5000000)*(70%-30%*0%))),IF(F13<=20000000,MIN((L13-M13)*15%,MAX(0,(L13-M13)*10%+(F13-10000000)*(70%-30%*10%))),IF(F13<=50000000,MIN((L13-M13)*25%,MAX(0,(L13-M13)*15%+(F13-20000000)*(70%-30%*15%))),MIN((L13-M13)*37%,MAX(0,(L13-M13)*25%+(F13-50000000)*(70%-30%*25%)))))))))),IF(OR(B13="2023-24",B13="2024-25",B13="2025-26"),IF(F13<=5000000,0,IF(F13<=10000000,MIN((L13-M13)*10%,MAX(0,(L13-M13)*0%+(F13-5000000)*(70%-30%*0%))),IF(F13<=20000000,MIN((L13-M13)*15%,MAX(0,(L13-M13)*10%+(F13-10000000)*(70%-30%*10%))),MIN((L13-M13)*25%,MAX(0,(L13-M13)*15%+(F13-20000000)*(70%-30%*15%)))))),IF(F13<=5000000,0,IF(F13<=10000000,MIN((L13-M13)*10%,MAX(0,(L13-M13)*0%+(F13-5000000)*(70%-30%*0%))),IF(F13<=20000000,MIN((L13-M13)*15%,MAX(0,(L13-M13)*10%+(F13-10000000)*(70%-30%*10%))),IF(F13<=50000000,MIN((L13-M13)*25%,MAX(0,(L13-M13)*15%+(F13-20000000)*(70%-30%*15%))),MIN((L13-M13)*37%,MAX(0,(L13-M13)*25%+(F13-50000000)*(70%-30%*25%))))))))),2) -> 0 | O13: =ROUND((L13-M13+N13)*IF(OR(B13="2014-15",B13="2015-16",B13="2016-17",B13="2017-18"),3%,4%),2) -> 0 | P13: =ROUND(L13-M13+N13+O13,2) -> 0 | Q13: =ROUND(P13-K13,2) -> 0
A14: =14 -> 14 | B14: =Source_Data!A14 -> 2024-25 | C14: =Source_Data!E14 -> NEW | D14: =Source_Data!F14 -> Resident-Senior Citizen | E14: =Source_Data!B14 -> 0 | F14: =Source_Data!D14 -> 0 | G14: =ROUND(IF(C14="OLD",MAX(0,MIN(E14,500000)-IF(D14="Resident-Senior Citizen",300000,250000))*IF(B14="2016-17",10%,5%)+MAX(0,MIN(E14,1000000)-500000)*20%+MAX(0,E14-1000000)*30%,IF(OR(B14="2020-21",B14="2021-22",B14="2022-23"),MAX(0,MIN(E14,500000)-250000)*5%+MAX(0,MIN(E14,750000)-500000)*10%+MAX(0,MIN(E14,1000000)-750000)*15%+MAX(0,MIN(E14,1250000)-1000000)*20%+MAX(0,MIN(E14,1500000)-1250000)*25%+MAX(0,E14-1500000)*30%,IF(B14="2023-24",MAX(0,MIN(E14,600000)-300000)*5%+MAX(0,MIN(E14,900000)-600000)*10%+MAX(0,MIN(E14,1200000)-900000)*15%+MAX(0,MIN(E14,1500000)-1200000)*20%+MAX(0,E14-1500000)*30%,IF(B14="2024-25",MAX(0,MIN(E14,700000)-300000)*5%+MAX(0,MIN(E14,1000000)-700000)*10%+MAX(0,MIN(E14,1200000)-1000000)*15%+MAX(0,MIN(E14,1500000)-1200000)*20%+MAX(0,E14-1500000)*30%,IF(B14="2025-26",MAX(0,MIN(E14,800000)-400000)*5%+MAX(0,MIN(E14,1200000)-800000)*10%+MAX(0,MIN(E14,1600000)-1200000)*15%+MAX(0,MIN(E14,2000000)-1600000)*20%+MAX(0,MIN(E14,2400000)-2000000)*25%+MAX(0,E14-2400000)*30%,0))))),2) -> 0 | H14: =ROUND(MAX(IF(C14="OLD",IF(E14<=IF(OR(B14="2014-15",B14="2015-16",B14="2016-17"),500000,IF(OR(B14="2017-18",B14="2018-19"),350000,500000)),MIN(G14,IF(OR(B14="2014-15",B14="2015-16"),2000,IF(B14="2016-17",5000,IF(OR(B14="2017-18",B14="2018-19"),2500,12500)))),0),IF(E14<=IF(OR(B14="2023-24",B14="2024-25"),700000,IF(B14="2025-26",1200000,500000)),MIN(G14,IF(OR(B14="2023-24",B14="2024-25"),25000,IF(B14="2025-26",60000,12500))),0)),IF(AND(C14="NEW",B14="2025-26",E14>1200000),MAX(0,G14-(E14-1200000)),0)),2) -> 0 | I14: =ROUND(IF(C14="OLD",IF(OR(B14="2014-15",B14="2016-17"),IF(E14<=10000000,0,MIN((G14-H14)*15%,MAX(0,(G14-H14)*0%+(E14-10000000)*(70%-30%*0%)))),IF(B14="2015-16",IF(E14<=10000000,0,MIN((G14-H14)*12%,MAX(0,(G14-H14)*0%+(E14-10000000)*(70%-30%*0%)))),IF(OR(B14="2017-18",B14="2018-19"),IF(E14<=5000000,0,IF(E14<=10000000,MIN((G14-H14)*10%,MAX(0,(G14-H14)*0%+(E14-5000000)*(70%-30%*0%))),MIN((G14-H14)*15%,MAX(0,(G14-H14)*10%+(E14-10000000)*(70%-30%*10%))))),IF(E14<=5000000,0,IF(E14<=10000000,MIN((G14-H14)*10%,MAX(0,(G14-H14)*0%+(E14-5000000)*(70%-30%*0%))),IF(E14<=20000000,MIN((G14-H14)*15%,MAX(0,(G14-H14)*10%+(E14-10000000)*(70%-30%*10%))),IF(E14<=50000000,MIN((G14-H14)*25%,MAX(0,(G14-H14)*15%+(E14-20000000)*(70%-30%*15%))),MIN((G14-H14)*37%,MAX(0,(G14-H14)*25%+(E14-50000000)*(70%-30%*25%)))))))))),IF(OR(B14="2023-24",B14="2024-25",B14="2025-26"),IF(E14<=5000000,0,IF(E14<=10000000,MIN((G14-H14)*10%,MAX(0,(G14-H14)*0%+(E14-5000000)*(70%-30%*0%))),IF(E14<=20000000,MIN((G14-H14)*15%,MAX(0,(G14-H14)*10%+(E14-10000000)*(70%-30%*10%))),MIN((G14-H14)*25%,MAX(0,(G14-H14)*15%+(E14-20000000)*(70%-30%*15%)))))),IF(E14<=5000000,0,IF(E14<=10000000,MIN((G14-H14)*10%,MAX(0,(G14-H14)*0%+(E14-5000000)*(70%-30%*0%))),IF(E14<=20000000,MIN((G14-H14)*15%,MAX(0,(G14-H14)*10%+(E14-10000000)*(70%-30%*10%))),IF(E14<=50000000,MIN((G14-H14)*25%,MAX(0,(G14-H14)*15%+(E14-20000000)*(70%-30%*15%))),MIN((G14-H14)*37%,MAX(0,(G14-H14)*25%+(E14-50000000)*(70%-30%*25%))))))))),2) -> 0 | J14: =ROUND((G14-H14+I14)*IF(OR(B14="2014-15",B14="2015-16",B14="2016-17",B14="2017-18"),3%,4%),2) -> 0 | K14: =ROUND(G14-H14+I14+J14,2) -> 0 | L14: =ROUND(IF(C14="OLD",MAX(0,MIN(F14,500000)-IF(D14="Resident-Senior Citizen",300000,250000))*IF(B14="2016-17",10%,5%)+MAX(0,MIN(F14,1000000)-500000)*20%+MAX(0,F14-1000000)*30%,IF(OR(B14="2020-21",B14="2021-22",B14="2022-23"),MAX(0,MIN(F14,500000)-250000)*5%+MAX(0,MIN(F14,750000)-500000)*10%+MAX(0,MIN(F14,1000000)-750000)*15%+MAX(0,MIN(F14,1250000)-1000000)*20%+MAX(0,MIN(F14,1500000)-1250000)*25%+MAX(0,F14-1500000)*30%,IF(B14="2023-24",MAX(0,MIN(F14,600000)-300000)*5%+MAX(0,MIN(F14,900000)-600000)*10%+MAX(0,MIN(F14,1200000)-900000)*15%+MAX(0,MIN(F14,1500000)-1200000)*20%+MAX(0,F14-1500000)*30%,IF(B14="2024-25",MAX(0,MIN(F14,700000)-300000)*5%+MAX(0,MIN(F14,1000000)-700000)*10%+MAX(0,MIN(F14,1200000)-1000000)*15%+MAX(0,MIN(F14,1500000)-1200000)*20%+MAX(0,F14-1500000)*30%,IF(B14="2025-26",MAX(0,MIN(F14,800000)-400000)*5%+MAX(0,MIN(F14,1200000)-800000)*10%+MAX(0,MIN(F14,1600000)-1200000)*15%+MAX(0,MIN(F14,2000000)-1600000)*20%+MAX(0,MIN(F14,2400000)-2000000)*25%+MAX(0,F14-2400000)*30%,0))))),2) -> 0 | M14: =ROUND(MAX(IF(C14="OLD",IF(F14<=IF(OR(B14="2014-15",B14="2015-16",B14="2016-17"),500000,IF(OR(B14="2017-18",B14="2018-19"),350000,500000)),MIN(L14,IF(OR(B14="2014-15",B14="2015-16"),2000,IF(B14="2016-17",5000,IF(OR(B14="2017-18",B14="2018-19"),2500,12500)))),0),IF(F14<=IF(OR(B14="2023-24",B14="2024-25"),700000,IF(B14="2025-26",1200000,500000)),MIN(L14,IF(OR(B14="2023-24",B14="2024-25"),25000,IF(B14="2025-26",60000,12500))),0)),IF(AND(C14="NEW",B14="2025-26",F14>1200000),MAX(0,L14-(F14-1200000)),0)),2) -> 0 | N14: =ROUND(IF(C14="OLD",IF(OR(B14="2014-15",B14="2016-17"),IF(F14<=10000000,0,MIN((L14-M14)*15%,MAX(0,(L14-M14)*0%+(F14-10000000)*(70%-30%*0%)))),IF(B14="2015-16",IF(F14<=10000000,0,MIN((L14-M14)*12%,MAX(0,(L14-M14)*0%+(F14-10000000)*(70%-30%*0%)))),IF(OR(B14="2017-18",B14="2018-19"),IF(F14<=5000000,0,IF(F14<=10000000,MIN((L14-M14)*10%,MAX(0,(L14-M14)*0%+(F14-5000000)*(70%-30%*0%))),MIN((L14-M14)*15%,MAX(0,(L14-M14)*10%+(F14-10000000)*(70%-30%*10%))))),IF(F14<=5000000,0,IF(F14<=10000000,MIN((L14-M14)*10%,MAX(0,(L14-M14)*0%+(F14-5000000)*(70%-30%*0%))),IF(F14<=20000000,MIN((L14-M14)*15%,MAX(0,(L14-M14)*10%+(F14-10000000)*(70%-30%*10%))),IF(F14<=50000000,MIN((L14-M14)*25%,MAX(0,(L14-M14)*15%+(F14-20000000)*(70%-30%*15%))),MIN((L14-M14)*37%,MAX(0,(L14-M14)*25%+(F14-50000000)*(70%-30%*25%)))))))))),IF(OR(B14="2023-24",B14="2024-25",B14="2025-26"),IF(F14<=5000000,0,IF(F14<=10000000,MIN((L14-M14)*10%,MAX(0,(L14-M14)*0%+(F14-5000000)*(70%-30%*0%))),IF(F14<=20000000,MIN((L14-M14)*15%,MAX(0,(L14-M14)*10%+(F14-10000000)*(70%-30%*10%))),MIN((L14-M14)*25%,MAX(0,(L14-M14)*15%+(F14-20000000)*(70%-30%*15%)))))),IF(F14<=5000000,0,IF(F14<=10000000,MIN((L14-M14)*10%,MAX(0,(L14-M14)*0%+(F14-5000000)*(70%-30%*0%))),IF(F14<=20000000,MIN((L14-M14)*15%,MAX(0,(L14-M14)*10%+(F14-10000000)*(70%-30%*10%))),IF(F14<=50000000,MIN((L14-M14)*25%,MAX(0,(L14-M14)*15%+(F14-20000000)*(70%-30%*15%))),MIN((L14-M14)*37%,MAX(0,(L14-M14)*25%+(F14-50000000)*(70%-30%*25%))))))))),2) -> 0 | O14: =ROUND((L14-M14+N14)*IF(OR(B14="2014-15",B14="2015-16",B14="2016-17",B14="2017-18"),3%,4%),2) -> 0 | P14: =ROUND(L14-M14+N14+O14,2) -> 0 | Q14: =ROUND(P14-K14,2) -> 0
A15: =15 -> 15 | B15: =Source_Data!A15 -> 2025-26 | C15: =Source_Data!E15 -> NEW | D15: =Source_Data!F15 -> Resident-Senior Citizen | E15: =Source_Data!B15 -> 0 | F15: =Source_Data!D15 -> 0 | G15: =ROUND(IF(C15="OLD",MAX(0,MIN(E15,500000)-IF(D15="Resident-Senior Citizen",300000,250000))*IF(B15="2016-17",10%,5%)+MAX(0,MIN(E15,1000000)-500000)*20%+MAX(0,E15-1000000)*30%,IF(OR(B15="2020-21",B15="2021-22",B15="2022-23"),MAX(0,MIN(E15,500000)-250000)*5%+MAX(0,MIN(E15,750000)-500000)*10%+MAX(0,MIN(E15,1000000)-750000)*15%+MAX(0,MIN(E15,1250000)-1000000)*20%+MAX(0,MIN(E15,1500000)-1250000)*25%+MAX(0,E15-1500000)*30%,IF(B15="2023-24",MAX(0,MIN(E15,600000)-300000)*5%+MAX(0,MIN(E15,900000)-600000)*10%+MAX(0,MIN(E15,1200000)-900000)*15%+MAX(0,MIN(E15,1500000)-1200000)*20%+MAX(0,E15-1500000)*30%,IF(B15="2024-25",MAX(0,MIN(E15,700000)-300000)*5%+MAX(0,MIN(E15,1000000)-700000)*10%+MAX(0,MIN(E15,1200000)-1000000)*15%+MAX(0,MIN(E15,1500000)-1200000)*20%+MAX(0,E15-1500000)*30%,IF(B15="2025-26",MAX(0,MIN(E15,800000)-400000)*5%+MAX(0,MIN(E15,1200000)-800000)*10%+MAX(0,MIN(E15,1600000)-1200000)*15%+MAX(0,MIN(E15,2000000)-1600000)*20%+MAX(0,MIN(E15,2400000)-2000000)*25%+MAX(0,E15-2400000)*30%,0))))),2) -> 0 | H15: =ROUND(MAX(IF(C15="OLD",IF(E15<=IF(OR(B15="2014-15",B15="2015-16",B15="2016-17"),500000,IF(OR(B15="2017-18",B15="2018-19"),350000,500000)),MIN(G15,IF(OR(B15="2014-15",B15="2015-16"),2000,IF(B15="2016-17",5000,IF(OR(B15="2017-18",B15="2018-19"),2500,12500)))),0),IF(E15<=IF(OR(B15="2023-24",B15="2024-25"),700000,IF(B15="2025-26",1200000,500000)),MIN(G15,IF(OR(B15="2023-24",B15="2024-25"),25000,IF(B15="2025-26",60000,12500))),0)),IF(AND(C15="NEW",B15="2025-26",E15>1200000),MAX(0,G15-(E15-1200000)),0)),2) -> 0 | I15: =ROUND(IF(C15="OLD",IF(OR(B15="2014-15",B15="2016-17"),IF(E15<=10000000,0,MIN((G15-H15)*15%,MAX(0,(G15-H15)*0%+(E15-10000000)*(70%-30%*0%)))),IF(B15="2015-16",IF(E15<=10000000,0,MIN((G15-H15)*12%,MAX(0,(G15-H15)*0%+(E15-10000000)*(70%-30%*0%)))),IF(OR(B15="2017-18",B15="2018-19"),IF(E15<=5000000,0,IF(E15<=10000000,MIN((G15-H15)*10%,MAX(0,(G15-H15)*0%+(E15-5000000)*(70%-30%*0%))),MIN((G15-H15)*15%,MAX(0,(G15-H15)*10%+(E15-10000000)*(70%-30%*10%))))),IF(E15<=5000000,0,IF(E15<=10000000,MIN((G15-H15)*10%,MAX(0,(G15-H15)*0%+(E15-5000000)*(70%-30%*0%))),IF(E15<=20000000,MIN((G15-H15)*15%,MAX(0,(G15-H15)*10%+(E15-10000000)*(70%-30%*10%))),IF(E15<=50000000,MIN((G15-H15)*25%,MAX(0,(G15-H15)*15%+(E15-20000000)*(70%-30%*15%))),MIN((G15-H15)*37%,MAX(0,(G15-H15)*25%+(E15-50000000)*(70%-30%*25%)))))))))),IF(OR(B15="2023-24",B15="2024-25",B15="2025-26"),IF(E15<=5000000,0,IF(E15<=10000000,MIN((G15-H15)*10%,MAX(0,(G15-H15)*0%+(E15-5000000)*(70%-30%*0%))),IF(E15<=20000000,MIN((G15-H15)*15%,MAX(0,(G15-H15)*10%+(E15-10000000)*(70%-30%*10%))),MIN((G15-H15)*25%,MAX(0,(G15-H15)*15%+(E15-20000000)*(70%-30%*15%)))))),IF(E15<=5000000,0,IF(E15<=10000000,MIN((G15-H15)*10%,MAX(0,(G15-H15)*0%+(E15-5000000)*(70%-30%*0%))),IF(E15<=20000000,MIN((G15-H15)*15%,MAX(0,(G15-H15)*10%+(E15-10000000)*(70%-30%*10%))),IF(E15<=50000000,MIN((G15-H15)*25%,MAX(0,(G15-H15)*15%+(E15-20000000)*(70%-30%*15%))),MIN((G15-H15)*37%,MAX(0,(G15-H15)*25%+(E15-50000000)*(70%-30%*25%))))))))),2) -> 0 | J15: =ROUND((G15-H15+I15)*IF(OR(B15="2014-15",B15="2015-16",B15="2016-17",B15="2017-18"),3%,4%),2) -> 0 | K15: =ROUND(G15-H15+I15+J15,2) -> 0 | L15: =ROUND(IF(C15="OLD",MAX(0,MIN(F15,500000)-IF(D15="Resident-Senior Citizen",300000,250000))*IF(B15="2016-17",10%,5%)+MAX(0,MIN(F15,1000000)-500000)*20%+MAX(0,F15-1000000)*30%,IF(OR(B15="2020-21",B15="2021-22",B15="2022-23"),MAX(0,MIN(F15,500000)-250000)*5%+MAX(0,MIN(F15,750000)-500000)*10%+MAX(0,MIN(F15,1000000)-750000)*15%+MAX(0,MIN(F15,1250000)-1000000)*20%+MAX(0,MIN(F15,1500000)-1250000)*25%+MAX(0,F15-1500000)*30%,IF(B15="2023-24",MAX(0,MIN(F15,600000)-300000)*5%+MAX(0,MIN(F15,900000)-600000)*10%+MAX(0,MIN(F15,1200000)-900000)*15%+MAX(0,MIN(F15,1500000)-1200000)*20%+MAX(0,F15-1500000)*30%,IF(B15="2024-25",MAX(0,MIN(F15,700000)-300000)*5%+MAX(0,MIN(F15,1000000)-700000)*10%+MAX(0,MIN(F15,1200000)-1000000)*15%+MAX(0,MIN(F15,1500000)-1200000)*20%+MAX(0,F15-1500000)*30%,IF(B15="2025-26",MAX(0,MIN(F15,800000)-400000)*5%+MAX(0,MIN(F15,1200000)-800000)*10%+MAX(0,MIN(F15,1600000)-1200000)*15%+MAX(0,MIN(F15,2000000)-1600000)*20%+MAX(0,MIN(F15,2400000)-2000000)*25%+MAX(0,F15-2400000)*30%,0))))),2) -> 0 | M15: =ROUND(MAX(IF(C15="OLD",IF(F15<=IF(OR(B15="2014-15",B15="2015-16",B15="2016-17"),500000,IF(OR(B15="2017-18",B15="2018-19"),350000,500000)),MIN(L15,IF(OR(B15="2014-15",B15="2015-16"),2000,IF(B15="2016-17",5000,IF(OR(B15="2017-18",B15="2018-19"),2500,12500)))),0),IF(F15<=IF(OR(B15="2023-24",B15="2024-25"),700000,IF(B15="2025-26",1200000,500000)),MIN(L15,IF(OR(B15="2023-24",B15="2024-25"),25000,IF(B15="2025-26",60000,12500))),0)),IF(AND(C15="NEW",B15="2025-26",F15>1200000),MAX(0,L15-(F15-1200000)),0)),2) -> 0 | N15: =ROUND(IF(C15="OLD",IF(OR(B15="2014-15",B15="2016-17"),IF(F15<=10000000,0,MIN((L15-M15)*15%,MAX(0,(L15-M15)*0%+(F15-10000000)*(70%-30%*0%)))),IF(B15="2015-16",IF(F15<=10000000,0,MIN((L15-M15)*12%,MAX(0,(L15-M15)*0%+(F15-10000000)*(70%-30%*0%)))),IF(OR(B15="2017-18",B15="2018-19"),IF(F15<=5000000,0,IF(F15<=10000000,MIN((L15-M15)*10%,MAX(0,(L15-M15)*0%+(F15-5000000)*(70%-30%*0%))),MIN((L15-M15)*15%,MAX(0,(L15-M15)*10%+(F15-10000000)*(70%-30%*10%))))),IF(F15<=5000000,0,IF(F15<=10000000,MIN((L15-M15)*10%,MAX(0,(L15-M15)*0%+(F15-5000000)*(70%-30%*0%))),IF(F15<=20000000,MIN((L15-M15)*15%,MAX(0,(L15-M15)*10%+(F15-10000000)*(70%-30%*10%))),IF(F15<=50000000,MIN((L15-M15)*25%,MAX(0,(L15-M15)*15%+(F15-20000000)*(70%-30%*15%))),MIN((L15-M15)*37%,MAX(0,(L15-M15)*25%+(F15-50000000)*(70%-30%*25%)))))))))),IF(OR(B15="2023-24",B15="2024-25",B15="2025-26"),IF(F15<=5000000,0,IF(F15<=10000000,MIN((L15-M15)*10%,MAX(0,(L15-M15)*0%+(F15-5000000)*(70%-30%*0%))),IF(F15<=20000000,MIN((L15-M15)*15%,MAX(0,(L15-M15)*10%+(F15-10000000)*(70%-30%*10%))),MIN((L15-M15)*25%,MAX(0,(L15-M15)*15%+(F15-20000000)*(70%-30%*15%)))))),IF(F15<=5000000,0,IF(F15<=10000000,MIN((L15-M15)*10%,MAX(0,(L15-M15)*0%+(F15-5000000)*(70%-30%*0%))),IF(F15<=20000000,MIN((L15-M15)*15%,MAX(0,(L15-M15)*10%+(F15-10000000)*(70%-30%*10%))),IF(F15<=50000000,MIN((L15-M15)*25%,MAX(0,(L15-M15)*15%+(F15-20000000)*(70%-30%*15%))),MIN((L15-M15)*37%,MAX(0,(L15-M15)*25%+(F15-50000000)*(70%-30%*25%))))))))),2) -> 0 | O15: =ROUND((L15-M15+N15)*IF(OR(B15="2014-15",B15="2015-16",B15="2016-17",B15="2017-18"),3%,4%),2) -> 0 | P15: =ROUND(L15-M15+N15+O15,2) -> 0 | Q15: =ROUND(P15-K15,2) -> 0
A18: =4 -> 4 | B18: =Source_Data!A4 -> 2014-15 | C18: ="OLD" -> OLD | D18: =Source_Data!F4 -> Resident-Normal Citizen | E18: =Source_Data!B4 -> 0 | F18: =Source_Data!D4 -> 0 | G18: =ROUND(IF(C18="OLD",MAX(0,MIN(E18,500000)-IF(D18="Resident-Senior Citizen",300000,250000))*IF(B18="2016-17",10%,5%)+MAX(0,MIN(E18,1000000)-500000)*20%+MAX(0,E18-1000000)*30%,IF(OR(B18="2020-21",B18="2021-22",B18="2022-23"),MAX(0,MIN(E18,500000)-250000)*5%+MAX(0,MIN(E18,750000)-500000)*10%+MAX(0,MIN(E18,1000000)-750000)*15%+MAX(0,MIN(E18,1250000)-1000000)*20%+MAX(0,MIN(E18,1500000)-1250000)*25%+MAX(0,E18-1500000)*30%,IF(B18="2023-24",MAX(0,MIN(E18,600000)-300000)*5%+MAX(0,MIN(E18,900000)-600000)*10%+MAX(0,MIN(E18,1200000)-900000)*15%+MAX(0,MIN(E18,1500000)-1200000)*20%+MAX(0,E18-1500000)*30%,IF(B18="2024-25",MAX(0,MIN(E18,700000)-300000)*5%+MAX(0,MIN(E18,1000000)-700000)*10%+MAX(0,MIN(E18,1200000)-1000000)*15%+MAX(0,MIN(E18,1500000)-1200000)*20%+MAX(0,E18-1500000)*30%,IF(B18="2025-26",MAX(0,MIN(E18,800000)-400000)*5%+MAX(0,MIN(E18,1200000)-800000)*10%+MAX(0,MIN(E18,1600000)-1200000)*15%+MAX(0,MIN(E18,2000000)-1600000)*20%+MAX(0,MIN(E18,2400000)-2000000)*25%+MAX(0,E18-2400000)*30%,0))))),2) -> 0 | H18: =ROUND(MAX(IF(C18="OLD",IF(E18<=IF(OR(B18="2014-15",B18="2015-16",B18="2016-17"),500000,IF(OR(B18="2017-18",B18="2018-19"),350000,500000)),MIN(G18,IF(OR(B18="2014-15",B18="2015-16"),2000,IF(B18="2016-17",5000,IF(OR(B18="2017-18",B18="2018-19"),2500,12500)))),0),IF(E18<=IF(OR(B18="2023-24",B18="2024-25"),700000,IF(B18="2025-26",1200000,500000)),MIN(G18,IF(OR(B18="2023-24",B18="2024-25"),25000,IF(B18="2025-26",60000,12500))),0)),IF(AND(C18="NEW",B18="2025-26",E18>1200000),MAX(0,G18-(E18-1200000)),0)),2) -> 0 | I18: =ROUND(IF(C18="OLD",IF(OR(B18="2014-15",B18="2016-17"),IF(E18<=10000000,0,MIN((G18-H18)*15%,MAX(0,(G18-H18)*0%+(E18-10000000)*(70%-30%*0%)))),IF(B18="2015-16",IF(E18<=10000000,0,MIN((G18-H18)*12%,MAX(0,(G18-H18)*0%+(E18-10000000)*(70%-30%*0%)))),IF(OR(B18="2017-18",B18="2018-19"),IF(E18<=5000000,0,IF(E18<=10000000,MIN((G18-H18)*10%,MAX(0,(G18-H18)*0%+(E18-5000000)*(70%-30%*0%))),MIN((G18-H18)*15%,MAX(0,(G18-H18)*10%+(E18-10000000)*(70%-30%*10%))))),IF(E18<=5000000,0,IF(E18<=10000000,MIN((G18-H18)*10%,MAX(0,(G18-H18)*0%+(E18-5000000)*(70%-30%*0%))),IF(E18<=20000000,MIN((G18-H18)*15%,MAX(0,(G18-H18)*10%+(E18-10000000)*(70%-30%*10%))),IF(E18<=50000000,MIN((G18-H18)*25%,MAX(0,(G18-H18)*15%+(E18-20000000)*(70%-30%*15%))),MIN((G18-H18)*37%,MAX(0,(G18-H18)*25%+(E18-50000000)*(70%-30%*25%)))))))))),IF(OR(B18="2023-24",B18="2024-25",B18="2025-26"),IF(E18<=5000000,0,IF(E18<=10000000,MIN((G18-H18)*10%,MAX(0,(G18-H18)*0%+(E18-5000000)*(70%-30%*0%))),IF(E18<=20000000,MIN((G18-H18)*15%,MAX(0,(G18-H18)*10%+(E18-10000000)*(70%-30%*10%))),MIN((G18-H18)*25%,MAX(0,(G18-H18)*15%+(E18-20000000)*(70%-30%*15%)))))),IF(E18<=5000000,0,IF(E18<=10000000,MIN((G18-H18)*10%,MAX(0,(G18-H18)*0%+(E18-5000000)*(70%-30%*0%))),IF(E18<=20000000,MIN((G18-H18)*15%,MAX(0,(G18-H18)*10%+(E18-10000000)*(70%-30%*10%))),IF(E18<=50000000,MIN((G18-H18)*25%,MAX(0,(G18-H18)*15%+(E18-20000000)*(70%-30%*15%))),MIN((G18-H18)*37%,MAX(0,(G18-H18)*25%+(E18-50000000)*(70%-30%*25%))))))))),2) -> 0 | J18: =ROUND((G18-H18+I18)*IF(OR(B18="2014-15",B18="2015-16",B18="2016-17",B18="2017-18"),3%,4%),2) -> 0 | K18: =ROUND(G18-H18+I18+J18,2) -> 0 | L18: =ROUND(IF(C18="OLD",MAX(0,MIN(F18,500000)-IF(D18="Resident-Senior Citizen",300000,250000))*IF(B18="2016-17",10%,5%)+MAX(0,MIN(F18,1000000)-500000)*20%+MAX(0,F18-1000000)*30%,IF(OR(B18="2020-21",B18="2021-22",B18="2022-23"),MAX(0,MIN(F18,500000)-250000)*5%+MAX(0,MIN(F18,750000)-500000)*10%+MAX(0,MIN(F18,1000000)-750000)*15%+MAX(0,MIN(F18,1250000)-1000000)*20%+MAX(0,MIN(F18,1500000)-1250000)*25%+MAX(0,F18-1500000)*30%,IF(B18="2023-24",MAX(0,MIN(F18,600000)-300000)*5%+MAX(0,MIN(F18,900000)-600000)*10%+MAX(0,MIN(F18,1200000)-900000)*15%+MAX(0,MIN(F18,1500000)-1200000)*20%+MAX(0,F18-1500000)*30%,IF(B18="2024-25",MAX(0,MIN(F18,700000)-300000)*5%+MAX(0,MIN(F18,1000000)-700000)*10%+MAX(0,MIN(F18,1200000)-1000000)*15%+MAX(0,MIN(F18,1500000)-1200000)*20%+MAX(0,F18-1500000)*30%,IF(B18="2025-26",MAX(0,MIN(F18,800000)-400000)*5%+MAX(0,MIN(F18,1200000)-800000)*10%+MAX(0,MIN(F18,1600000)-1200000)*15%+MAX(0,MIN(F18,2000000)-1600000)*20%+MAX(0,MIN(F18,2400000)-2000000)*25%+MAX(0,F18-2400000)*30%,0))))),2) -> 0 | M18: =ROUND(MAX(IF(C18="OLD",IF(F18<=IF(OR(B18="2014-15",B18="2015-16",B18="2016-17"),500000,IF(OR(B18="2017-18",B18="2018-19"),350000,500000)),MIN(L18,IF(OR(B18="2014-15",B18="2015-16"),2000,IF(B18="2016-17",5000,IF(OR(B18="2017-18",B18="2018-19"),2500,12500)))),0),IF(F18<=IF(OR(B18="2023-24",B18="2024-25"),700000,IF(B18="2025-26",1200000,500000)),MIN(L18,IF(OR(B18="2023-24",B18="2024-25"),25000,IF(B18="2025-26",60000,12500))),0)),IF(AND(C18="NEW",B18="2025-26",F18>1200000),MAX(0,L18-(F18-1200000)),0)),2) -> 0 | N18: =ROUND(IF(C18="OLD",IF(OR(B18="2014-15",B18="2016-17"),IF(F18<=10000000,0,MIN((L18-M18)*15%,MAX(0,(L18-M18)*0%+(F18-10000000)*(70%-30%*0%)))),IF(B18="2015-16",IF(F18<=10000000,0,MIN((L18-M18)*12%,MAX(0,(L18-M18)*0%+(F18-10000000)*(70%-30%*0%)))),IF(OR(B18="2017-18",B18="2018-19"),IF(F18<=5000000,0,IF(F18<=10000000,MIN((L18-M18)*10%,MAX(0,(L18-M18)*0%+(F18-5000000)*(70%-30%*0%))),MIN((L18-M18)*15%,MAX(0,(L18-M18)*10%+(F18-10000000)*(70%-30%*10%))))),IF(F18<=5000000,0,IF(F18<=10000000,MIN((L18-M18)*10%,MAX(0,(L18-M18)*0%+(F18-5000000)*(70%-30%*0%))),IF(F18<=20000000,MIN((L18-M18)*15%,MAX(0,(L18-M18)*10%+(F18-10000000)*(70%-30%*10%))),IF(F18<=50000000,MIN((L18-M18)*25%,MAX(0,(L18-M18)*15%+(F18-20000000)*(70%-30%*15%))),MIN((L18-M18)*37%,MAX(0,(L18-M18)*25%+(F18-50000000)*(70%-30%*25%)))))))))),IF(OR(B18="2023-24",B18="2024-25",B18="2025-26"),IF(F18<=5000000,0,IF(F18<=10000000,MIN((L18-M18)*10%,MAX(0,(L18-M18)*0%+(F18-5000000)*(70%-30%*0%))),IF(F18<=20000000,MIN((L18-M18)*15%,MAX(0,(L18-M18)*10%+(F18-10000000)*(70%-30%*10%))),MIN((L18-M18)*25%,MAX(0,(L18-M18)*15%+(F18-20000000)*(70%-30%*15%)))))),IF(F18<=5000000,0,IF(F18<=10000000,MIN((L18-M18)*10%,MAX(0,(L18-M18)*0%+(F18-5000000)*(70%-30%*0%))),IF(F18<=20000000,MIN((L18-M18)*15%,MAX(0,(L18-M18)*10%+(F18-10000000)*(70%-30%*10%))),IF(F18<=50000000,MIN((L18-M18)*25%,MAX(0,(L18-M18)*15%+(F18-20000000)*(70%-30%*15%))),MIN((L18-M18)*37%,MAX(0,(L18-M18)*25%+(F18-50000000)*(70%-30%*25%))))))))),2) -> 0 | O18: =ROUND((L18-M18+N18)*IF(OR(B18="2014-15",B18="2015-16",B18="2016-17",B18="2017-18"),3%,4%),2) -> 0 | P18: =ROUND(L18-M18+N18+O18,2) -> 0 | Q18: =ROUND(P18-K18,2) -> 0
A19: =5 -> 5 | B19: =Source_Data!A5 -> 2015-16 | C19: ="OLD" -> OLD | D19: =Source_Data!F5 -> Resident-Normal Citizen | E19: =Source_Data!B5 -> 0 | F19: =Source_Data!D5 -> 0 | G19: =ROUND(IF(C19="OLD",MAX(0,MIN(E19,500000)-IF(D19="Resident-Senior Citizen",300000,250000))*IF(B19="2016-17",10%,5%)+MAX(0,MIN(E19,1000000)-500000)*20%+MAX(0,E19-1000000)*30%,IF(OR(B19="2020-21",B19="2021-22",B19="2022-23"),MAX(0,MIN(E19,500000)-250000)*5%+MAX(0,MIN(E19,750000)-500000)*10%+MAX(0,MIN(E19,1000000)-750000)*15%+MAX(0,MIN(E19,1250000)-1000000)*20%+MAX(0,MIN(E19,1500000)-1250000)*25%+MAX(0,E19-1500000)*30%,IF(B19="2023-24",MAX(0,MIN(E19,600000)-300000)*5%+MAX(0,MIN(E19,900000)-600000)*10%+MAX(0,MIN(E19,1200000)-900000)*15%+MAX(0,MIN(E19,1500000)-1200000)*20%+MAX(0,E19-1500000)*30%,IF(B19="2024-25",MAX(0,MIN(E19,700000)-300000)*5%+MAX(0,MIN(E19,1000000)-700000)*10%+MAX(0,MIN(E19,1200000)-1000000)*15%+MAX(0,MIN(E19,1500000)-1200000)*20%+MAX(0,E19-1500000)*30%,IF(B19="2025-26",MAX(0,MIN(E19,800000)-400000)*5%+MAX(0,MIN(E19,1200000)-800000)*10%+MAX(0,MIN(E19,1600000)-1200000)*15%+MAX(0,MIN(E19,2000000)-1600000)*20%+MAX(0,MIN(E19,2400000)-2000000)*25%+MAX(0,E19-2400000)*30%,0))))),2) -> 0 | H19: =ROUND(MAX(IF(C19="OLD",IF(E19<=IF(OR(B19="2014-15",B19="2015-16",B19="2016-17"),500000,IF(OR(B19="2017-18",B19="2018-19"),350000,500000)),MIN(G19,IF(OR(B19="2014-15",B19="2015-16"),2000,IF(B19="2016-17",5000,IF(OR(B19="2017-18",B19="2018-19"),2500,12500)))),0),IF(E19<=IF(OR(B19="2023-24",B19="2024-25"),700000,IF(B19="2025-26",1200000,500000)),MIN(G19,IF(OR(B19="2023-24",B19="2024-25"),25000,IF(B19="2025-26",60000,12500))),0)),IF(AND(C19="NEW",B19="2025-26",E19>1200000),MAX(0,G19-(E19-1200000)),0)),2) -> 0 | I19: =ROUND(IF(C19="OLD",IF(OR(B19="2014-15",B19="2016-17"),IF(E19<=10000000,0,MIN((G19-H19)*15%,MAX(0,(G19-H19)*0%+(E19-10000000)*(70%-30%*0%)))),IF(B19="2015-16",IF(E19<=10000000,0,MIN((G19-H19)*12%,MAX(0,(G19-H19)*0%+(E19-10000000)*(70%-30%*0%)))),IF(OR(B19="2017-18",B19="2018-19"),IF(E19<=5000000,0,IF(E19<=10000000,MIN((G19-H19)*10%,MAX(0,(G19-H19)*0%+(E19-5000000)*(70%-30%*0%))),MIN((G19-H19)*15%,MAX(0,(G19-H19)*10%+(E19-10000000)*(70%-30%*10%))))),IF(E19<=5000000,0,IF(E19<=10000000,MIN((G19-H19)*10%,MAX(0,(G19-H19)*0%+(E19-5000000)*(70%-30%*0%))),IF(E19<=20000000,MIN((G19-H19)*15%,MAX(0,(G19-H19)*10%+(E19-10000000)*(70%-30%*10%))),IF(E19<=50000000,MIN((G19-H19)*25%,MAX(0,(G19-H19)*15%+(E19-20000000)*(70%-30%*15%))),MIN((G19-H19)*37%,MAX(0,(G19-H19)*25%+(E19-50000000)*(70%-30%*25%)))))))))),IF(OR(B19="2023-24",B19="2024-25",B19="2025-26"),IF(E19<=5000000,0,IF(E19<=10000000,MIN((G19-H19)*10%,MAX(0,(G19-H19)*0%+(E19-5000000)*(70%-30%*0%))),IF(E19<=20000000,MIN((G19-H19)*15%,MAX(0,(G19-H19)*10%+(E19-10000000)*(70%-30%*10%))),MIN((G19-H19)*25%,MAX(0,(G19-H19)*15%+(E19-20000000)*(70%-30%*15%)))))),IF(E19<=5000000,0,IF(E19<=10000000,MIN((G19-H19)*10%,MAX(0,(G19-H19)*0%+(E19-5000000)*(70%-30%*0%))),IF(E19<=20000000,MIN((G19-H19)*15%,MAX(0,(G19-H19)*10%+(E19-10000000)*(70%-30%*10%))),IF(E19<=50000000,MIN((G19-H19)*25%,MAX(0,(G19-H19)*15%+(E19-20000000)*(70%-30%*15%))),MIN((G19-H19)*37%,MAX(0,(G19-H19)*25%+(E19-50000000)*(70%-30%*25%))))))))),2) -> 0 | J19: =ROUND((G19-H19+I19)*IF(OR(B19="2014-15",B19="2015-16",B19="2016-17",B19="2017-18"),3%,4%),2) -> 0 | K19: =ROUND(G19-H19+I19+J19,2) -> 0 | L19: =ROUND(IF(C19="OLD",MAX(0,MIN(F19,500000)-IF(D19="Resident-Senior Citizen",300000,250000))*IF(B19="2016-17",10%,5%)+MAX(0,MIN(F19,1000000)-500000)*20%+MAX(0,F19-1000000)*30%,IF(OR(B19="2020-21",B19="2021-22",B19="2022-23"),MAX(0,MIN(F19,500000)-250000)*5%+MAX(0,MIN(F19,750000)-500000)*10%+MAX(0,MIN(F19,1000000)-750000)*15%+MAX(0,MIN(F19,1250000)-1000000)*20%+MAX(0,MIN(F19,1500000)-1250000)*25%+MAX(0,F19-1500000)*30%,IF(B19="2023-24",MAX(0,MIN(F19,600000)-300000)*5%+MAX(0,MIN(F19,900000)-600000)*10%+MAX(0,MIN(F19,1200000)-900000)*15%+MAX(0,MIN(F19,1500000)-1200000)*20%+MAX(0,F19-1500000)*30%,IF(B19="2024-25",MAX(0,MIN(F19,700000)-300000)*5%+MAX(0,MIN(F19,1000000)-700000)*10%+MAX(0,MIN(F19,1200000)-1000000)*15%+MAX(0,MIN(F19,1500000)-1200000)*20%+MAX(0,F19-1500000)*30%,IF(B19="2025-26",MAX(0,MIN(F19,800000)-400000)*5%+MAX(0,MIN(F19,1200000)-800000)*10%+MAX(0,MIN(F19,1600000)-1200000)*15%+MAX(0,MIN(F19,2000000)-1600000)*20%+MAX(0,MIN(F19,2400000)-2000000)*25%+MAX(0,F19-2400000)*30%,0))))),2) -> 0 | M19: =ROUND(MAX(IF(C19="OLD",IF(F19<=IF(OR(B19="2014-15",B19="2015-16",B19="2016-17"),500000,IF(OR(B19="2017-18",B19="2018-19"),350000,500000)),MIN(L19,IF(OR(B19="2014-15",B19="2015-16"),2000,IF(B19="2016-17",5000,IF(OR(B19="2017-18",B19="2018-19"),2500,12500)))),0),IF(F19<=IF(OR(B19="2023-24",B19="2024-25"),700000,IF(B19="2025-26",1200000,500000)),MIN(L19,IF(OR(B19="2023-24",B19="2024-25"),25000,IF(B19="2025-26",60000,12500))),0)),IF(AND(C19="NEW",B19="2025-26",F19>1200000),MAX(0,L19-(F19-1200000)),0)),2) -> 0 | N19: =ROUND(IF(C19="OLD",IF(OR(B19="2014-15",B19="2016-17"),IF(F19<=10000000,0,MIN((L19-M19)*15%,MAX(0,(L19-M19)*0%+(F19-10000000)*(70%-30%*0%)))),IF(B19="2015-16",IF(F19<=10000000,0,MIN((L19-M19)*12%,MAX(0,(L19-M19)*0%+(F19-10000000)*(70%-30%*0%)))),IF(OR(B19="2017-18",B19="2018-19"),IF(F19<=5000000,0,IF(F19<=10000000,MIN((L19-M19)*10%,MAX(0,(L19-M19)*0%+(F19-5000000)*(70%-30%*0%))),MIN((L19-M19)*15%,MAX(0,(L19-M19)*10%+(F19-10000000)*(70%-30%*10%))))),IF(F19<=5000000,0,IF(F19<=10000000,MIN((L19-M19)*10%,MAX(0,(L19-M19)*0%+(F19-5000000)*(70%-30%*0%))),IF(F19<=20000000,MIN((L19-M19)*15%,MAX(0,(L19-M19)*10%+(F19-10000000)*(70%-30%*10%))),IF(F19<=50000000,MIN((L19-M19)*25%,MAX(0,(L19-M19)*15%+(F19-20000000)*(70%-30%*15%))),MIN((L19-M19)*37%,MAX(0,(L19-M19)*25%+(F19-50000000)*(70%-30%*25%)))))))))),IF(OR(B19="2023-24",B19="2024-25",B19="2025-26"),IF(F19<=5000000,0,IF(F19<=10000000,MIN((L19-M19)*10%,MAX(0,(L19-M19)*0%+(F19-5000000)*(70%-30%*0%))),IF(F19<=20000000,MIN((L19-M19)*15%,MAX(0,(L19-M19)*10%+(F19-10000000)*(70%-30%*10%))),MIN((L19-M19)*25%,MAX(0,(L19-M19)*15%+(F19-20000000)*(70%-30%*15%)))))),IF(F19<=5000000,0,IF(F19<=10000000,MIN((L19-M19)*10%,MAX(0,(L19-M19)*0%+(F19-5000000)*(70%-30%*0%))),IF(F19<=20000000,MIN((L19-M19)*15%,MAX(0,(L19-M19)*10%+(F19-10000000)*(70%-30%*10%))),IF(F19<=50000000,MIN((L19-M19)*25%,MAX(0,(L19-M19)*15%+(F19-20000000)*(70%-30%*15%))),MIN((L19-M19)*37%,MAX(0,(L19-M19)*25%+(F19-50000000)*(70%-30%*25%))))))))),2) -> 0 | O19: =ROUND((L19-M19+N19)*IF(OR(B19="2014-15",B19="2015-16",B19="2016-17",B19="2017-18"),3%,4%),2) -> 0 | P19: =ROUND(L19-M19+N19+O19,2) -> 0 | Q19: =ROUND(P19-K19,2) -> 0
A20: =6 -> 6 | B20: =Source_Data!A6 -> 2016-17 | C20: ="OLD" -> OLD | D20: =Source_Data!F6 -> Resident-Senior Citizen | E20: =Source_Data!B6 -> 0 | F20: =Source_Data!D6 -> 0 | G20: =ROUND(IF(C20="OLD",MAX(0,MIN(E20,500000)-IF(D20="Resident-Senior Citizen",300000,250000))*IF(B20="2016-17",10%,5%)+MAX(0,MIN(E20,1000000)-500000)*20%+MAX(0,E20-1000000)*30%,IF(OR(B20="2020-21",B20="2021-22",B20="2022-23"),MAX(0,MIN(E20,500000)-250000)*5%+MAX(0,MIN(E20,750000)-500000)*10%+MAX(0,MIN(E20,1000000)-750000)*15%+MAX(0,MIN(E20,1250000)-1000000)*20%+MAX(0,MIN(E20,1500000)-1250000)*25%+MAX(0,E20-1500000)*30%,IF(B20="2023-24",MAX(0,MIN(E20,600000)-300000)*5%+MAX(0,MIN(E20,900000)-600000)*10%+MAX(0,MIN(E20,1200000)-900000)*15%+MAX(0,MIN(E20,1500000)-1200000)*20%+MAX(0,E20-1500000)*30%,IF(B20="2024-25",MAX(0,MIN(E20,700000)-300000)*5%+MAX(0,MIN(E20,1000000)-700000)*10%+MAX(0,MIN(E20,1200000)-1000000)*15%+MAX(0,MIN(E20,1500000)-1200000)*20%+MAX(0,E20-1500000)*30%,IF(B20="2025-26",MAX(0,MIN(E20,800000)-400000)*5%+MAX(0,MIN(E20,1200000)-800000)*10%+MAX(0,MIN(E20,1600000)-1200000)*15%+MAX(0,MIN(E20,2000000)-1600000)*20%+MAX(0,MIN(E20,2400000)-2000000)*25%+MAX(0,E20-2400000)*30%,0))))),2) -> 0 | H20: =ROUND(MAX(IF(C20="OLD",IF(E20<=IF(OR(B20="2014-15",B20="2015-16",B20="2016-17"),500000,IF(OR(B20="2017-18",B20="2018-19"),350000,500000)),MIN(G20,IF(OR(B20="2014-15",B20="2015-16"),2000,IF(B20="2016-17",5000,IF(OR(B20="2017-18",B20="2018-19"),2500,12500)))),0),IF(E20<=IF(OR(B20="2023-24",B20="2024-25"),700000,IF(B20="2025-26",1200000,500000)),MIN(G20,IF(OR(B20="2023-24",B20="2024-25"),25000,IF(B20="2025-26",60000,12500))),0)),IF(AND(C20="NEW",B20="2025-26",E20>1200000),MAX(0,G20-(E20-1200000)),0)),2) -> 0 | I20: =ROUND(IF(C20="OLD",IF(OR(B20="2014-15",B20="2016-17"),IF(E20<=10000000,0,MIN((G20-H20)*15%,MAX(0,(G20-H20)*0%+(E20-10000000)*(70%-30%*0%)))),IF(B20="2015-16",IF(E20<=10000000,0,MIN((G20-H20)*12%,MAX(0,(G20-H20)*0%+(E20-10000000)*(70%-30%*0%)))),IF(OR(B20="2017-18",B20="2018-19"),IF(E20<=5000000,0,IF(E20<=10000000,MIN((G20-H20)*10%,MAX(0,(G20-H20)*0%+(E20-5000000)*(70%-30%*0%))),MIN((G20-H20)*15%,MAX(0,(G20-H20)*10%+(E20-10000000)*(70%-30%*10%))))),IF(E20<=5000000,0,IF(E20<=10000000,MIN((G20-H20)*10%,MAX(0,(G20-H20)*0%+(E20-5000000)*(70%-30%*0%))),IF(E20<=20000000,MIN((G20-H20)*15%,MAX(0,(G20-H20)*10%+(E20-10000000)*(70%-30%*10%))),IF(E20<=50000000,MIN((G20-H20)*25%,MAX(0,(G20-H20)*15%+(E20-20000000)*(70%-30%*15%))),MIN((G20-H20)*37%,MAX(0,(G20-H20)*25%+(E20-50000000)*(70%-30%*25%)))))))))),IF(OR(B20="2023-24",B20="2024-25",B20="2025-26"),IF(E20<=5000000,0,IF(E20<=10000000,MIN((G20-H20)*10%,MAX(0,(G20-H20)*0%+(E20-5000000)*(70%-30%*0%))),IF(E20<=20000000,MIN((G20-H20)*15%,MAX(0,(G20-H20)*10%+(E20-10000000)*(70%-30%*10%))),MIN((G20-H20)*25%,MAX(0,(G20-H20)*15%+(E20-20000000)*(70%-30%*15%)))))),IF(E20<=5000000,0,IF(E20<=10000000,MIN((G20-H20)*10%,MAX(0,(G20-H20)*0%+(E20-5000000)*(70%-30%*0%))),IF(E20<=20000000,MIN((G20-H20)*15%,MAX(0,(G20-H20)*10%+(E20-10000000)*(70%-30%*10%))),IF(E20<=50000000,MIN((G20-H20)*25%,MAX(0,(G20-H20)*15%+(E20-20000000)*(70%-30%*15%))),MIN((G20-H20)*37%,MAX(0,(G20-H20)*25%+(E20-50000000)*(70%-30%*25%))))))))),2) -> 0 | J20: =ROUND((G20-H20+I20)*IF(OR(B20="2014-15",B20="2015-16",B20="2016-17",B20="2017-18"),3%,4%),2) -> 0 | K20: =ROUND(G20-H20+I20+J20,2) -> 0 | L20: =ROUND(IF(C20="OLD",MAX(0,MIN(F20,500000)-IF(D20="Resident-Senior Citizen",300000,250000))*IF(B20="2016-17",10%,5%)+MAX(0,MIN(F20,1000000)-500000)*20%+MAX(0,F20-1000000)*30%,IF(OR(B20="2020-21",B20="2021-22",B20="2022-23"),MAX(0,MIN(F20,500000)-250000)*5%+MAX(0,MIN(F20,750000)-500000)*10%+MAX(0,MIN(F20,1000000)-750000)*15%+MAX(0,MIN(F20,1250000)-1000000)*20%+MAX(0,MIN(F20,1500000)-1250000)*25%+MAX(0,F20-1500000)*30%,IF(B20="2023-24",MAX(0,MIN(F20,600000)-300000)*5%+MAX(0,MIN(F20,900000)-600000)*10%+MAX(0,MIN(F20,1200000)-900000)*15%+MAX(0,MIN(F20,1500000)-1200000)*20%+MAX(0,F20-1500000)*30%,IF(B20="2024-25",MAX(0,MIN(F20,700000)-300000)*5%+MAX(0,MIN(F20,1000000)-700000)*10%+MAX(0,MIN(F20,1200000)-1000000)*15%+MAX(0,MIN(F20,1500000)-1200000)*20%+MAX(0,F20-1500000)*30%,IF(B20="2025-26",MAX(0,MIN(F20,800000)-400000)*5%+MAX(0,MIN(F20,1200000)-800000)*10%+MAX(0,MIN(F20,1600000)-1200000)*15%+MAX(0,MIN(F20,2000000)-1600000)*20%+MAX(0,MIN(F20,2400000)-2000000)*25%+MAX(0,F20-2400000)*30%,0))))),2) -> 0 | M20: =ROUND(MAX(IF(C20="OLD",IF(F20<=IF(OR(B20="2014-15",B20="2015-16",B20="2016-17"),500000,IF(OR(B20="2017-18",B20="2018-19"),350000,500000)),MIN(L20,IF(OR(B20="2014-15",B20="2015-16"),2000,IF(B20="2016-17",5000,IF(OR(B20="2017-18",B20="2018-19"),2500,12500)))),0),IF(F20<=IF(OR(B20="2023-24",B20="2024-25"),700000,IF(B20="2025-26",1200000,500000)),MIN(L20,IF(OR(B20="2023-24",B20="2024-25"),25000,IF(B20="2025-26",60000,12500))),0)),IF(AND(C20="NEW",B20="2025-26",F20>1200000),MAX(0,L20-(F20-1200000)),0)),2) -> 0 | N20: =ROUND(IF(C20="OLD",IF(OR(B20="2014-15",B20="2016-17"),IF(F20<=10000000,0,MIN((L20-M20)*15%,MAX(0,(L20-M20)*0%+(F20-10000000)*(70%-30%*0%)))),IF(B20="2015-16",IF(F20<=10000000,0,MIN((L20-M20)*12%,MAX(0,(L20-M20)*0%+(F20-10000000)*(70%-30%*0%)))),IF(OR(B20="2017-18",B20="2018-19"),IF(F20<=5000000,0,IF(F20<=10000000,MIN((L20-M20)*10%,MAX(0,(L20-M20)*0%+(F20-5000000)*(70%-30%*0%))),MIN((L20-M20)*15%,MAX(0,(L20-M20)*10%+(F20-10000000)*(70%-30%*10%))))),IF(F20<=5000000,0,IF(F20<=10000000,MIN((L20-M20)*10%,MAX(0,(L20-M20)*0%+(F20-5000000)*(70%-30%*0%))),IF(F20<=20000000,MIN((L20-M20)*15%,MAX(0,(L20-M20)*10%+(F20-10000000)*(70%-30%*10%))),IF(F20<=50000000,MIN((L20-M20)*25%,MAX(0,(L20-M20)*15%+(F20-20000000)*(70%-30%*15%))),MIN((L20-M20)*37%,MAX(0,(L20-M20)*25%+(F20-50000000)*(70%-30%*25%)))))))))),IF(OR(B20="2023-24",B20="2024-25",B20="2025-26"),IF(F20<=5000000,0,IF(F20<=10000000,MIN((L20-M20)*10%,MAX(0,(L20-M20)*0%+(F20-5000000)*(70%-30%*0%))),IF(F20<=20000000,MIN((L20-M20)*15%,MAX(0,(L20-M20)*10%+(F20-10000000)*(70%-30%*10%))),MIN((L20-M20)*25%,MAX(0,(L20-M20)*15%+(F20-20000000)*(70%-30%*15%)))))),IF(F20<=5000000,0,IF(F20<=10000000,MIN((L20-M20)*10%,MAX(0,(L20-M20)*0%+(F20-5000000)*(70%-30%*0%))),IF(F20<=20000000,MIN((L20-M20)*15%,MAX(0,(L20-M20)*10%+(F20-10000000)*(70%-30%*10%))),IF(F20<=50000000,MIN((L20-M20)*25%,MAX(0,(L20-M20)*15%+(F20-20000000)*(70%-30%*15%))),MIN((L20-M20)*37%,MAX(0,(L20-M20)*25%+(F20-50000000)*(70%-30%*25%))))))))),2) -> 0 | O20: =ROUND((L20-M20+N20)*IF(OR(B20="2014-15",B20="2015-16",B20="2016-17",B20="2017-18"),3%,4%),2) -> 0 | P20: =ROUND(L20-M20+N20+O20,2) -> 0 | Q20: =ROUND(P20-K20,2) -> 0
A21: =7 -> 7 | B21: =Source_Data!A7 -> 2017-18 | C21: ="OLD" -> OLD | D21: =Source_Data!F7 -> Resident-Senior Citizen | E21: =Source_Data!B7 -> 0 | F21: =Source_Data!D7 -> 0 | G21: =ROUND(IF(C21="OLD",MAX(0,MIN(E21,500000)-IF(D21="Resident-Senior Citizen",300000,250000))*IF(B21="2016-17",10%,5%)+MAX(0,MIN(E21,1000000)-500000)*20%+MAX(0,E21-1000000)*30%,IF(OR(B21="2020-21",B21="2021-22",B21="2022-23"),MAX(0,MIN(E21,500000)-250000)*5%+MAX(0,MIN(E21,750000)-500000)*10%+MAX(0,MIN(E21,1000000)-750000)*15%+MAX(0,MIN(E21,1250000)-1000000)*20%+MAX(0,MIN(E21,1500000)-1250000)*25%+MAX(0,E21-1500000)*30%,IF(B21="2023-24",MAX(0,MIN(E21,600000)-300000)*5%+MAX(0,MIN(E21,900000)-600000)*10%+MAX(0,MIN(E21,1200000)-900000)*15%+MAX(0,MIN(E21,1500000)-1200000)*20%+MAX(0,E21-1500000)*30%,IF(B21="2024-25",MAX(0,MIN(E21,700000)-300000)*5%+MAX(0,MIN(E21,1000000)-700000)*10%+MAX(0,MIN(E21,1200000)-1000000)*15%+MAX(0,MIN(E21,1500000)-1200000)*20%+MAX(0,E21-1500000)*30%,IF(B21="2025-26",MAX(0,MIN(E21,800000)-400000)*5%+MAX(0,MIN(E21,1200000)-800000)*10%+MAX(0,MIN(E21,1600000)-1200000)*15%+MAX(0,MIN(E21,2000000)-1600000)*20%+MAX(0,MIN(E21,2400000)-2000000)*25%+MAX(0,E21-2400000)*30%,0))))),2) -> 0 | H21: =ROUND(MAX(IF(C21="OLD",IF(E21<=IF(OR(B21="2014-15",B21="2015-16",B21="2016-17"),500000,IF(OR(B21="2017-18",B21="2018-19"),350000,500000)),MIN(G21,IF(OR(B21="2014-15",B21="2015-16"),2000,IF(B21="2016-17",5000,IF(OR(B21="2017-18",B21="2018-19"),2500,12500)))),0),IF(E21<=IF(OR(B21="2023-24",B21="2024-25"),700000,IF(B21="2025-26",1200000,500000)),MIN(G21,IF(OR(B21="2023-24",B21="2024-25"),25000,IF(B21="2025-26",60000,12500))),0)),IF(AND(C21="NEW",B21="2025-26",E21>1200000),MAX(0,G21-(E21-1200000)),0)),2) -> 0 | I21: =ROUND(IF(C21="OLD",IF(OR(B21="2014-15",B21="2016-17"),IF(E21<=10000000,0,MIN((G21-H21)*15%,MAX(0,(G21-H21)*0%+(E21-10000000)*(70%-30%*0%)))),IF(B21="2015-16",IF(E21<=10000000,0,MIN((G21-H21)*12%,MAX(0,(G21-H21)*0%+(E21-10000000)*(70%-30%*0%)))),IF(OR(B21="2017-18",B21="2018-19"),IF(E21<=5000000,0,IF(E21<=10000000,MIN((G21-H21)*10%,MAX(0,(G21-H21)*0%+(E21-5000000)*(70%-30%*0%))),MIN((G21-H21)*15%,MAX(0,(G21-H21)*10%+(E21-10000000)*(70%-30%*10%))))),IF(E21<=5000000,0,IF(E21<=10000000,MIN((G21-H21)*10%,MAX(0,(G21-H21)*0%+(E21-5000000)*(70%-30%*0%))),IF(E21<=20000000,MIN((G21-H21)*15%,MAX(0,(G21-H21)*10%+(E21-10000000)*(70%-30%*10%))),IF(E21<=50000000,MIN((G21-H21)*25%,MAX(0,(G21-H21)*15%+(E21-20000000)*(70%-30%*15%))),MIN((G21-H21)*37%,MAX(0,(G21-H21)*25%+(E21-50000000)*(70%-30%*25%)))))))))),IF(OR(B21="2023-24",B21="2024-25",B21="2025-26"),IF(E21<=5000000,0,IF(E21<=10000000,MIN((G21-H21)*10%,MAX(0,(G21-H21)*0%+(E21-5000000)*(70%-30%*0%))),IF(E21<=20000000,MIN((G21-H21)*15%,MAX(0,(G21-H21)*10%+(E21-10000000)*(70%-30%*10%))),MIN((G21-H21)*25%,MAX(0,(G21-H21)*15%+(E21-20000000)*(70%-30%*15%)))))),IF(E21<=5000000,0,IF(E21<=10000000,MIN((G21-H21)*10%,MAX(0,(G21-H21)*0%+(E21-5000000)*(70%-30%*0%))),IF(E21<=20000000,MIN((G21-H21)*15%,MAX(0,(G21-H21)*10%+(E21-10000000)*(70%-30%*10%))),IF(E21<=50000000,MIN((G21-H21)*25%,MAX(0,(G21-H21)*15%+(E21-20000000)*(70%-30%*15%))),MIN((G21-H21)*37%,MAX(0,(G21-H21)*25%+(E21-50000000)*(70%-30%*25%))))))))),2) -> 0 | J21: =ROUND((G21-H21+I21)*IF(OR(B21="2014-15",B21="2015-16",B21="2016-17",B21="2017-18"),3%,4%),2) -> 0 | K21: =ROUND(G21-H21+I21+J21,2) -> 0 | L21: =ROUND(IF(C21="OLD",MAX(0,MIN(F21,500000)-IF(D21="Resident-Senior Citizen",300000,250000))*IF(B21="2016-17",10%,5%)+MAX(0,MIN(F21,1000000)-500000)*20%+MAX(0,F21-1000000)*30%,IF(OR(B21="2020-21",B21="2021-22",B21="2022-23"),MAX(0,MIN(F21,500000)-250000)*5%+MAX(0,MIN(F21,750000)-500000)*10%+MAX(0,MIN(F21,1000000)-750000)*15%+MAX(0,MIN(F21,1250000)-1000000)*20%+MAX(0,MIN(F21,1500000)-1250000)*25%+MAX(0,F21-1500000)*30%,IF(B21="2023-24",MAX(0,MIN(F21,600000)-300000)*5%+MAX(0,MIN(F21,900000)-600000)*10%+MAX(0,MIN(F21,1200000)-900000)*15%+MAX(0,MIN(F21,1500000)-1200000)*20%+MAX(0,F21-1500000)*30%,IF(B21="2024-25",MAX(0,MIN(F21,700000)-300000)*5%+MAX(0,MIN(F21,1000000)-700000)*10%+MAX(0,MIN(F21,1200000)-1000000)*15%+MAX(0,MIN(F21,1500000)-1200000)*20%+MAX(0,F21-1500000)*30%,IF(B21="2025-26",MAX(0,MIN(F21,800000)-400000)*5%+MAX(0,MIN(F21,1200000)-800000)*10%+MAX(0,MIN(F21,1600000)-1200000)*15%+MAX(0,MIN(F21,2000000)-1600000)*20%+MAX(0,MIN(F21,2400000)-2000000)*25%+MAX(0,F21-2400000)*30%,0))))),2) -> 0 | M21: =ROUND(MAX(IF(C21="OLD",IF(F21<=IF(OR(B21="2014-15",B21="2015-16",B21="2016-17"),500000,IF(OR(B21="2017-18",B21="2018-19"),350000,500000)),MIN(L21,IF(OR(B21="2014-15",B21="2015-16"),2000,IF(B21="2016-17",5000,IF(OR(B21="2017-18",B21="2018-19"),2500,12500)))),0),IF(F21<=IF(OR(B21="2023-24",B21="2024-25"),700000,IF(B21="2025-26",1200000,500000)),MIN(L21,IF(OR(B21="2023-24",B21="2024-25"),25000,IF(B21="2025-26",60000,12500))),0)),IF(AND(C21="NEW",B21="2025-26",F21>1200000),MAX(0,L21-(F21-1200000)),0)),2) -> 0 | N21: =ROUND(IF(C21="OLD",IF(OR(B21="2014-15",B21="2016-17"),IF(F21<=10000000,0,MIN((L21-M21)*15%,MAX(0,(L21-M21)*0%+(F21-10000000)*(70%-30%*0%)))),IF(B21="2015-16",IF(F21<=10000000,0,MIN((L21-M21)*12%,MAX(0,(L21-M21)*0%+(F21-10000000)*(70%-30%*0%)))),IF(OR(B21="2017-18",B21="2018-19"),IF(F21<=5000000,0,IF(F21<=10000000,MIN((L21-M21)*10%,MAX(0,(L21-M21)*0%+(F21-5000000)*(70%-30%*0%))),MIN((L21-M21)*15%,MAX(0,(L21-M21)*10%+(F21-10000000)*(70%-30%*10%))))),IF(F21<=5000000,0,IF(F21<=10000000,MIN((L21-M21)*10%,MAX(0,(L21-M21)*0%+(F21-5000000)*(70%-30%*0%))),IF(F21<=20000000,MIN((L21-M21)*15%,MAX(0,(L21-M21)*10%+(F21-10000000)*(70%-30%*10%))),IF(F21<=50000000,MIN((L21-M21)*25%,MAX(0,(L21-M21)*15%+(F21-20000000)*(70%-30%*15%))),MIN((L21-M21)*37%,MAX(0,(L21-M21)*25%+(F21-50000000)*(70%-30%*25%)))))))))),IF(OR(B21="2023-24",B21="2024-25",B21="2025-26"),IF(F21<=5000000,0,IF(F21<=10000000,MIN((L21-M21)*10%,MAX(0,(L21-M21)*0%+(F21-5000000)*(70%-30%*0%))),IF(F21<=20000000,MIN((L21-M21)*15%,MAX(0,(L21-M21)*10%+(F21-10000000)*(70%-30%*10%))),MIN((L21-M21)*25%,MAX(0,(L21-M21)*15%+(F21-20000000)*(70%-30%*15%)))))),IF(F21<=5000000,0,IF(F21<=10000000,MIN((L21-M21)*10%,MAX(0,(L21-M21)*0%+(F21-5000000)*(70%-30%*0%))),IF(F21<=20000000,MIN((L21-M21)*15%,MAX(0,(L21-M21)*10%+(F21-10000000)*(70%-30%*10%))),IF(F21<=50000000,MIN((L21-M21)*25%,MAX(0,(L21-M21)*15%+(F21-20000000)*(70%-30%*15%))),MIN((L21-M21)*37%,MAX(0,(L21-M21)*25%+(F21-50000000)*(70%-30%*25%))))))))),2) -> 0 | O21: =ROUND((L21-M21+N21)*IF(OR(B21="2014-15",B21="2015-16",B21="2016-17",B21="2017-18"),3%,4%),2) -> 0 | P21: =ROUND(L21-M21+N21+O21,2) -> 0 | Q21: =ROUND(P21-K21,2) -> 0
A22: =8 -> 8 | B22: =Source_Data!A8 -> 2018-19 | C22: ="OLD" -> OLD | D22: =Source_Data!F8 -> Resident-Normal Citizen | E22: =Source_Data!B8 -> 0 | F22: =Source_Data!D8 -> 0 | G22: =ROUND(IF(C22="OLD",MAX(0,MIN(E22,500000)-IF(D22="Resident-Senior Citizen",300000,250000))*IF(B22="2016-17",10%,5%)+MAX(0,MIN(E22,1000000)-500000)*20%+MAX(0,E22-1000000)*30%,IF(OR(B22="2020-21",B22="2021-22",B22="2022-23"),MAX(0,MIN(E22,500000)-250000)*5%+MAX(0,MIN(E22,750000)-500000)*10%+MAX(0,MIN(E22,1000000)-750000)*15%+MAX(0,MIN(E22,1250000)-1000000)*20%+MAX(0,MIN(E22,1500000)-1250000)*25%+MAX(0,E22-1500000)*30%,IF(B22="2023-24",MAX(0,MIN(E22,600000)-300000)*5%+MAX(0,MIN(E22,900000)-600000)*10%+MAX(0,MIN(E22,1200000)-900000)*15%+MAX(0,MIN(E22,1500000)-1200000)*20%+MAX(0,E22-1500000)*30%,IF(B22="2024-25",MAX(0,MIN(E22,700000)-300000)*5%+MAX(0,MIN(E22,1000000)-700000)*10%+MAX(0,MIN(E22,1200000)-1000000)*15%+MAX(0,MIN(E22,1500000)-1200000)*20%+MAX(0,E22-1500000)*30%,IF(B22="2025-26",MAX(0,MIN(E22,800000)-400000)*5%+MAX(0,MIN(E22,1200000)-800000)*10%+MAX(0,MIN(E22,1600000)-1200000)*15%+MAX(0,MIN(E22,2000000)-1600000)*20%+MAX(0,MIN(E22,2400000)-2000000)*25%+MAX(0,E22-2400000)*30%,0))))),2) -> 0 | H22: =ROUND(MAX(IF(C22="OLD",IF(E22<=IF(OR(B22="2014-15",B22="2015-16",B22="2016-17"),500000,IF(OR(B22="2017-18",B22="2018-19"),350000,500000)),MIN(G22,IF(OR(B22="2014-15",B22="2015-16"),2000,IF(B22="2016-17",5000,IF(OR(B22="2017-18",B22="2018-19"),2500,12500)))),0),IF(E22<=IF(OR(B22="2023-24",B22="2024-25"),700000,IF(B22="2025-26",1200000,500000)),MIN(G22,IF(OR(B22="2023-24",B22="2024-25"),25000,IF(B22="2025-26",60000,12500))),0)),IF(AND(C22="NEW",B22="2025-26",E22>1200000),MAX(0,G22-(E22-1200000)),0)),2) -> 0 | I22: =ROUND(IF(C22="OLD",IF(OR(B22="2014-15",B22="2016-17"),IF(E22<=10000000,0,MIN((G22-H22)*15%,MAX(0,(G22-H22)*0%+(E22-10000000)*(70%-30%*0%)))),IF(B22="2015-16",IF(E22<=10000000,0,MIN((G22-H22)*12%,MAX(0,(G22-H22)*0%+(E22-10000000)*(70%-30%*0%)))),IF(OR(B22="2017-18",B22="2018-19"),IF(E22<=5000000,0,IF(E22<=10000000,MIN((G22-H22)*10%,MAX(0,(G22-H22)*0%+(E22-5000000)*(70%-30%*0%))),MIN((G22-H22)*15%,MAX(0,(G22-H22)*10%+(E22-10000000)*(70%-30%*10%))))),IF(E22<=5000000,0,IF(E22<=10000000,MIN((G22-H22)*10%,MAX(0,(G22-H22)*0%+(E22-5000000)*(70%-30%*0%))),IF(E22<=20000000,MIN((G22-H22)*15%,MAX(0,(G22-H22)*10%+(E22-10000000)*(70%-30%*10%))),IF(E22<=50000000,MIN((G22-H22)*25%,MAX(0,(G22-H22)*15%+(E22-20000000)*(70%-30%*15%))),MIN((G22-H22)*37%,MAX(0,(G22-H22)*25%+(E22-50000000)*(70%-30%*25%)))))))))),IF(OR(B22="2023-24",B22="2024-25",B22="2025-26"),IF(E22<=5000000,0,IF(E22<=10000000,MIN((G22-H22)*10%,MAX(0,(G22-H22)*0%+(E22-5000000)*(70%-30%*0%))),IF(E22<=20000000,MIN((G22-H22)*15%,MAX(0,(G22-H22)*10%+(E22-10000000)*(70%-30%*10%))),MIN((G22-H22)*25%,MAX(0,(G22-H22)*15%+(E22-20000000)*(70%-30%*15%)))))),IF(E22<=5000000,0,IF(E22<=10000000,MIN((G22-H22)*10%,MAX(0,(G22-H22)*0%+(E22-5000000)*(70%-30%*0%))),IF(E22<=20000000,MIN((G22-H22)*15%,MAX(0,(G22-H22)*10%+(E22-10000000)*(70%-30%*10%))),IF(E22<=50000000,MIN((G22-H22)*25%,MAX(0,(G22-H22)*15%+(E22-20000000)*(70%-30%*15%))),MIN((G22-H22)*37%,MAX(0,(G22-H22)*25%+(E22-50000000)*(70%-30%*25%))))))))),2) -> 0 | J22: =ROUND((G22-H22+I22)*IF(OR(B22="2014-15",B22="2015-16",B22="2016-17",B22="2017-18"),3%,4%),2) -> 0 | K22: =ROUND(G22-H22+I22+J22,2) -> 0 | L22: =ROUND(IF(C22="OLD",MAX(0,MIN(F22,500000)-IF(D22="Resident-Senior Citizen",300000,250000))*IF(B22="2016-17",10%,5%)+MAX(0,MIN(F22,1000000)-500000)*20%+MAX(0,F22-1000000)*30%,IF(OR(B22="2020-21",B22="2021-22",B22="2022-23"),MAX(0,MIN(F22,500000)-250000)*5%+MAX(0,MIN(F22,750000)-500000)*10%+MAX(0,MIN(F22,1000000)-750000)*15%+MAX(0,MIN(F22,1250000)-1000000)*20%+MAX(0,MIN(F22,1500000)-1250000)*25%+MAX(0,F22-1500000)*30%,IF(B22="2023-24",MAX(0,MIN(F22,600000)-300000)*5%+MAX(0,MIN(F22,900000)-600000)*10%+MAX(0,MIN(F22,1200000)-900000)*15%+MAX(0,MIN(F22,1500000)-1200000)*20%+MAX(0,F22-1500000)*30%,IF(B22="2024-25",MAX(0,MIN(F22,700000)-300000)*5%+MAX(0,MIN(F22,1000000)-700000)*10%+MAX(0,MIN(F22,1200000)-1000000)*15%+MAX(0,MIN(F22,1500000)-1200000)*20%+MAX(0,F22-1500000)*30%,IF(B22="2025-26",MAX(0,MIN(F22,800000)-400000)*5%+MAX(0,MIN(F22,1200000)-800000)*10%+MAX(0,MIN(F22,1600000)-1200000)*15%+MAX(0,MIN(F22,2000000)-1600000)*20%+MAX(0,MIN(F22,2400000)-2000000)*25%+MAX(0,F22-2400000)*30%,0))))),2) -> 0 | M22: =ROUND(MAX(IF(C22="OLD",IF(F22<=IF(OR(B22="2014-15",B22="2015-16",B22="2016-17"),500000,IF(OR(B22="2017-18",B22="2018-19"),350000,500000)),MIN(L22,IF(OR(B22="2014-15",B22="2015-16"),2000,IF(B22="2016-17",5000,IF(OR(B22="2017-18",B22="2018-19"),2500,12500)))),0),IF(F22<=IF(OR(B22="2023-24",B22="2024-25"),700000,IF(B22="2025-26",1200000,500000)),MIN(L22,IF(OR(B22="2023-24",B22="2024-25"),25000,IF(B22="2025-26",60000,12500))),0)),IF(AND(C22="NEW",B22="2025-26",F22>1200000),MAX(0,L22-(F22-1200000)),0)),2) -> 0 | N22: =ROUND(IF(C22="OLD",IF(OR(B22="2014-15",B22="2016-17"),IF(F22<=10000000,0,MIN((L22-M22)*15%,MAX(0,(L22-M22)*0%+(F22-10000000)*(70%-30%*0%)))),IF(B22="2015-16",IF(F22<=10000000,0,MIN((L22-M22)*12%,MAX(0,(L22-M22)*0%+(F22-10000000)*(70%-30%*0%)))),IF(OR(B22="2017-18",B22="2018-19"),IF(F22<=5000000,0,IF(F22<=10000000,MIN((L22-M22)*10%,MAX(0,(L22-M22)*0%+(F22-5000000)*(70%-30%*0%))),MIN((L22-M22)*15%,MAX(0,(L22-M22)*10%+(F22-10000000)*(70%-30%*10%))))),IF(F22<=5000000,0,IF(F22<=10000000,MIN((L22-M22)*10%,MAX(0,(L22-M22)*0%+(F22-5000000)*(70%-30%*0%))),IF(F22<=20000000,MIN((L22-M22)*15%,MAX(0,(L22-M22)*10%+(F22-10000000)*(70%-30%*10%))),IF(F22<=50000000,MIN((L22-M22)*25%,MAX(0,(L22-M22)*15%+(F22-20000000)*(70%-30%*15%))),MIN((L22-M22)*37%,MAX(0,(L22-M22)*25%+(F22-50000000)*(70%-30%*25%)))))))))),IF(OR(B22="2023-24",B22="2024-25",B22="2025-26"),IF(F22<=5000000,0,IF(F22<=10000000,MIN((L22-M22)*10%,MAX(0,(L22-M22)*0%+(F22-5000000)*(70%-30%*0%))),IF(F22<=20000000,MIN((L22-M22)*15%,MAX(0,(L22-M22)*10%+(F22-10000000)*(70%-30%*10%))),MIN((L22-M22)*25%,MAX(0,(L22-M22)*15%+(F22-20000000)*(70%-30%*15%)))))),IF(F22<=5000000,0,IF(F22<=10000000,MIN((L22-M22)*10%,MAX(0,(L22-M22)*0%+(F22-5000000)*(70%-30%*0%))),IF(F22<=20000000,MIN((L22-M22)*15%,MAX(0,(L22-M22)*10%+(F22-10000000)*(70%-30%*10%))),IF(F22<=50000000,MIN((L22-M22)*25%,MAX(0,(L22-M22)*15%+(F22-20000000)*(70%-30%*15%))),MIN((L22-M22)*37%,MAX(0,(L22-M22)*25%+(F22-50000000)*(70%-30%*25%))))))))),2) -> 0 | O22: =ROUND((L22-M22+N22)*IF(OR(B22="2014-15",B22="2015-16",B22="2016-17",B22="2017-18"),3%,4%),2) -> 0 | P22: =ROUND(L22-M22+N22+O22,2) -> 0 | Q22: =ROUND(P22-K22,2) -> 0
A23: =9 -> 9 | B23: =Source_Data!A9 -> 2019-20 | C23: ="OLD" -> OLD | D23: =Source_Data!F9 -> Resident-Normal Citizen | E23: =Source_Data!B9 -> 0 | F23: =Source_Data!D9 -> 0 | G23: =ROUND(IF(C23="OLD",MAX(0,MIN(E23,500000)-IF(D23="Resident-Senior Citizen",300000,250000))*IF(B23="2016-17",10%,5%)+MAX(0,MIN(E23,1000000)-500000)*20%+MAX(0,E23-1000000)*30%,IF(OR(B23="2020-21",B23="2021-22",B23="2022-23"),MAX(0,MIN(E23,500000)-250000)*5%+MAX(0,MIN(E23,750000)-500000)*10%+MAX(0,MIN(E23,1000000)-750000)*15%+MAX(0,MIN(E23,1250000)-1000000)*20%+MAX(0,MIN(E23,1500000)-1250000)*25%+MAX(0,E23-1500000)*30%,IF(B23="2023-24",MAX(0,MIN(E23,600000)-300000)*5%+MAX(0,MIN(E23,900000)-600000)*10%+MAX(0,MIN(E23,1200000)-900000)*15%+MAX(0,MIN(E23,1500000)-1200000)*20%+MAX(0,E23-1500000)*30%,IF(B23="2024-25",MAX(0,MIN(E23,700000)-300000)*5%+MAX(0,MIN(E23,1000000)-700000)*10%+MAX(0,MIN(E23,1200000)-1000000)*15%+MAX(0,MIN(E23,1500000)-1200000)*20%+MAX(0,E23-1500000)*30%,IF(B23="2025-26",MAX(0,MIN(E23,800000)-400000)*5%+MAX(0,MIN(E23,1200000)-800000)*10%+MAX(0,MIN(E23,1600000)-1200000)*15%+MAX(0,MIN(E23,2000000)-1600000)*20%+MAX(0,MIN(E23,2400000)-2000000)*25%+MAX(0,E23-2400000)*30%,0))))),2) -> 0 | H23: =ROUND(MAX(IF(C23="OLD",IF(E23<=IF(OR(B23="2014-15",B23="2015-16",B23="2016-17"),500000,IF(OR(B23="2017-18",B23="2018-19"),350000,500000)),MIN(G23,IF(OR(B23="2014-15",B23="2015-16"),2000,IF(B23="2016-17",5000,IF(OR(B23="2017-18",B23="2018-19"),2500,12500)))),0),IF(E23<=IF(OR(B23="2023-24",B23="2024-25"),700000,IF(B23="2025-26",1200000,500000)),MIN(G23,IF(OR(B23="2023-24",B23="2024-25"),25000,IF(B23="2025-26",60000,12500))),0)),IF(AND(C23="NEW",B23="2025-26",E23>1200000),MAX(0,G23-(E23-1200000)),0)),2) -> 0 | I23: =ROUND(IF(C23="OLD",IF(OR(B23="2014-15",B23="2016-17"),IF(E23<=10000000,0,MIN((G23-H23)*15%,MAX(0,(G23-H23)*0%+(E23-10000000)*(70%-30%*0%)))),IF(B23="2015-16",IF(E23<=10000000,0,MIN((G23-H23)*12%,MAX(0,(G23-H23)*0%+(E23-10000000)*(70%-30%*0%)))),IF(OR(B23="2017-18",B23="2018-19"),IF(E23<=5000000,0,IF(E23<=10000000,MIN((G23-H23)*10%,MAX(0,(G23-H23)*0%+(E23-5000000)*(70%-30%*0%))),MIN((G23-H23)*15%,MAX(0,(G23-H23)*10%+(E23-10000000)*(70%-30%*10%))))),IF(E23<=5000000,0,IF(E23<=10000000,MIN((G23-H23)*10%,MAX(0,(G23-H23)*0%+(E23-5000000)*(70%-30%*0%))),IF(E23<=20000000,MIN((G23-H23)*15%,MAX(0,(G23-H23)*10%+(E23-10000000)*(70%-30%*10%))),IF(E23<=50000000,MIN((G23-H23)*25%,MAX(0,(G23-H23)*15%+(E23-20000000)*(70%-30%*15%))),MIN((G23-H23)*37%,MAX(0,(G23-H23)*25%+(E23-50000000)*(70%-30%*25%)))))))))),IF(OR(B23="2023-24",B23="2024-25",B23="2025-26"),IF(E23<=5000000,0,IF(E23<=10000000,MIN((G23-H23)*10%,MAX(0,(G23-H23)*0%+(E23-5000000)*(70%-30%*0%))),IF(E23<=20000000,MIN((G23-H23)*15%,MAX(0,(G23-H23)*10%+(E23-10000000)*(70%-30%*10%))),MIN((G23-H23)*25%,MAX(0,(G23-H23)*15%+(E23-20000000)*(70%-30%*15%)))))),IF(E23<=5000000,0,IF(E23<=10000000,MIN((G23-H23)*10%,MAX(0,(G23-H23)*0%+(E23-5000000)*(70%-30%*0%))),IF(E23<=20000000,MIN((G23-H23)*15%,MAX(0,(G23-H23)*10%+(E23-10000000)*(70%-30%*10%))),IF(E23<=50000000,MIN((G23-H23)*25%,MAX(0,(G23-H23)*15%+(E23-20000000)*(70%-30%*15%))),MIN((G23-H23)*37%,MAX(0,(G23-H23)*25%+(E23-50000000)*(70%-30%*25%))))))))),2) -> 0 | J23: =ROUND((G23-H23+I23)*IF(OR(B23="2014-15",B23="2015-16",B23="2016-17",B23="2017-18"),3%,4%),2) -> 0 | K23: =ROUND(G23-H23+I23+J23,2) -> 0 | L23: =ROUND(IF(C23="OLD",MAX(0,MIN(F23,500000)-IF(D23="Resident-Senior Citizen",300000,250000))*IF(B23="2016-17",10%,5%)+MAX(0,MIN(F23,1000000)-500000)*20%+MAX(0,F23-1000000)*30%,IF(OR(B23="2020-21",B23="2021-22",B23="2022-23"),MAX(0,MIN(F23,500000)-250000)*5%+MAX(0,MIN(F23,750000)-500000)*10%+MAX(0,MIN(F23,1000000)-750000)*15%+MAX(0,MIN(F23,1250000)-1000000)*20%+MAX(0,MIN(F23,1500000)-1250000)*25%+MAX(0,F23-1500000)*30%,IF(B23="2023-24",MAX(0,MIN(F23,600000)-300000)*5%+MAX(0,MIN(F23,900000)-600000)*10%+MAX(0,MIN(F23,1200000)-900000)*15%+MAX(0,MIN(F23,1500000)-1200000)*20%+MAX(0,F23-1500000)*30%,IF(B23="2024-25",MAX(0,MIN(F23,700000)-300000)*5%+MAX(0,MIN(F23,1000000)-700000)*10%+MAX(0,MIN(F23,1200000)-1000000)*15%+MAX(0,MIN(F23,1500000)-1200000)*20%+MAX(0,F23-1500000)*30%,IF(B23="2025-26",MAX(0,MIN(F23,800000)-400000)*5%+MAX(0,MIN(F23,1200000)-800000)*10%+MAX(0,MIN(F23,1600000)-1200000)*15%+MAX(0,MIN(F23,2000000)-1600000)*20%+MAX(0,MIN(F23,2400000)-2000000)*25%+MAX(0,F23-2400000)*30%,0))))),2) -> 0 | M23: =ROUND(MAX(IF(C23="OLD",IF(F23<=IF(OR(B23="2014-15",B23="2015-16",B23="2016-17"),500000,IF(OR(B23="2017-18",B23="2018-19"),350000,500000)),MIN(L23,IF(OR(B23="2014-15",B23="2015-16"),2000,IF(B23="2016-17",5000,IF(OR(B23="2017-18",B23="2018-19"),2500,12500)))),0),IF(F23<=IF(OR(B23="2023-24",B23="2024-25"),700000,IF(B23="2025-26",1200000,500000)),MIN(L23,IF(OR(B23="2023-24",B23="2024-25"),25000,IF(B23="2025-26",60000,12500))),0)),IF(AND(C23="NEW",B23="2025-26",F23>1200000),MAX(0,L23-(F23-1200000)),0)),2) -> 0 | N23: =ROUND(IF(C23="OLD",IF(OR(B23="2014-15",B23="2016-17"),IF(F23<=10000000,0,MIN((L23-M23)*15%,MAX(0,(L23-M23)*0%+(F23-10000000)*(70%-30%*0%)))),IF(B23="2015-16",IF(F23<=10000000,0,MIN((L23-M23)*12%,MAX(0,(L23-M23)*0%+(F23-10000000)*(70%-30%*0%)))),IF(OR(B23="2017-18",B23="2018-19"),IF(F23<=5000000,0,IF(F23<=10000000,MIN((L23-M23)*10%,MAX(0,(L23-M23)*0%+(F23-5000000)*(70%-30%*0%))),MIN((L23-M23)*15%,MAX(0,(L23-M23)*10%+(F23-10000000)*(70%-30%*10%))))),IF(F23<=5000000,0,IF(F23<=10000000,MIN((L23-M23)*10%,MAX(0,(L23-M23)*0%+(F23-5000000)*(70%-30%*0%))),IF(F23<=20000000,MIN((L23-M23)*15%,MAX(0,(L23-M23)*10%+(F23-10000000)*(70%-30%*10%))),IF(F23<=50000000,MIN((L23-M23)*25%,MAX(0,(L23-M23)*15%+(F23-20000000)*(70%-30%*15%))),MIN((L23-M23)*37%,MAX(0,(L23-M23)*25%+(F23-50000000)*(70%-30%*25%)))))))))),IF(OR(B23="2023-24",B23="2024-25",B23="2025-26"),IF(F23<=5000000,0,IF(F23<=10000000,MIN((L23-M23)*10%,MAX(0,(L23-M23)*0%+(F23-5000000)*(70%-30%*0%))),IF(F23<=20000000,MIN((L23-M23)*15%,MAX(0,(L23-M23)*10%+(F23-10000000)*(70%-30%*10%))),MIN((L23-M23)*25%,MAX(0,(L23-M23)*15%+(F23-20000000)*(70%-30%*15%)))))),IF(F23<=5000000,0,IF(F23<=10000000,MIN((L23-M23)*10%,MAX(0,(L23-M23)*0%+(F23-5000000)*(70%-30%*0%))),IF(F23<=20000000,MIN((L23-M23)*15%,MAX(0,(L23-M23)*10%+(F23-10000000)*(70%-30%*10%))),IF(F23<=50000000,MIN((L23-M23)*25%,MAX(0,(L23-M23)*15%+(F23-20000000)*(70%-30%*15%))),MIN((L23-M23)*37%,MAX(0,(L23-M23)*25%+(F23-50000000)*(70%-30%*25%))))))))),2) -> 0 | O23: =ROUND((L23-M23+N23)*IF(OR(B23="2014-15",B23="2015-16",B23="2016-17",B23="2017-18"),3%,4%),2) -> 0 | P23: =ROUND(L23-M23+N23+O23,2) -> 0 | Q23: =ROUND(P23-K23,2) -> 0
A24: =10 -> 10 | B24: =Source_Data!A10 -> 2020-21 | C24: ="OLD" -> OLD | D24: =Source_Data!F10 -> Resident-Senior Citizen | E24: =Source_Data!B10 -> 0 | F24: =Source_Data!D10 -> 0 | G24: =ROUND(IF(C24="OLD",MAX(0,MIN(E24,500000)-IF(D24="Resident-Senior Citizen",300000,250000))*IF(B24="2016-17",10%,5%)+MAX(0,MIN(E24,1000000)-500000)*20%+MAX(0,E24-1000000)*30%,IF(OR(B24="2020-21",B24="2021-22",B24="2022-23"),MAX(0,MIN(E24,500000)-250000)*5%+MAX(0,MIN(E24,750000)-500000)*10%+MAX(0,MIN(E24,1000000)-750000)*15%+MAX(0,MIN(E24,1250000)-1000000)*20%+MAX(0,MIN(E24,1500000)-1250000)*25%+MAX(0,E24-1500000)*30%,IF(B24="2023-24",MAX(0,MIN(E24,600000)-300000)*5%+MAX(0,MIN(E24,900000)-600000)*10%+MAX(0,MIN(E24,1200000)-900000)*15%+MAX(0,MIN(E24,1500000)-1200000)*20%+MAX(0,E24-1500000)*30%,IF(B24="2024-25",MAX(0,MIN(E24,700000)-300000)*5%+MAX(0,MIN(E24,1000000)-700000)*10%+MAX(0,MIN(E24,1200000)-1000000)*15%+MAX(0,MIN(E24,1500000)-1200000)*20%+MAX(0,E24-1500000)*30%,IF(B24="2025-26",MAX(0,MIN(E24,800000)-400000)*5%+MAX(0,MIN(E24,1200000)-800000)*10%+MAX(0,MIN(E24,1600000)-1200000)*15%+MAX(0,MIN(E24,2000000)-1600000)*20%+MAX(0,MIN(E24,2400000)-2000000)*25%+MAX(0,E24-2400000)*30%,0))))),2) -> 0 | H24: =ROUND(MAX(IF(C24="OLD",IF(E24<=IF(OR(B24="2014-15",B24="2015-16",B24="2016-17"),500000,IF(OR(B24="2017-18",B24="2018-19"),350000,500000)),MIN(G24,IF(OR(B24="2014-15",B24="2015-16"),2000,IF(B24="2016-17",5000,IF(OR(B24="2017-18",B24="2018-19"),2500,12500)))),0),IF(E24<=IF(OR(B24="2023-24",B24="2024-25"),700000,IF(B24="2025-26",1200000,500000)),MIN(G24,IF(OR(B24="2023-24",B24="2024-25"),25000,IF(B24="2025-26",60000,12500))),0)),IF(AND(C24="NEW",B24="2025-26",E24>1200000),MAX(0,G24-(E24-1200000)),0)),2) -> 0 | I24: =ROUND(IF(C24="OLD",IF(OR(B24="2014-15",B24="2016-17"),IF(E24<=10000000,0,MIN((G24-H24)*15%,MAX(0,(G24-H24)*0%+(E24-10000000)*(70%-30%*0%)))),IF(B24="2015-16",IF(E24<=10000000,0,MIN((G24-H24)*12%,MAX(0,(G24-H24)*0%+(E24-10000000)*(70%-30%*0%)))),IF(OR(B24="2017-18",B24="2018-19"),IF(E24<=5000000,0,IF(E24<=10000000,MIN((G24-H24)*10%,MAX(0,(G24-H24)*0%+(E24-5000000)*(70%-30%*0%))),MIN((G24-H24)*15%,MAX(0,(G24-H24)*10%+(E24-10000000)*(70%-30%*10%))))),IF(E24<=5000000,0,IF(E24<=10000000,MIN((G24-H24)*10%,MAX(0,(G24-H24)*0%+(E24-5000000)*(70%-30%*0%))),IF(E24<=20000000,MIN((G24-H24)*15%,MAX(0,(G24-H24)*10%+(E24-10000000)*(70%-30%*10%))),IF(E24<=50000000,MIN((G24-H24)*25%,MAX(0,(G24-H24)*15%+(E24-20000000)*(70%-30%*15%))),MIN((G24-H24)*37%,MAX(0,(G24-H24)*25%+(E24-50000000)*(70%-30%*25%)))))))))),IF(OR(B24="2023-24",B24="2024-25",B24="2025-26"),IF(E24<=5000000,0,IF(E24<=10000000,MIN((G24-H24)*10%,MAX(0,(G24-H24)*0%+(E24-5000000)*(70%-30%*0%))),IF(E24<=20000000,MIN((G24-H24)*15%,MAX(0,(G24-H24)*10%+(E24-10000000)*(70%-30%*10%))),MIN((G24-H24)*25%,MAX(0,(G24-H24)*15%+(E24-20000000)*(70%-30%*15%)))))),IF(E24<=5000000,0,IF(E24<=10000000,MIN((G24-H24)*10%,MAX(0,(G24-H24)*0%+(E24-5000000)*(70%-30%*0%))),IF(E24<=20000000,MIN((G24-H24)*15%,MAX(0,(G24-H24)*10%+(E24-10000000)*(70%-30%*10%))),IF(E24<=50000000,MIN((G24-H24)*25%,MAX(0,(G24-H24)*15%+(E24-20000000)*(70%-30%*15%))),MIN((G24-H24)*37%,MAX(0,(G24-H24)*25%+(E24-50000000)*(70%-30%*25%))))))))),2) -> 0 | J24: =ROUND((G24-H24+I24)*IF(OR(B24="2014-15",B24="2015-16",B24="2016-17",B24="2017-18"),3%,4%),2) -> 0 | K24: =ROUND(G24-H24+I24+J24,2) -> 0 | L24: =ROUND(IF(C24="OLD",MAX(0,MIN(F24,500000)-IF(D24="Resident-Senior Citizen",300000,250000))*IF(B24="2016-17",10%,5%)+MAX(0,MIN(F24,1000000)-500000)*20%+MAX(0,F24-1000000)*30%,IF(OR(B24="2020-21",B24="2021-22",B24="2022-23"),MAX(0,MIN(F24,500000)-250000)*5%+MAX(0,MIN(F24,750000)-500000)*10%+MAX(0,MIN(F24,1000000)-750000)*15%+MAX(0,MIN(F24,1250000)-1000000)*20%+MAX(0,MIN(F24,1500000)-1250000)*25%+MAX(0,F24-1500000)*30%,IF(B24="2023-24",MAX(0,MIN(F24,600000)-300000)*5%+MAX(0,MIN(F24,900000)-600000)*10%+MAX(0,MIN(F24,1200000)-900000)*15%+MAX(0,MIN(F24,1500000)-1200000)*20%+MAX(0,F24-1500000)*30%,IF(B24="2024-25",MAX(0,MIN(F24,700000)-300000)*5%+MAX(0,MIN(F24,1000000)-700000)*10%+MAX(0,MIN(F24,1200000)-1000000)*15%+MAX(0,MIN(F24,1500000)-1200000)*20%+MAX(0,F24-1500000)*30%,IF(B24="2025-26",MAX(0,MIN(F24,800000)-400000)*5%+MAX(0,MIN(F24,1200000)-800000)*10%+MAX(0,MIN(F24,1600000)-1200000)*15%+MAX(0,MIN(F24,2000000)-1600000)*20%+MAX(0,MIN(F24,2400000)-2000000)*25%+MAX(0,F24-2400000)*30%,0))))),2) -> 0 | M24: =ROUND(MAX(IF(C24="OLD",IF(F24<=IF(OR(B24="2014-15",B24="2015-16",B24="2016-17"),500000,IF(OR(B24="2017-18",B24="2018-19"),350000,500000)),MIN(L24,IF(OR(B24="2014-15",B24="2015-16"),2000,IF(B24="2016-17",5000,IF(OR(B24="2017-18",B24="2018-19"),2500,12500)))),0),IF(F24<=IF(OR(B24="2023-24",B24="2024-25"),700000,IF(B24="2025-26",1200000,500000)),MIN(L24,IF(OR(B24="2023-24",B24="2024-25"),25000,IF(B24="2025-26",60000,12500))),0)),IF(AND(C24="NEW",B24="2025-26",F24>1200000),MAX(0,L24-(F24-1200000)),0)),2) -> 0 | N24: =ROUND(IF(C24="OLD",IF(OR(B24="2014-15",B24="2016-17"),IF(F24<=10000000,0,MIN((L24-M24)*15%,MAX(0,(L24-M24)*0%+(F24-10000000)*(70%-30%*0%)))),IF(B24="2015-16",IF(F24<=10000000,0,MIN((L24-M24)*12%,MAX(0,(L24-M24)*0%+(F24-10000000)*(70%-30%*0%)))),IF(OR(B24="2017-18",B24="2018-19"),IF(F24<=5000000,0,IF(F24<=10000000,MIN((L24-M24)*10%,MAX(0,(L24-M24)*0%+(F24-5000000)*(70%-30%*0%))),MIN((L24-M24)*15%,MAX(0,(L24-M24)*10%+(F24-10000000)*(70%-30%*10%))))),IF(F24<=5000000,0,IF(F24<=10000000,MIN((L24-M24)*10%,MAX(0,(L24-M24)*0%+(F24-5000000)*(70%-30%*0%))),IF(F24<=20000000,MIN((L24-M24)*15%,MAX(0,(L24-M24)*10%+(F24-10000000)*(70%-30%*10%))),IF(F24<=50000000,MIN((L24-M24)*25%,MAX(0,(L24-M24)*15%+(F24-20000000)*(70%-30%*15%))),MIN((L24-M24)*37%,MAX(0,(L24-M24)*25%+(F24-50000000)*(70%-30%*25%)))))))))),IF(OR(B24="2023-24",B24="2024-25",B24="2025-26"),IF(F24<=5000000,0,IF(F24<=10000000,MIN((L24-M24)*10%,MAX(0,(L24-M24)*0%+(F24-5000000)*(70%-30%*0%))),IF(F24<=20000000,MIN((L24-M24)*15%,MAX(0,(L24-M24)*10%+(F24-10000000)*(70%-30%*10%))),MIN((L24-M24)*25%,MAX(0,(L24-M24)*15%+(F24-20000000)*(70%-30%*15%)))))),IF(F24<=5000000,0,IF(F24<=10000000,MIN((L24-M24)*10%,MAX(0,(L24-M24)*0%+(F24-5000000)*(70%-30%*0%))),IF(F24<=20000000,MIN((L24-M24)*15%,MAX(0,(L24-M24)*10%+(F24-10000000)*(70%-30%*10%))),IF(F24<=50000000,MIN((L24-M24)*25%,MAX(0,(L24-M24)*15%+(F24-20000000)*(70%-30%*15%))),MIN((L24-M24)*37%,MAX(0,(L24-M24)*25%+(F24-50000000)*(70%-30%*25%))))))))),2) -> 0 | O24: =ROUND((L24-M24+N24)*IF(OR(B24="2014-15",B24="2015-16",B24="2016-17",B24="2017-18"),3%,4%),2) -> 0 | P24: =ROUND(L24-M24+N24+O24,2) -> 0 | Q24: =ROUND(P24-K24,2) -> 0
A25: =11 -> 11 | B25: =Source_Data!A11 -> 2021-22 | C25: ="OLD" -> OLD | D25: =Source_Data!F11 -> Resident-Senior Citizen | E25: =Source_Data!B11 -> 0 | F25: =Source_Data!D11 -> 0 | G25: =ROUND(IF(C25="OLD",MAX(0,MIN(E25,500000)-IF(D25="Resident-Senior Citizen",300000,250000))*IF(B25="2016-17",10%,5%)+MAX(0,MIN(E25,1000000)-500000)*20%+MAX(0,E25-1000000)*30%,IF(OR(B25="2020-21",B25="2021-22",B25="2022-23"),MAX(0,MIN(E25,500000)-250000)*5%+MAX(0,MIN(E25,750000)-500000)*10%+MAX(0,MIN(E25,1000000)-750000)*15%+MAX(0,MIN(E25,1250000)-1000000)*20%+MAX(0,MIN(E25,1500000)-1250000)*25%+MAX(0,E25-1500000)*30%,IF(B25="2023-24",MAX(0,MIN(E25,600000)-300000)*5%+MAX(0,MIN(E25,900000)-600000)*10%+MAX(0,MIN(E25,1200000)-900000)*15%+MAX(0,MIN(E25,1500000)-1200000)*20%+MAX(0,E25-1500000)*30%,IF(B25="2024-25",MAX(0,MIN(E25,700000)-300000)*5%+MAX(0,MIN(E25,1000000)-700000)*10%+MAX(0,MIN(E25,1200000)-1000000)*15%+MAX(0,MIN(E25,1500000)-1200000)*20%+MAX(0,E25-1500000)*30%,IF(B25="2025-26",MAX(0,MIN(E25,800000)-400000)*5%+MAX(0,MIN(E25,1200000)-800000)*10%+MAX(0,MIN(E25,1600000)-1200000)*15%+MAX(0,MIN(E25,2000000)-1600000)*20%+MAX(0,MIN(E25,2400000)-2000000)*25%+MAX(0,E25-2400000)*30%,0))))),2) -> 0 | H25: =ROUND(MAX(IF(C25="OLD",IF(E25<=IF(OR(B25="2014-15",B25="2015-16",B25="2016-17"),500000,IF(OR(B25="2017-18",B25="2018-19"),350000,500000)),MIN(G25,IF(OR(B25="2014-15",B25="2015-16"),2000,IF(B25="2016-17",5000,IF(OR(B25="2017-18",B25="2018-19"),2500,12500)))),0),IF(E25<=IF(OR(B25="2023-24",B25="2024-25"),700000,IF(B25="2025-26",1200000,500000)),MIN(G25,IF(OR(B25="2023-24",B25="2024-25"),25000,IF(B25="2025-26",60000,12500))),0)),IF(AND(C25="NEW",B25="2025-26",E25>1200000),MAX(0,G25-(E25-1200000)),0)),2) -> 0 | I25: =ROUND(IF(C25="OLD",IF(OR(B25="2014-15",B25="2016-17"),IF(E25<=10000000,0,MIN((G25-H25)*15%,MAX(0,(G25-H25)*0%+(E25-10000000)*(70%-30%*0%)))),IF(B25="2015-16",IF(E25<=10000000,0,MIN((G25-H25)*12%,MAX(0,(G25-H25)*0%+(E25-10000000)*(70%-30%*0%)))),IF(OR(B25="2017-18",B25="2018-19"),IF(E25<=5000000,0,IF(E25<=10000000,MIN((G25-H25)*10%,MAX(0,(G25-H25)*0%+(E25-5000000)*(70%-30%*0%))),MIN((G25-H25)*15%,MAX(0,(G25-H25)*10%+(E25-10000000)*(70%-30%*10%))))),IF(E25<=5000000,0,IF(E25<=10000000,MIN((G25-H25)*10%,MAX(0,(G25-H25)*0%+(E25-5000000)*(70%-30%*0%))),IF(E25<=20000000,MIN((G25-H25)*15%,MAX(0,(G25-H25)*10%+(E25-10000000)*(70%-30%*10%))),IF(E25<=50000000,MIN((G25-H25)*25%,MAX(0,(G25-H25)*15%+(E25-20000000)*(70%-30%*15%))),MIN((G25-H25)*37%,MAX(0,(G25-H25)*25%+(E25-50000000)*(70%-30%*25%)))))))))),IF(OR(B25="2023-24",B25="2024-25",B25="2025-26"),IF(E25<=5000000,0,IF(E25<=10000000,MIN((G25-H25)*10%,MAX(0,(G25-H25)*0%+(E25-5000000)*(70%-30%*0%))),IF(E25<=20000000,MIN((G25-H25)*15%,MAX(0,(G25-H25)*10%+(E25-10000000)*(70%-30%*10%))),MIN((G25-H25)*25%,MAX(0,(G25-H25)*15%+(E25-20000000)*(70%-30%*15%)))))),IF(E25<=5000000,0,IF(E25<=10000000,MIN((G25-H25)*10%,MAX(0,(G25-H25)*0%+(E25-5000000)*(70%-30%*0%))),IF(E25<=20000000,MIN((G25-H25)*15%,MAX(0,(G25-H25)*10%+(E25-10000000)*(70%-30%*10%))),IF(E25<=50000000,MIN((G25-H25)*25%,MAX(0,(G25-H25)*15%+(E25-20000000)*(70%-30%*15%))),MIN((G25-H25)*37%,MAX(0,(G25-H25)*25%+(E25-50000000)*(70%-30%*25%))))))))),2) -> 0 | J25: =ROUND((G25-H25+I25)*IF(OR(B25="2014-15",B25="2015-16",B25="2016-17",B25="2017-18"),3%,4%),2) -> 0 | K25: =ROUND(G25-H25+I25+J25,2) -> 0 | L25: =ROUND(IF(C25="OLD",MAX(0,MIN(F25,500000)-IF(D25="Resident-Senior Citizen",300000,250000))*IF(B25="2016-17",10%,5%)+MAX(0,MIN(F25,1000000)-500000)*20%+MAX(0,F25-1000000)*30%,IF(OR(B25="2020-21",B25="2021-22",B25="2022-23"),MAX(0,MIN(F25,500000)-250000)*5%+MAX(0,MIN(F25,750000)-500000)*10%+MAX(0,MIN(F25,1000000)-750000)*15%+MAX(0,MIN(F25,1250000)-1000000)*20%+MAX(0,MIN(F25,1500000)-1250000)*25%+MAX(0,F25-1500000)*30%,IF(B25="2023-24",MAX(0,MIN(F25,600000)-300000)*5%+MAX(0,MIN(F25,900000)-600000)*10%+MAX(0,MIN(F25,1200000)-900000)*15%+MAX(0,MIN(F25,1500000)-1200000)*20%+MAX(0,F25-1500000)*30%,IF(B25="2024-25",MAX(0,MIN(F25,700000)-300000)*5%+MAX(0,MIN(F25,1000000)-700000)*10%+MAX(0,MIN(F25,1200000)-1000000)*15%+MAX(0,MIN(F25,1500000)-1200000)*20%+MAX(0,F25-1500000)*30%,IF(B25="2025-26",MAX(0,MIN(F25,800000)-400000)*5%+MAX(0,MIN(F25,1200000)-800000)*10%+MAX(0,MIN(F25,1600000)-1200000)*15%+MAX(0,MIN(F25,2000000)-1600000)*20%+MAX(0,MIN(F25,2400000)-2000000)*25%+MAX(0,F25-2400000)*30%,0))))),2) -> 0 | M25: =ROUND(MAX(IF(C25="OLD",IF(F25<=IF(OR(B25="2014-15",B25="2015-16",B25="2016-17"),500000,IF(OR(B25="2017-18",B25="2018-19"),350000,500000)),MIN(L25,IF(OR(B25="2014-15",B25="2015-16"),2000,IF(B25="2016-17",5000,IF(OR(B25="2017-18",B25="2018-19"),2500,12500)))),0),IF(F25<=IF(OR(B25="2023-24",B25="2024-25"),700000,IF(B25="2025-26",1200000,500000)),MIN(L25,IF(OR(B25="2023-24",B25="2024-25"),25000,IF(B25="2025-26",60000,12500))),0)),IF(AND(C25="NEW",B25="2025-26",F25>1200000),MAX(0,L25-(F25-1200000)),0)),2) -> 0 | N25: =ROUND(IF(C25="OLD",IF(OR(B25="2014-15",B25="2016-17"),IF(F25<=10000000,0,MIN((L25-M25)*15%,MAX(0,(L25-M25)*0%+(F25-10000000)*(70%-30%*0%)))),IF(B25="2015-16",IF(F25<=10000000,0,MIN((L25-M25)*12%,MAX(0,(L25-M25)*0%+(F25-10000000)*(70%-30%*0%)))),IF(OR(B25="2017-18",B25="2018-19"),IF(F25<=5000000,0,IF(F25<=10000000,MIN((L25-M25)*10%,MAX(0,(L25-M25)*0%+(F25-5000000)*(70%-30%*0%))),MIN((L25-M25)*15%,MAX(0,(L25-M25)*10%+(F25-10000000)*(70%-30%*10%))))),IF(F25<=5000000,0,IF(F25<=10000000,MIN((L25-M25)*10%,MAX(0,(L25-M25)*0%+(F25-5000000)*(70%-30%*0%))),IF(F25<=20000000,MIN((L25-M25)*15%,MAX(0,(L25-M25)*10%+(F25-10000000)*(70%-30%*10%))),IF(F25<=50000000,MIN((L25-M25)*25%,MAX(0,(L25-M25)*15%+(F25-20000000)*(70%-30%*15%))),MIN((L25-M25)*37%,MAX(0,(L25-M25)*25%+(F25-50000000)*(70%-30%*25%)))))))))),IF(OR(B25="2023-24",B25="2024-25",B25="2025-26"),IF(F25<=5000000,0,IF(F25<=10000000,MIN((L25-M25)*10%,MAX(0,(L25-M25)*0%+(F25-5000000)*(70%-30%*0%))),IF(F25<=20000000,MIN((L25-M25)*15%,MAX(0,(L25-M25)*10%+(F25-10000000)*(70%-30%*10%))),MIN((L25-M25)*25%,MAX(0,(L25-M25)*15%+(F25-20000000)*(70%-30%*15%)))))),IF(F25<=5000000,0,IF(F25<=10000000,MIN((L25-M25)*10%,MAX(0,(L25-M25)*0%+(F25-5000000)*(70%-30%*0%))),IF(F25<=20000000,MIN((L25-M25)*15%,MAX(0,(L25-M25)*10%+(F25-10000000)*(70%-30%*10%))),IF(F25<=50000000,MIN((L25-M25)*25%,MAX(0,(L25-M25)*15%+(F25-20000000)*(70%-30%*15%))),MIN((L25-M25)*37%,MAX(0,(L25-M25)*25%+(F25-50000000)*(70%-30%*25%))))))))),2) -> 0 | O25: =ROUND((L25-M25+N25)*IF(OR(B25="2014-15",B25="2015-16",B25="2016-17",B25="2017-18"),3%,4%),2) -> 0 | P25: =ROUND(L25-M25+N25+O25,2) -> 0 | Q25: =ROUND(P25-K25,2) -> 0
A26: =12 -> 12 | B26: =Source_Data!A12 -> 2022-23 | C26: ="OLD" -> OLD | D26: =Source_Data!F12 -> Resident-Senior Citizen | E26: =Source_Data!B12 -> 0 | F26: =Source_Data!D12 -> 0 | G26: =ROUND(IF(C26="OLD",MAX(0,MIN(E26,500000)-IF(D26="Resident-Senior Citizen",300000,250000))*IF(B26="2016-17",10%,5%)+MAX(0,MIN(E26,1000000)-500000)*20%+MAX(0,E26-1000000)*30%,IF(OR(B26="2020-21",B26="2021-22",B26="2022-23"),MAX(0,MIN(E26,500000)-250000)*5%+MAX(0,MIN(E26,750000)-500000)*10%+MAX(0,MIN(E26,1000000)-750000)*15%+MAX(0,MIN(E26,1250000)-1000000)*20%+MAX(0,MIN(E26,1500000)-1250000)*25%+MAX(0,E26-1500000)*30%,IF(B26="2023-24",MAX(0,MIN(E26,600000)-300000)*5%+MAX(0,MIN(E26,900000)-600000)*10%+MAX(0,MIN(E26,1200000)-900000)*15%+MAX(0,MIN(E26,1500000)-1200000)*20%+MAX(0,E26-1500000)*30%,IF(B26="2024-25",MAX(0,MIN(E26,700000)-300000)*5%+MAX(0,MIN(E26,1000000)-700000)*10%+MAX(0,MIN(E26,1200000)-1000000)*15%+MAX(0,MIN(E26,1500000)-1200000)*20%+MAX(0,E26-1500000)*30%,IF(B26="2025-26",MAX(0,MIN(E26,800000)-400000)*5%+MAX(0,MIN(E26,1200000)-800000)*10%+MAX(0,MIN(E26,1600000)-1200000)*15%+MAX(0,MIN(E26,2000000)-1600000)*20%+MAX(0,MIN(E26,2400000)-2000000)*25%+MAX(0,E26-2400000)*30%,0))))),2) -> 0 | H26: =ROUND(MAX(IF(C26="OLD",IF(E26<=IF(OR(B26="2014-15",B26="2015-16",B26="2016-17"),500000,IF(OR(B26="2017-18",B26="2018-19"),350000,500000)),MIN(G26,IF(OR(B26="2014-15",B26="2015-16"),2000,IF(B26="2016-17",5000,IF(OR(B26="2017-18",B26="2018-19"),2500,12500)))),0),IF(E26<=IF(OR(B26="2023-24",B26="2024-25"),700000,IF(B26="2025-26",1200000,500000)),MIN(G26,IF(OR(B26="2023-24",B26="2024-25"),25000,IF(B26="2025-26",60000,12500))),0)),IF(AND(C26="NEW",B26="2025-26",E26>1200000),MAX(0,G26-(E26-1200000)),0)),2) -> 0 | I26: =ROUND(IF(C26="OLD",IF(OR(B26="2014-15",B26="2016-17"),IF(E26<=10000000,0,MIN((G26-H26)*15%,MAX(0,(G26-H26)*0%+(E26-10000000)*(70%-30%*0%)))),IF(B26="2015-16",IF(E26<=10000000,0,MIN((G26-H26)*12%,MAX(0,(G26-H26)*0%+(E26-10000000)*(70%-30%*0%)))),IF(OR(B26="2017-18",B26="2018-19"),IF(E26<=5000000,0,IF(E26<=10000000,MIN((G26-H26)*10%,MAX(0,(G26-H26)*0%+(E26-5000000)*(70%-30%*0%))),MIN((G26-H26)*15%,MAX(0,(G26-H26)*10%+(E26-10000000)*(70%-30%*10%))))),IF(E26<=5000000,0,IF(E26<=10000000,MIN((G26-H26)*10%,MAX(0,(G26-H26)*0%+(E26-5000000)*(70%-30%*0%))),IF(E26<=20000000,MIN((G26-H26)*15%,MAX(0,(G26-H26)*10%+(E26-10000000)*(70%-30%*10%))),IF(E26<=50000000,MIN((G26-H26)*25%,MAX(0,(G26-H26)*15%+(E26-20000000)*(70%-30%*15%))),MIN((G26-H26)*37%,MAX(0,(G26-H26)*25%+(E26-50000000)*(70%-30%*25%)))))))))),IF(OR(B26="2023-24",B26="2024-25",B26="2025-26"),IF(E26<=5000000,0,IF(E26<=10000000,MIN((G26-H26)*10%,MAX(0,(G26-H26)*0%+(E26-5000000)*(70%-30%*0%))),IF(E26<=20000000,MIN((G26-H26)*15%,MAX(0,(G26-H26)*10%+(E26-10000000)*(70%-30%*10%))),MIN((G26-H26)*25%,MAX(0,(G26-H26)*15%+(E26-20000000)*(70%-30%*15%)))))),IF(E26<=5000000,0,IF(E26<=10000000,MIN((G26-H26)*10%,MAX(0,(G26-H26)*0%+(E26-5000000)*(70%-30%*0%))),IF(E26<=20000000,MIN((G26-H26)*15%,MAX(0,(G26-H26)*10%+(E26-10000000)*(70%-30%*10%))),IF(E26<=50000000,MIN((G26-H26)*25%,MAX(0,(G26-H26)*15%+(E26-20000000)*(70%-30%*15%))),MIN((G26-H26)*37%,MAX(0,(G26-H26)*25%+(E26-50000000)*(70%-30%*25%))))))))),2) -> 0 | J26: =ROUND((G26-H26+I26)*IF(OR(B26="2014-15",B26="2015-16",B26="2016-17",B26="2017-18"),3%,4%),2) -> 0 | K26: =ROUND(G26-H26+I26+J26,2) -> 0 | L26: =ROUND(IF(C26="OLD",MAX(0,MIN(F26,500000)-IF(D26="Resident-Senior Citizen",300000,250000))*IF(B26="2016-17",10%,5%)+MAX(0,MIN(F26,1000000)-500000)*20%+MAX(0,F26-1000000)*30%,IF(OR(B26="2020-21",B26="2021-22",B26="2022-23"),MAX(0,MIN(F26,500000)-250000)*5%+MAX(0,MIN(F26,750000)-500000)*10%+MAX(0,MIN(F26,1000000)-750000)*15%+MAX(0,MIN(F26,1250000)-1000000)*20%+MAX(0,MIN(F26,1500000)-1250000)*25%+MAX(0,F26-1500000)*30%,IF(B26="2023-24",MAX(0,MIN(F26,600000)-300000)*5%+MAX(0,MIN(F26,900000)-600000)*10%+MAX(0,MIN(F26,1200000)-900000)*15%+MAX(0,MIN(F26,1500000)-1200000)*20%+MAX(0,F26-1500000)*30%,IF(B26="2024-25",MAX(0,MIN(F26,700000)-300000)*5%+MAX(0,MIN(F26,1000000)-700000)*10%+MAX(0,MIN(F26,1200000)-1000000)*15%+MAX(0,MIN(F26,1500000)-1200000)*20%+MAX(0,F26-1500000)*30%,IF(B26="2025-26",MAX(0,MIN(F26,800000)-400000)*5%+MAX(0,MIN(F26,1200000)-800000)*10%+MAX(0,MIN(F26,1600000)-1200000)*15%+MAX(0,MIN(F26,2000000)-1600000)*20%+MAX(0,MIN(F26,2400000)-2000000)*25%+MAX(0,F26-2400000)*30%,0))))),2) -> 0 | M26: =ROUND(MAX(IF(C26="OLD",IF(F26<=IF(OR(B26="2014-15",B26="2015-16",B26="2016-17"),500000,IF(OR(B26="2017-18",B26="2018-19"),350000,500000)),MIN(L26,IF(OR(B26="2014-15",B26="2015-16"),2000,IF(B26="2016-17",5000,IF(OR(B26="2017-18",B26="2018-19"),2500,12500)))),0),IF(F26<=IF(OR(B26="2023-24",B26="2024-25"),700000,IF(B26="2025-26",1200000,500000)),MIN(L26,IF(OR(B26="2023-24",B26="2024-25"),25000,IF(B26="2025-26",60000,12500))),0)),IF(AND(C26="NEW",B26="2025-26",F26>1200000),MAX(0,L26-(F26-1200000)),0)),2) -> 0 | N26: =ROUND(IF(C26="OLD",IF(OR(B26="2014-15",B26="2016-17"),IF(F26<=10000000,0,MIN((L26-M26)*15%,MAX(0,(L26-M26)*0%+(F26-10000000)*(70%-30%*0%)))),IF(B26="2015-16",IF(F26<=10000000,0,MIN((L26-M26)*12%,MAX(0,(L26-M26)*0%+(F26-10000000)*(70%-30%*0%)))),IF(OR(B26="2017-18",B26="2018-19"),IF(F26<=5000000,0,IF(F26<=10000000,MIN((L26-M26)*10%,MAX(0,(L26-M26)*0%+(F26-5000000)*(70%-30%*0%))),MIN((L26-M26)*15%,MAX(0,(L26-M26)*10%+(F26-10000000)*(70%-30%*10%))))),IF(F26<=5000000,0,IF(F26<=10000000,MIN((L26-M26)*10%,MAX(0,(L26-M26)*0%+(F26-5000000)*(70%-30%*0%))),IF(F26<=20000000,MIN((L26-M26)*15%,MAX(0,(L26-M26)*10%+(F26-10000000)*(70%-30%*10%))),IF(F26<=50000000,MIN((L26-M26)*25%,MAX(0,(L26-M26)*15%+(F26-20000000)*(70%-30%*15%))),MIN((L26-M26)*37%,MAX(0,(L26-M26)*25%+(F26-50000000)*(70%-30%*25%)))))))))),IF(OR(B26="2023-24",B26="2024-25",B26="2025-26"),IF(F26<=5000000,0,IF(F26<=10000000,MIN((L26-M26)*10%,MAX(0,(L26-M26)*0%+(F26-5000000)*(70%-30%*0%))),IF(F26<=20000000,MIN((L26-M26)*15%,MAX(0,(L26-M26)*10%+(F26-10000000)*(70%-30%*10%))),MIN((L26-M26)*25%,MAX(0,(L26-M26)*15%+(F26-20000000)*(70%-30%*15%)))))),IF(F26<=5000000,0,IF(F26<=10000000,MIN((L26-M26)*10%,MAX(0,(L26-M26)*0%+(F26-5000000)*(70%-30%*0%))),IF(F26<=20000000,MIN((L26-M26)*15%,MAX(0,(L26-M26)*10%+(F26-10000000)*(70%-30%*10%))),IF(F26<=50000000,MIN((L26-M26)*25%,MAX(0,(L26-M26)*15%+(F26-20000000)*(70%-30%*15%))),MIN((L26-M26)*37%,MAX(0,(L26-M26)*25%+(F26-50000000)*(70%-30%*25%))))))))),2) -> 0 | O26: =ROUND((L26-M26+N26)*IF(OR(B26="2014-15",B26="2015-16",B26="2016-17",B26="2017-18"),3%,4%),2) -> 0 | P26: =ROUND(L26-M26+N26+O26,2) -> 0 | Q26: =ROUND(P26-K26,2) -> 0
A27: =13 -> 13 | B27: =Source_Data!A13 -> 2023-24 | C27: ="OLD" -> OLD | D27: =Source_Data!F13 -> Resident-Senior Citizen | E27: =Source_Data!B13 -> 0 | F27: =Source_Data!D13 -> 0 | G27: =ROUND(IF(C27="OLD",MAX(0,MIN(E27,500000)-IF(D27="Resident-Senior Citizen",300000,250000))*IF(B27="2016-17",10%,5%)+MAX(0,MIN(E27,1000000)-500000)*20%+MAX(0,E27-1000000)*30%,IF(OR(B27="2020-21",B27="2021-22",B27="2022-23"),MAX(0,MIN(E27,500000)-250000)*5%+MAX(0,MIN(E27,750000)-500000)*10%+MAX(0,MIN(E27,1000000)-750000)*15%+MAX(0,MIN(E27,1250000)-1000000)*20%+MAX(0,MIN(E27,1500000)-1250000)*25%+MAX(0,E27-1500000)*30%,IF(B27="2023-24",MAX(0,MIN(E27,600000)-300000)*5%+MAX(0,MIN(E27,900000)-600000)*10%+MAX(0,MIN(E27,1200000)-900000)*15%+MAX(0,MIN(E27,1500000)-1200000)*20%+MAX(0,E27-1500000)*30%,IF(B27="2024-25",MAX(0,MIN(E27,700000)-300000)*5%+MAX(0,MIN(E27,1000000)-700000)*10%+MAX(0,MIN(E27,1200000)-1000000)*15%+MAX(0,MIN(E27,1500000)-1200000)*20%+MAX(0,E27-1500000)*30%,IF(B27="2025-26",MAX(0,MIN(E27,800000)-400000)*5%+MAX(0,MIN(E27,1200000)-800000)*10%+MAX(0,MIN(E27,1600000)-1200000)*15%+MAX(0,MIN(E27,2000000)-1600000)*20%+MAX(0,MIN(E27,2400000)-2000000)*25%+MAX(0,E27-2400000)*30%,0))))),2) -> 0 | H27: =ROUND(MAX(IF(C27="OLD",IF(E27<=IF(OR(B27="2014-15",B27="2015-16",B27="2016-17"),500000,IF(OR(B27="2017-18",B27="2018-19"),350000,500000)),MIN(G27,IF(OR(B27="2014-15",B27="2015-16"),2000,IF(B27="2016-17",5000,IF(OR(B27="2017-18",B27="2018-19"),2500,12500)))),0),IF(E27<=IF(OR(B27="2023-24",B27="2024-25"),700000,IF(B27="2025-26",1200000,500000)),MIN(G27,IF(OR(B27="2023-24",B27="2024-25"),25000,IF(B27="2025-26",60000,12500))),0)),IF(AND(C27="NEW",B27="2025-26",E27>1200000),MAX(0,G27-(E27-1200000)),0)),2) -> 0 | I27: =ROUND(IF(C27="OLD",IF(OR(B27="2014-15",B27="2016-17"),IF(E27<=10000000,0,MIN((G27-H27)*15%,MAX(0,(G27-H27)*0%+(E27-10000000)*(70%-30%*0%)))),IF(B27="2015-16",IF(E27<=10000000,0,MIN((G27-H27)*12%,MAX(0,(G27-H27)*0%+(E27-10000000)*(70%-30%*0%)))),IF(OR(B27="2017-18",B27="2018-19"),IF(E27<=5000000,0,IF(E27<=10000000,MIN((G27-H27)*10%,MAX(0,(G27-H27)*0%+(E27-5000000)*(70%-30%*0%))),MIN((G27-H27)*15%,MAX(0,(G27-H27)*10%+(E27-10000000)*(70%-30%*10%))))),IF(E27<=5000000,0,IF(E27<=10000000,MIN((G27-H27)*10%,MAX(0,(G27-H27)*0%+(E27-5000000)*(70%-30%*0%))),IF(E27<=20000000,MIN((G27-H27)*15%,MAX(0,(G27-H27)*10%+(E27-10000000)*(70%-30%*10%))),IF(E27<=50000000,MIN((G27-H27)*25%,MAX(0,(G27-H27)*15%+(E27-20000000)*(70%-30%*15%))),MIN((G27-H27)*37%,MAX(0,(G27-H27)*25%+(E27-50000000)*(70%-30%*25%)))))))))),IF(OR(B27="2023-24",B27="2024-25",B27="2025-26"),IF(E27<=5000000,0,IF(E27<=10000000,MIN((G27-H27)*10%,MAX(0,(G27-H27)*0%+(E27-5000000)*(70%-30%*0%))),IF(E27<=20000000,MIN((G27-H27)*15%,MAX(0,(G27-H27)*10%+(E27-10000000)*(70%-30%*10%))),MIN((G27-H27)*25%,MAX(0,(G27-H27)*15%+(E27-20000000)*(70%-30%*15%)))))),IF(E27<=5000000,0,IF(E27<=10000000,MIN((G27-H27)*10%,MAX(0,(G27-H27)*0%+(E27-5000000)*(70%-30%*0%))),IF(E27<=20000000,MIN((G27-H27)*15%,MAX(0,(G27-H27)*10%+(E27-10000000)*(70%-30%*10%))),IF(E27<=50000000,MIN((G27-H27)*25%,MAX(0,(G27-H27)*15%+(E27-20000000)*(70%-30%*15%))),MIN((G27-H27)*37%,MAX(0,(G27-H27)*25%+(E27-50000000)*(70%-30%*25%))))))))),2) -> 0 | J27: =ROUND((G27-H27+I27)*IF(OR(B27="2014-15",B27="2015-16",B27="2016-17",B27="2017-18"),3%,4%),2) -> 0 | K27: =ROUND(G27-H27+I27+J27,2) -> 0 | L27: =ROUND(IF(C27="OLD",MAX(0,MIN(F27,500000)-IF(D27="Resident-Senior Citizen",300000,250000))*IF(B27="2016-17",10%,5%)+MAX(0,MIN(F27,1000000)-500000)*20%+MAX(0,F27-1000000)*30%,IF(OR(B27="2020-21",B27="2021-22",B27="2022-23"),MAX(0,MIN(F27,500000)-250000)*5%+MAX(0,MIN(F27,750000)-500000)*10%+MAX(0,MIN(F27,1000000)-750000)*15%+MAX(0,MIN(F27,1250000)-1000000)*20%+MAX(0,MIN(F27,1500000)-1250000)*25%+MAX(0,F27-1500000)*30%,IF(B27="2023-24",MAX(0,MIN(F27,600000)-300000)*5%+MAX(0,MIN(F27,900000)-600000)*10%+MAX(0,MIN(F27,1200000)-900000)*15%+MAX(0,MIN(F27,1500000)-1200000)*20%+MAX(0,F27-1500000)*30%,IF(B27="2024-25",MAX(0,MIN(F27,700000)-300000)*5%+MAX(0,MIN(F27,1000000)-700000)*10%+MAX(0,MIN(F27,1200000)-1000000)*15%+MAX(0,MIN(F27,1500000)-1200000)*20%+MAX(0,F27-1500000)*30%,IF(B27="2025-26",MAX(0,MIN(F27,800000)-400000)*5%+MAX(0,MIN(F27,1200000)-800000)*10%+MAX(0,MIN(F27,1600000)-1200000)*15%+MAX(0,MIN(F27,2000000)-1600000)*20%+MAX(0,MIN(F27,2400000)-2000000)*25%+MAX(0,F27-2400000)*30%,0))))),2) -> 0 | M27: =ROUND(MAX(IF(C27="OLD",IF(F27<=IF(OR(B27="2014-15",B27="2015-16",B27="2016-17"),500000,IF(OR(B27="2017-18",B27="2018-19"),350000,500000)),MIN(L27,IF(OR(B27="2014-15",B27="2015-16"),2000,IF(B27="2016-17",5000,IF(OR(B27="2017-18",B27="2018-19"),2500,12500)))),0),IF(F27<=IF(OR(B27="2023-24",B27="2024-25"),700000,IF(B27="2025-26",1200000,500000)),MIN(L27,IF(OR(B27="2023-24",B27="2024-25"),25000,IF(B27="2025-26",60000,12500))),0)),IF(AND(C27="NEW",B27="2025-26",F27>1200000),MAX(0,L27-(F27-1200000)),0)),2) -> 0 | N27: =ROUND(IF(C27="OLD",IF(OR(B27="2014-15",B27="2016-17"),IF(F27<=10000000,0,MIN((L27-M27)*15%,MAX(0,(L27-M27)*0%+(F27-10000000)*(70%-30%*0%)))),IF(B27="2015-16",IF(F27<=10000000,0,MIN((L27-M27)*12%,MAX(0,(L27-M27)*0%+(F27-10000000)*(70%-30%*0%)))),IF(OR(B27="2017-18",B27="2018-19"),IF(F27<=5000000,0,IF(F27<=10000000,MIN((L27-M27)*10%,MAX(0,(L27-M27)*0%+(F27-5000000)*(70%-30%*0%))),MIN((L27-M27)*15%,MAX(0,(L27-M27)*10%+(F27-10000000)*(70%-30%*10%))))),IF(F27<=5000000,0,IF(F27<=10000000,MIN((L27-M27)*10%,MAX(0,(L27-M27)*0%+(F27-5000000)*(70%-30%*0%))),IF(F27<=20000000,MIN((L27-M27)*15%,MAX(0,(L27-M27)*10%+(F27-10000000)*(70%-30%*10%))),IF(F27<=50000000,MIN((L27-M27)*25%,MAX(0,(L27-M27)*15%+(F27-20000000)*(70%-30%*15%))),MIN((L27-M27)*37%,MAX(0,(L27-M27)*25%+(F27-50000000)*(70%-30%*25%)))))))))),IF(OR(B27="2023-24",B27="2024-25",B27="2025-26"),IF(F27<=5000000,0,IF(F27<=10000000,MIN((L27-M27)*10%,MAX(0,(L27-M27)*0%+(F27-5000000)*(70%-30%*0%))),IF(F27<=20000000,MIN((L27-M27)*15%,MAX(0,(L27-M27)*10%+(F27-10000000)*(70%-30%*10%))),MIN((L27-M27)*25%,MAX(0,(L27-M27)*15%+(F27-20000000)*(70%-30%*15%)))))),IF(F27<=5000000,0,IF(F27<=10000000,MIN((L27-M27)*10%,MAX(0,(L27-M27)*0%+(F27-5000000)*(70%-30%*0%))),IF(F27<=20000000,MIN((L27-M27)*15%,MAX(0,(L27-M27)*10%+(F27-10000000)*(70%-30%*10%))),IF(F27<=50000000,MIN((L27-M27)*25%,MAX(0,(L27-M27)*15%+(F27-20000000)*(70%-30%*15%))),MIN((L27-M27)*37%,MAX(0,(L27-M27)*25%+(F27-50000000)*(70%-30%*25%))))))))),2) -> 0 | O27: =ROUND((L27-M27+N27)*IF(OR(B27="2014-15",B27="2015-16",B27="2016-17",B27="2017-18"),3%,4%),2) -> 0 | P27: =ROUND(L27-M27+N27+O27,2) -> 0 | Q27: =ROUND(P27-K27,2) -> 0
A28: =14 -> 14 | B28: =Source_Data!A14 -> 2024-25 | C28: ="OLD" -> OLD | D28: =Source_Data!F14 -> Resident-Senior Citizen | E28: =Source_Data!B14 -> 0 | F28: =Source_Data!D14 -> 0 | G28: =ROUND(IF(C28="OLD",MAX(0,MIN(E28,500000)-IF(D28="Resident-Senior Citizen",300000,250000))*IF(B28="2016-17",10%,5%)+MAX(0,MIN(E28,1000000)-500000)*20%+MAX(0,E28-1000000)*30%,IF(OR(B28="2020-21",B28="2021-22",B28="2022-23"),MAX(0,MIN(E28,500000)-250000)*5%+MAX(0,MIN(E28,750000)-500000)*10%+MAX(0,MIN(E28,1000000)-750000)*15%+MAX(0,MIN(E28,1250000)-1000000)*20%+MAX(0,MIN(E28,1500000)-1250000)*25%+MAX(0,E28-1500000)*30%,IF(B28="2023-24",MAX(0,MIN(E28,600000)-300000)*5%+MAX(0,MIN(E28,900000)-600000)*10%+MAX(0,MIN(E28,1200000)-900000)*15%+MAX(0,MIN(E28,1500000)-1200000)*20%+MAX(0,E28-1500000)*30%,IF(B28="2024-25",MAX(0,MIN(E28,700000)-300000)*5%+MAX(0,MIN(E28,1000000)-700000)*10%+MAX(0,MIN(E28,1200000)-1000000)*15%+MAX(0,MIN(E28,1500000)-1200000)*20%+MAX(0,E28-1500000)*30%,IF(B28="2025-26",MAX(0,MIN(E28,800000)-400000)*5%+MAX(0,MIN(E28,1200000)-800000)*10%+MAX(0,MIN(E28,1600000)-1200000)*15%+MAX(0,MIN(E28,2000000)-1600000)*20%+MAX(0,MIN(E28,2400000)-2000000)*25%+MAX(0,E28-2400000)*30%,0))))),2) -> 0 | H28: =ROUND(MAX(IF(C28="OLD",IF(E28<=IF(OR(B28="2014-15",B28="2015-16",B28="2016-17"),500000,IF(OR(B28="2017-18",B28="2018-19"),350000,500000)),MIN(G28,IF(OR(B28="2014-15",B28="2015-16"),2000,IF(B28="2016-17",5000,IF(OR(B28="2017-18",B28="2018-19"),2500,12500)))),0),IF(E28<=IF(OR(B28="2023-24",B28="2024-25"),700000,IF(B28="2025-26",1200000,500000)),MIN(G28,IF(OR(B28="2023-24",B28="2024-25"),25000,IF(B28="2025-26",60000,12500))),0)),IF(AND(C28="NEW",B28="2025-26",E28>1200000),MAX(0,G28-(E28-1200000)),0)),2) -> 0 | I28: =ROUND(IF(C28="OLD",IF(OR(B28="2014-15",B28="2016-17"),IF(E28<=10000000,0,MIN((G28-H28)*15%,MAX(0,(G28-H28)*0%+(E28-10000000)*(70%-30%*0%)))),IF(B28="2015-16",IF(E28<=10000000,0,MIN((G28-H28)*12%,MAX(0,(G28-H28)*0%+(E28-10000000)*(70%-30%*0%)))),IF(OR(B28="2017-18",B28="2018-19"),IF(E28<=5000000,0,IF(E28<=10000000,MIN((G28-H28)*10%,MAX(0,(G28-H28)*0%+(E28-5000000)*(70%-30%*0%))),MIN((G28-H28)*15%,MAX(0,(G28-H28)*10%+(E28-10000000)*(70%-30%*10%))))),IF(E28<=5000000,0,IF(E28<=10000000,MIN((G28-H28)*10%,MAX(0,(G28-H28)*0%+(E28-5000000)*(70%-30%*0%))),IF(E28<=20000000,MIN((G28-H28)*15%,MAX(0,(G28-H28)*10%+(E28-10000000)*(70%-30%*10%))),IF(E28<=50000000,MIN((G28-H28)*25%,MAX(0,(G28-H28)*15%+(E28-20000000)*(70%-30%*15%))),MIN((G28-H28)*37%,MAX(0,(G28-H28)*25%+(E28-50000000)*(70%-30%*25%)))))))))),IF(OR(B28="2023-24",B28="2024-25",B28="2025-26"),IF(E28<=5000000,0,IF(E28<=10000000,MIN((G28-H28)*10%,MAX(0,(G28-H28)*0%+(E28-5000000)*(70%-30%*0%))),IF(E28<=20000000,MIN((G28-H28)*15%,MAX(0,(G28-H28)*10%+(E28-10000000)*(70%-30%*10%))),MIN((G28-H28)*25%,MAX(0,(G28-H28)*15%+(E28-20000000)*(70%-30%*15%)))))),IF(E28<=5000000,0,IF(E28<=10000000,MIN((G28-H28)*10%,MAX(0,(G28-H28)*0%+(E28-5000000)*(70%-30%*0%))),IF(E28<=20000000,MIN((G28-H28)*15%,MAX(0,(G28-H28)*10%+(E28-10000000)*(70%-30%*10%))),IF(E28<=50000000,MIN((G28-H28)*25%,MAX(0,(G28-H28)*15%+(E28-20000000)*(70%-30%*15%))),MIN((G28-H28)*37%,MAX(0,(G28-H28)*25%+(E28-50000000)*(70%-30%*25%))))))))),2) -> 0 | J28: =ROUND((G28-H28+I28)*IF(OR(B28="2014-15",B28="2015-16",B28="2016-17",B28="2017-18"),3%,4%),2) -> 0 | K28: =ROUND(G28-H28+I28+J28,2) -> 0 | L28: =ROUND(IF(C28="OLD",MAX(0,MIN(F28,500000)-IF(D28="Resident-Senior Citizen",300000,250000))*IF(B28="2016-17",10%,5%)+MAX(0,MIN(F28,1000000)-500000)*20%+MAX(0,F28-1000000)*30%,IF(OR(B28="2020-21",B28="2021-22",B28="2022-23"),MAX(0,MIN(F28,500000)-250000)*5%+MAX(0,MIN(F28,750000)-500000)*10%+MAX(0,MIN(F28,1000000)-750000)*15%+MAX(0,MIN(F28,1250000)-1000000)*20%+MAX(0,MIN(F28,1500000)-1250000)*25%+MAX(0,F28-1500000)*30%,IF(B28="2023-24",MAX(0,MIN(F28,600000)-300000)*5%+MAX(0,MIN(F28,900000)-600000)*10%+MAX(0,MIN(F28,1200000)-900000)*15%+MAX(0,MIN(F28,1500000)-1200000)*20%+MAX(0,F28-1500000)*30%,IF(B28="2024-25",MAX(0,MIN(F28,700000)-300000)*5%+MAX(0,MIN(F28,1000000)-700000)*10%+MAX(0,MIN(F28,1200000)-1000000)*15%+MAX(0,MIN(F28,1500000)-1200000)*20%+MAX(0,F28-1500000)*30%,IF(B28="2025-26",MAX(0,MIN(F28,800000)-400000)*5%+MAX(0,MIN(F28,1200000)-800000)*10%+MAX(0,MIN(F28,1600000)-1200000)*15%+MAX(0,MIN(F28,2000000)-1600000)*20%+MAX(0,MIN(F28,2400000)-2000000)*25%+MAX(0,F28-2400000)*30%,0))))),2) -> 0 | M28: =ROUND(MAX(IF(C28="OLD",IF(F28<=IF(OR(B28="2014-15",B28="2015-16",B28="2016-17"),500000,IF(OR(B28="2017-18",B28="2018-19"),350000,500000)),MIN(L28,IF(OR(B28="2014-15",B28="2015-16"),2000,IF(B28="2016-17",5000,IF(OR(B28="2017-18",B28="2018-19"),2500,12500)))),0),IF(F28<=IF(OR(B28="2023-24",B28="2024-25"),700000,IF(B28="2025-26",1200000,500000)),MIN(L28,IF(OR(B28="2023-24",B28="2024-25"),25000,IF(B28="2025-26",60000,12500))),0)),IF(AND(C28="NEW",B28="2025-26",F28>1200000),MAX(0,L28-(F28-1200000)),0)),2) -> 0 | N28: =ROUND(IF(C28="OLD",IF(OR(B28="2014-15",B28="2016-17"),IF(F28<=10000000,0,MIN((L28-M28)*15%,MAX(0,(L28-M28)*0%+(F28-10000000)*(70%-30%*0%)))),IF(B28="2015-16",IF(F28<=10000000,0,MIN((L28-M28)*12%,MAX(0,(L28-M28)*0%+(F28-10000000)*(70%-30%*0%)))),IF(OR(B28="2017-18",B28="2018-19"),IF(F28<=5000000,0,IF(F28<=10000000,MIN((L28-M28)*10%,MAX(0,(L28-M28)*0%+(F28-5000000)*(70%-30%*0%))),MIN((L28-M28)*15%,MAX(0,(L28-M28)*10%+(F28-10000000)*(70%-30%*10%))))),IF(F28<=5000000,0,IF(F28<=10000000,MIN((L28-M28)*10%,MAX(0,(L28-M28)*0%+(F28-5000000)*(70%-30%*0%))),IF(F28<=20000000,MIN((L28-M28)*15%,MAX(0,(L28-M28)*10%+(F28-10000000)*(70%-30%*10%))),IF(F28<=50000000,MIN((L28-M28)*25%,MAX(0,(L28-M28)*15%+(F28-20000000)*(70%-30%*15%))),MIN((L28-M28)*37%,MAX(0,(L28-M28)*25%+(F28-50000000)*(70%-30%*25%)))))))))),IF(OR(B28="2023-24",B28="2024-25",B28="2025-26"),IF(F28<=5000000,0,IF(F28<=10000000,MIN((L28-M28)*10%,MAX(0,(L28-M28)*0%+(F28-5000000)*(70%-30%*0%))),IF(F28<=20000000,MIN((L28-M28)*15%,MAX(0,(L28-M28)*10%+(F28-10000000)*(70%-30%*10%))),MIN((L28-M28)*25%,MAX(0,(L28-M28)*15%+(F28-20000000)*(70%-30%*15%)))))),IF(F28<=5000000,0,IF(F28<=10000000,MIN((L28-M28)*10%,MAX(0,(L28-M28)*0%+(F28-5000000)*(70%-30%*0%))),IF(F28<=20000000,MIN((L28-M28)*15%,MAX(0,(L28-M28)*10%+(F28-10000000)*(70%-30%*10%))),IF(F28<=50000000,MIN((L28-M28)*25%,MAX(0,(L28-M28)*15%+(F28-20000000)*(70%-30%*15%))),MIN((L28-M28)*37%,MAX(0,(L28-M28)*25%+(F28-50000000)*(70%-30%*25%))))))))),2) -> 0 | O28: =ROUND((L28-M28+N28)*IF(OR(B28="2014-15",B28="2015-16",B28="2016-17",B28="2017-18"),3%,4%),2) -> 0 | P28: =ROUND(L28-M28+N28+O28,2) -> 0 | Q28: =ROUND(P28-K28,2) -> 0
A29: =15 -> 15 | B29: =Source_Data!A15 -> 2025-26 | C29: ="OLD" -> OLD | D29: =Source_Data!F15 -> Resident-Senior Citizen | E29: =Source_Data!B15 -> 0 | F29: =Source_Data!D15 -> 0 | G29: =ROUND(IF(C29="OLD",MAX(0,MIN(E29,500000)-IF(D29="Resident-Senior Citizen",300000,250000))*IF(B29="2016-17",10%,5%)+MAX(0,MIN(E29,1000000)-500000)*20%+MAX(0,E29-1000000)*30%,IF(OR(B29="2020-21",B29="2021-22",B29="2022-23"),MAX(0,MIN(E29,500000)-250000)*5%+MAX(0,MIN(E29,750000)-500000)*10%+MAX(0,MIN(E29,1000000)-750000)*15%+MAX(0,MIN(E29,1250000)-1000000)*20%+MAX(0,MIN(E29,1500000)-1250000)*25%+MAX(0,E29-1500000)*30%,IF(B29="2023-24",MAX(0,MIN(E29,600000)-300000)*5%+MAX(0,MIN(E29,900000)-600000)*10%+MAX(0,MIN(E29,1200000)-900000)*15%+MAX(0,MIN(E29,1500000)-1200000)*20%+MAX(0,E29-1500000)*30%,IF(B29="2024-25",MAX(0,MIN(E29,700000)-300000)*5%+MAX(0,MIN(E29,1000000)-700000)*10%+MAX(0,MIN(E29,1200000)-1000000)*15%+MAX(0,MIN(E29,1500000)-1200000)*20%+MAX(0,E29-1500000)*30%,IF(B29="2025-26",MAX(0,MIN(E29,800000)-400000)*5%+MAX(0,MIN(E29,1200000)-800000)*10%+MAX(0,MIN(E29,1600000)-1200000)*15%+MAX(0,MIN(E29,2000000)-1600000)*20%+MAX(0,MIN(E29,2400000)-2000000)*25%+MAX(0,E29-2400000)*30%,0))))),2) -> 0 | H29: =ROUND(MAX(IF(C29="OLD",IF(E29<=IF(OR(B29="2014-15",B29="2015-16",B29="2016-17"),500000,IF(OR(B29="2017-18",B29="2018-19"),350000,500000)),MIN(G29,IF(OR(B29="2014-15",B29="2015-16"),2000,IF(B29="2016-17",5000,IF(OR(B29="2017-18",B29="2018-19"),2500,12500)))),0),IF(E29<=IF(OR(B29="2023-24",B29="2024-25"),700000,IF(B29="2025-26",1200000,500000)),MIN(G29,IF(OR(B29="2023-24",B29="2024-25"),25000,IF(B29="2025-26",60000,12500))),0)),IF(AND(C29="NEW",B29="2025-26",E29>1200000),MAX(0,G29-(E29-1200000)),0)),2) -> 0 | I29: =ROUND(IF(C29="OLD",IF(OR(B29="2014-15",B29="2016-17"),IF(E29<=10000000,0,MIN((G29-H29)*15%,MAX(0,(G29-H29)*0%+(E29-10000000)*(70%-30%*0%)))),IF(B29="2015-16",IF(E29<=10000000,0,MIN((G29-H29)*12%,MAX(0,(G29-H29)*0%+(E29-10000000)*(70%-30%*0%)))),IF(OR(B29="2017-18",B29="2018-19"),IF(E29<=5000000,0,IF(E29<=10000000,MIN((G29-H29)*10%,MAX(0,(G29-H29)*0%+(E29-5000000)*(70%-30%*0%))),MIN((G29-H29)*15%,MAX(0,(G29-H29)*10%+(E29-10000000)*(70%-30%*10%))))),IF(E29<=5000000,0,IF(E29<=10000000,MIN((G29-H29)*10%,MAX(0,(G29-H29)*0%+(E29-5000000)*(70%-30%*0%))),IF(E29<=20000000,MIN((G29-H29)*15%,MAX(0,(G29-H29)*10%+(E29-10000000)*(70%-30%*10%))),IF(E29<=50000000,MIN((G29-H29)*25%,MAX(0,(G29-H29)*15%+(E29-20000000)*(70%-30%*15%))),MIN((G29-H29)*37%,MAX(0,(G29-H29)*25%+(E29-50000000)*(70%-30%*25%)))))))))),IF(OR(B29="2023-24",B29="2024-25",B29="2025-26"),IF(E29<=5000000,0,IF(E29<=10000000,MIN((G29-H29)*10%,MAX(0,(G29-H29)*0%+(E29-5000000)*(70%-30%*0%))),IF(E29<=20000000,MIN((G29-H29)*15%,MAX(0,(G29-H29)*10%+(E29-10000000)*(70%-30%*10%))),MIN((G29-H29)*25%,MAX(0,(G29-H29)*15%+(E29-20000000)*(70%-30%*15%)))))),IF(E29<=5000000,0,IF(E29<=10000000,MIN((G29-H29)*10%,MAX(0,(G29-H29)*0%+(E29-5000000)*(70%-30%*0%))),IF(E29<=20000000,MIN((G29-H29)*15%,MAX(0,(G29-H29)*10%+(E29-10000000)*(70%-30%*10%))),IF(E29<=50000000,MIN((G29-H29)*25%,MAX(0,(G29-H29)*15%+(E29-20000000)*(70%-30%*15%))),MIN((G29-H29)*37%,MAX(0,(G29-H29)*25%+(E29-50000000)*(70%-30%*25%))))))))),2) -> 0 | J29: =ROUND((G29-H29+I29)*IF(OR(B29="2014-15",B29="2015-16",B29="2016-17",B29="2017-18"),3%,4%),2) -> 0 | K29: =ROUND(G29-H29+I29+J29,2) -> 0 | L29: =ROUND(IF(C29="OLD",MAX(0,MIN(F29,500000)-IF(D29="Resident-Senior Citizen",300000,250000))*IF(B29="2016-17",10%,5%)+MAX(0,MIN(F29,1000000)-500000)*20%+MAX(0,F29-1000000)*30%,IF(OR(B29="2020-21",B29="2021-22",B29="2022-23"),MAX(0,MIN(F29,500000)-250000)*5%+MAX(0,MIN(F29,750000)-500000)*10%+MAX(0,MIN(F29,1000000)-750000)*15%+MAX(0,MIN(F29,1250000)-1000000)*20%+MAX(0,MIN(F29,1500000)-1250000)*25%+MAX(0,F29-1500000)*30%,IF(B29="2023-24",MAX(0,MIN(F29,600000)-300000)*5%+MAX(0,MIN(F29,900000)-600000)*10%+MAX(0,MIN(F29,1200000)-900000)*15%+MAX(0,MIN(F29,1500000)-1200000)*20%+MAX(0,F29-1500000)*30%,IF(B29="2024-25",MAX(0,MIN(F29,700000)-300000)*5%+MAX(0,MIN(F29,1000000)-700000)*10%+MAX(0,MIN(F29,1200000)-1000000)*15%+MAX(0,MIN(F29,1500000)-1200000)*20%+MAX(0,F29-1500000)*30%,IF(B29="2025-26",MAX(0,MIN(F29,800000)-400000)*5%+MAX(0,MIN(F29,1200000)-800000)*10%+MAX(0,MIN(F29,1600000)-1200000)*15%+MAX(0,MIN(F29,2000000)-1600000)*20%+MAX(0,MIN(F29,2400000)-2000000)*25%+MAX(0,F29-2400000)*30%,0))))),2) -> 0 | M29: =ROUND(MAX(IF(C29="OLD",IF(F29<=IF(OR(B29="2014-15",B29="2015-16",B29="2016-17"),500000,IF(OR(B29="2017-18",B29="2018-19"),350000,500000)),MIN(L29,IF(OR(B29="2014-15",B29="2015-16"),2000,IF(B29="2016-17",5000,IF(OR(B29="2017-18",B29="2018-19"),2500,12500)))),0),IF(F29<=IF(OR(B29="2023-24",B29="2024-25"),700000,IF(B29="2025-26",1200000,500000)),MIN(L29,IF(OR(B29="2023-24",B29="2024-25"),25000,IF(B29="2025-26",60000,12500))),0)),IF(AND(C29="NEW",B29="2025-26",F29>1200000),MAX(0,L29-(F29-1200000)),0)),2) -> 0 | N29: =ROUND(IF(C29="OLD",IF(OR(B29="2014-15",B29="2016-17"),IF(F29<=10000000,0,MIN((L29-M29)*15%,MAX(0,(L29-M29)*0%+(F29-10000000)*(70%-30%*0%)))),IF(B29="2015-16",IF(F29<=10000000,0,MIN((L29-M29)*12%,MAX(0,(L29-M29)*0%+(F29-10000000)*(70%-30%*0%)))),IF(OR(B29="2017-18",B29="2018-19"),IF(F29<=5000000,0,IF(F29<=10000000,MIN((L29-M29)*10%,MAX(0,(L29-M29)*0%+(F29-5000000)*(70%-30%*0%))),MIN((L29-M29)*15%,MAX(0,(L29-M29)*10%+(F29-10000000)*(70%-30%*10%))))),IF(F29<=5000000,0,IF(F29<=10000000,MIN((L29-M29)*10%,MAX(0,(L29-M29)*0%+(F29-5000000)*(70%-30%*0%))),IF(F29<=20000000,MIN((L29-M29)*15%,MAX(0,(L29-M29)*10%+(F29-10000000)*(70%-30%*10%))),IF(F29<=50000000,MIN((L29-M29)*25%,MAX(0,(L29-M29)*15%+(F29-20000000)*(70%-30%*15%))),MIN((L29-M29)*37%,MAX(0,(L29-M29)*25%+(F29-50000000)*(70%-30%*25%)))))))))),IF(OR(B29="2023-24",B29="2024-25",B29="2025-26"),IF(F29<=5000000,0,IF(F29<=10000000,MIN((L29-M29)*10%,MAX(0,(L29-M29)*0%+(F29-5000000)*(70%-30%*0%))),IF(F29<=20000000,MIN((L29-M29)*15%,MAX(0,(L29-M29)*10%+(F29-10000000)*(70%-30%*10%))),MIN((L29-M29)*25%,MAX(0,(L29-M29)*15%+(F29-20000000)*(70%-30%*15%)))))),IF(F29<=5000000,0,IF(F29<=10000000,MIN((L29-M29)*10%,MAX(0,(L29-M29)*0%+(F29-5000000)*(70%-30%*0%))),IF(F29<=20000000,MIN((L29-M29)*15%,MAX(0,(L29-M29)*10%+(F29-10000000)*(70%-30%*10%))),IF(F29<=50000000,MIN((L29-M29)*25%,MAX(0,(L29-M29)*15%+(F29-20000000)*(70%-30%*15%))),MIN((L29-M29)*37%,MAX(0,(L29-M29)*25%+(F29-50000000)*(70%-30%*25%))))))))),2) -> 0 | O29: =ROUND((L29-M29+N29)*IF(OR(B29="2014-15",B29="2015-16",B29="2016-17",B29="2017-18"),3%,4%),2) -> 0 | P29: =ROUND(L29-M29+N29+O29,2) -> 0 | Q29: =ROUND(P29-K29,2) -> 0
A32: =4 -> 4 | B32: =Source_Data!A4 -> 2014-15 | C32: ="NEW" -> NEW | D32: =Source_Data!F4 -> Resident-Normal Citizen | E32: =Source_Data!B4 -> 0 | F32: =Source_Data!D4 -> 0 | G32: =ROUND(IF(C32="OLD",MAX(0,MIN(E32,500000)-IF(D32="Resident-Senior Citizen",300000,250000))*IF(B32="2016-17",10%,5%)+MAX(0,MIN(E32,1000000)-500000)*20%+MAX(0,E32-1000000)*30%,IF(OR(B32="2020-21",B32="2021-22",B32="2022-23"),MAX(0,MIN(E32,500000)-250000)*5%+MAX(0,MIN(E32,750000)-500000)*10%+MAX(0,MIN(E32,1000000)-750000)*15%+MAX(0,MIN(E32,1250000)-1000000)*20%+MAX(0,MIN(E32,1500000)-1250000)*25%+MAX(0,E32-1500000)*30%,IF(B32="2023-24",MAX(0,MIN(E32,600000)-300000)*5%+MAX(0,MIN(E32,900000)-600000)*10%+MAX(0,MIN(E32,1200000)-900000)*15%+MAX(0,MIN(E32,1500000)-1200000)*20%+MAX(0,E32-1500000)*30%,IF(B32="2024-25",MAX(0,MIN(E32,700000)-300000)*5%+MAX(0,MIN(E32,1000000)-700000)*10%+MAX(0,MIN(E32,1200000)-1000000)*15%+MAX(0,MIN(E32,1500000)-1200000)*20%+MAX(0,E32-1500000)*30%,IF(B32="2025-26",MAX(0,MIN(E32,800000)-400000)*5%+MAX(0,MIN(E32,1200000)-800000)*10%+MAX(0,MIN(E32,1600000)-1200000)*15%+MAX(0,MIN(E32,2000000)-1600000)*20%+MAX(0,MIN(E32,2400000)-2000000)*25%+MAX(0,E32-2400000)*30%,0))))),2) -> 0 | H32: =ROUND(MAX(IF(C32="OLD",IF(E32<=IF(OR(B32="2014-15",B32="2015-16",B32="2016-17"),500000,IF(OR(B32="2017-18",B32="2018-19"),350000,500000)),MIN(G32,IF(OR(B32="2014-15",B32="2015-16"),2000,IF(B32="2016-17",5000,IF(OR(B32="2017-18",B32="2018-19"),2500,12500)))),0),IF(E32<=IF(OR(B32="2023-24",B32="2024-25"),700000,IF(B32="2025-26",1200000,500000)),MIN(G32,IF(OR(B32="2023-24",B32="2024-25"),25000,IF(B32="2025-26",60000,12500))),0)),IF(AND(C32="NEW",B32="2025-26",E32>1200000),MAX(0,G32-(E32-1200000)),0)),2) -> 0 | I32: =ROUND(IF(C32="OLD",IF(OR(B32="2014-15",B32="2016-17"),IF(E32<=10000000,0,MIN((G32-H32)*15%,MAX(0,(G32-H32)*0%+(E32-10000000)*(70%-30%*0%)))),IF(B32="2015-16",IF(E32<=10000000,0,MIN((G32-H32)*12%,MAX(0,(G32-H32)*0%+(E32-10000000)*(70%-30%*0%)))),IF(OR(B32="2017-18",B32="2018-19"),IF(E32<=5000000,0,IF(E32<=10000000,MIN((G32-H32)*10%,MAX(0,(G32-H32)*0%+(E32-5000000)*(70%-30%*0%))),MIN((G32-H32)*15%,MAX(0,(G32-H32)*10%+(E32-10000000)*(70%-30%*10%))))),IF(E32<=5000000,0,IF(E32<=10000000,MIN((G32-H32)*10%,MAX(0,(G32-H32)*0%+(E32-5000000)*(70%-30%*0%))),IF(E32<=20000000,MIN((G32-H32)*15%,MAX(0,(G32-H32)*10%+(E32-10000000)*(70%-30%*10%))),IF(E32<=50000000,MIN((G32-H32)*25%,MAX(0,(G32-H32)*15%+(E32-20000000)*(70%-30%*15%))),MIN((G32-H32)*37%,MAX(0,(G32-H32)*25%+(E32-50000000)*(70%-30%*25%)))))))))),IF(OR(B32="2023-24",B32="2024-25",B32="2025-26"),IF(E32<=5000000,0,IF(E32<=10000000,MIN((G32-H32)*10%,MAX(0,(G32-H32)*0%+(E32-5000000)*(70%-30%*0%))),IF(E32<=20000000,MIN((G32-H32)*15%,MAX(0,(G32-H32)*10%+(E32-10000000)*(70%-30%*10%))),MIN((G32-H32)*25%,MAX(0,(G32-H32)*15%+(E32-20000000)*(70%-30%*15%)))))),IF(E32<=5000000,0,IF(E32<=10000000,MIN((G32-H32)*10%,MAX(0,(G32-H32)*0%+(E32-5000000)*(70%-30%*0%))),IF(E32<=20000000,MIN((G32-H32)*15%,MAX(0,(G32-H32)*10%+(E32-10000000)*(70%-30%*10%))),IF(E32<=50000000,MIN((G32-H32)*25%,MAX(0,(G32-H32)*15%+(E32-20000000)*(70%-30%*15%))),MIN((G32-H32)*37%,MAX(0,(G32-H32)*25%+(E32-50000000)*(70%-30%*25%))))))))),2) -> 0 | J32: =ROUND((G32-H32+I32)*IF(OR(B32="2014-15",B32="2015-16",B32="2016-17",B32="2017-18"),3%,4%),2) -> 0 | K32: =ROUND(G32-H32+I32+J32,2) -> 0 | L32: =ROUND(IF(C32="OLD",MAX(0,MIN(F32,500000)-IF(D32="Resident-Senior Citizen",300000,250000))*IF(B32="2016-17",10%,5%)+MAX(0,MIN(F32,1000000)-500000)*20%+MAX(0,F32-1000000)*30%,IF(OR(B32="2020-21",B32="2021-22",B32="2022-23"),MAX(0,MIN(F32,500000)-250000)*5%+MAX(0,MIN(F32,750000)-500000)*10%+MAX(0,MIN(F32,1000000)-750000)*15%+MAX(0,MIN(F32,1250000)-1000000)*20%+MAX(0,MIN(F32,1500000)-1250000)*25%+MAX(0,F32-1500000)*30%,IF(B32="2023-24",MAX(0,MIN(F32,600000)-300000)*5%+MAX(0,MIN(F32,900000)-600000)*10%+MAX(0,MIN(F32,1200000)-900000)*15%+MAX(0,MIN(F32,1500000)-1200000)*20%+MAX(0,F32-1500000)*30%,IF(B32="2024-25",MAX(0,MIN(F32,700000)-300000)*5%+MAX(0,MIN(F32,1000000)-700000)*10%+MAX(0,MIN(F32,1200000)-1000000)*15%+MAX(0,MIN(F32,1500000)-1200000)*20%+MAX(0,F32-1500000)*30%,IF(B32="2025-26",MAX(0,MIN(F32,800000)-400000)*5%+MAX(0,MIN(F32,1200000)-800000)*10%+MAX(0,MIN(F32,1600000)-1200000)*15%+MAX(0,MIN(F32,2000000)-1600000)*20%+MAX(0,MIN(F32,2400000)-2000000)*25%+MAX(0,F32-2400000)*30%,0))))),2) -> 0 | M32: =ROUND(MAX(IF(C32="OLD",IF(F32<=IF(OR(B32="2014-15",B32="2015-16",B32="2016-17"),500000,IF(OR(B32="2017-18",B32="2018-19"),350000,500000)),MIN(L32,IF(OR(B32="2014-15",B32="2015-16"),2000,IF(B32="2016-17",5000,IF(OR(B32="2017-18",B32="2018-19"),2500,12500)))),0),IF(F32<=IF(OR(B32="2023-24",B32="2024-25"),700000,IF(B32="2025-26",1200000,500000)),MIN(L32,IF(OR(B32="2023-24",B32="2024-25"),25000,IF(B32="2025-26",60000,12500))),0)),IF(AND(C32="NEW",B32="2025-26",F32>1200000),MAX(0,L32-(F32-1200000)),0)),2) -> 0 | N32: =ROUND(IF(C32="OLD",IF(OR(B32="2014-15",B32="2016-17"),IF(F32<=10000000,0,MIN((L32-M32)*15%,MAX(0,(L32-M32)*0%+(F32-10000000)*(70%-30%*0%)))),IF(B32="2015-16",IF(F32<=10000000,0,MIN((L32-M32)*12%,MAX(0,(L32-M32)*0%+(F32-10000000)*(70%-30%*0%)))),IF(OR(B32="2017-18",B32="2018-19"),IF(F32<=5000000,0,IF(F32<=10000000,MIN((L32-M32)*10%,MAX(0,(L32-M32)*0%+(F32-5000000)*(70%-30%*0%))),MIN((L32-M32)*15%,MAX(0,(L32-M32)*10%+(F32-10000000)*(70%-30%*10%))))),IF(F32<=5000000,0,IF(F32<=10000000,MIN((L32-M32)*10%,MAX(0,(L32-M32)*0%+(F32-5000000)*(70%-30%*0%))),IF(F32<=20000000,MIN((L32-M32)*15%,MAX(0,(L32-M32)*10%+(F32-10000000)*(70%-30%*10%))),IF(F32<=50000000,MIN((L32-M32)*25%,MAX(0,(L32-M32)*15%+(F32-20000000)*(70%-30%*15%))),MIN((L32-M32)*37%,MAX(0,(L32-M32)*25%+(F32-50000000)*(70%-30%*25%)))))))))),IF(OR(B32="2023-24",B32="2024-25",B32="2025-26"),IF(F32<=5000000,0,IF(F32<=10000000,MIN((L32-M32)*10%,MAX(0,(L32-M32)*0%+(F32-5000000)*(70%-30%*0%))),IF(F32<=20000000,MIN((L32-M32)*15%,MAX(0,(L32-M32)*10%+(F32-10000000)*(70%-30%*10%))),MIN((L32-M32)*25%,MAX(0,(L32-M32)*15%+(F32-20000000)*(70%-30%*15%)))))),IF(F32<=5000000,0,IF(F32<=10000000,MIN((L32-M32)*10%,MAX(0,(L32-M32)*0%+(F32-5000000)*(70%-30%*0%))),IF(F32<=20000000,MIN((L32-M32)*15%,MAX(0,(L32-M32)*10%+(F32-10000000)*(70%-30%*10%))),IF(F32<=50000000,MIN((L32-M32)*25%,MAX(0,(L32-M32)*15%+(F32-20000000)*(70%-30%*15%))),MIN((L32-M32)*37%,MAX(0,(L32-M32)*25%+(F32-50000000)*(70%-30%*25%))))))))),2) -> 0 | O32: =ROUND((L32-M32+N32)*IF(OR(B32="2014-15",B32="2015-16",B32="2016-17",B32="2017-18"),3%,4%),2) -> 0 | P32: =ROUND(L32-M32+N32+O32,2) -> 0 | Q32: =ROUND(P32-K32,2) -> 0
A33: =5 -> 5 | B33: =Source_Data!A5 -> 2015-16 | C33: ="NEW" -> NEW | D33: =Source_Data!F5 -> Resident-Normal Citizen | E33: =Source_Data!B5 -> 0 | F33: =Source_Data!D5 -> 0 | G33: =ROUND(IF(C33="OLD",MAX(0,MIN(E33,500000)-IF(D33="Resident-Senior Citizen",300000,250000))*IF(B33="2016-17",10%,5%)+MAX(0,MIN(E33,1000000)-500000)*20%+MAX(0,E33-1000000)*30%,IF(OR(B33="2020-21",B33="2021-22",B33="2022-23"),MAX(0,MIN(E33,500000)-250000)*5%+MAX(0,MIN(E33,750000)-500000)*10%+MAX(0,MIN(E33,1000000)-750000)*15%+MAX(0,MIN(E33,1250000)-1000000)*20%+MAX(0,MIN(E33,1500000)-1250000)*25%+MAX(0,E33-1500000)*30%,IF(B33="2023-24",MAX(0,MIN(E33,600000)-300000)*5%+MAX(0,MIN(E33,900000)-600000)*10%+MAX(0,MIN(E33,1200000)-900000)*15%+MAX(0,MIN(E33,1500000)-1200000)*20%+MAX(0,E33-1500000)*30%,IF(B33="2024-25",MAX(0,MIN(E33,700000)-300000)*5%+MAX(0,MIN(E33,1000000)-700000)*10%+MAX(0,MIN(E33,1200000)-1000000)*15%+MAX(0,MIN(E33,1500000)-1200000)*20%+MAX(0,E33-1500000)*30%,IF(B33="2025-26",MAX(0,MIN(E33,800000)-400000)*5%+MAX(0,MIN(E33,1200000)-800000)*10%+MAX(0,MIN(E33,1600000)-1200000)*15%+MAX(0,MIN(E33,2000000)-1600000)*20%+MAX(0,MIN(E33,2400000)-2000000)*25%+MAX(0,E33-2400000)*30%,0))))),2) -> 0 | H33: =ROUND(MAX(IF(C33="OLD",IF(E33<=IF(OR(B33="2014-15",B33="2015-16",B33="2016-17"),500000,IF(OR(B33="2017-18",B33="2018-19"),350000,500000)),MIN(G33,IF(OR(B33="2014-15",B33="2015-16"),2000,IF(B33="2016-17",5000,IF(OR(B33="2017-18",B33="2018-19"),2500,12500)))),0),IF(E33<=IF(OR(B33="2023-24",B33="2024-25"),700000,IF(B33="2025-26",1200000,500000)),MIN(G33,IF(OR(B33="2023-24",B33="2024-25"),25000,IF(B33="2025-26",60000,12500))),0)),IF(AND(C33="NEW",B33="2025-26",E33>1200000),MAX(0,G33-(E33-1200000)),0)),2) -> 0 | I33: =ROUND(IF(C33="OLD",IF(OR(B33="2014-15",B33="2016-17"),IF(E33<=10000000,0,MIN((G33-H33)*15%,MAX(0,(G33-H33)*0%+(E33-10000000)*(70%-30%*0%)))),IF(B33="2015-16",IF(E33<=10000000,0,MIN((G33-H33)*12%,MAX(0,(G33-H33)*0%+(E33-10000000)*(70%-30%*0%)))),IF(OR(B33="2017-18",B33="2018-19"),IF(E33<=5000000,0,IF(E33<=10000000,MIN((G33-H33)*10%,MAX(0,(G33-H33)*0%+(E33-5000000)*(70%-30%*0%))),MIN((G33-H33)*15%,MAX(0,(G33-H33)*10%+(E33-10000000)*(70%-30%*10%))))),IF(E33<=5000000,0,IF(E33<=10000000,MIN((G33-H33)*10%,MAX(0,(G33-H33)*0%+(E33-5000000)*(70%-30%*0%))),IF(E33<=20000000,MIN((G33-H33)*15%,MAX(0,(G33-H33)*10%+(E33-10000000)*(70%-30%*10%))),IF(E33<=50000000,MIN((G33-H33)*25%,MAX(0,(G33-H33)*15%+(E33-20000000)*(70%-30%*15%))),MIN((G33-H33)*37%,MAX(0,(G33-H33)*25%+(E33-50000000)*(70%-30%*25%)))))))))),IF(OR(B33="2023-24",B33="2024-25",B33="2025-26"),IF(E33<=5000000,0,IF(E33<=10000000,MIN((G33-H33)*10%,MAX(0,(G33-H33)*0%+(E33-5000000)*(70%-30%*0%))),IF(E33<=20000000,MIN((G33-H33)*15%,MAX(0,(G33-H33)*10%+(E33-10000000)*(70%-30%*10%))),MIN((G33-H33)*25%,MAX(0,(G33-H33)*15%+(E33-20000000)*(70%-30%*15%)))))),IF(E33<=5000000,0,IF(E33<=10000000,MIN((G33-H33)*10%,MAX(0,(G33-H33)*0%+(E33-5000000)*(70%-30%*0%))),IF(E33<=20000000,MIN((G33-H33)*15%,MAX(0,(G33-H33)*10%+(E33-10000000)*(70%-30%*10%))),IF(E33<=50000000,MIN((G33-H33)*25%,MAX(0,(G33-H33)*15%+(E33-20000000)*(70%-30%*15%))),MIN((G33-H33)*37%,MAX(0,(G33-H33)*25%+(E33-50000000)*(70%-30%*25%))))))))),2) -> 0 | J33: =ROUND((G33-H33+I33)*IF(OR(B33="2014-15",B33="2015-16",B33="2016-17",B33="2017-18"),3%,4%),2) -> 0 | K33: =ROUND(G33-H33+I33+J33,2) -> 0 | L33: =ROUND(IF(C33="OLD",MAX(0,MIN(F33,500000)-IF(D33="Resident-Senior Citizen",300000,250000))*IF(B33="2016-17",10%,5%)+MAX(0,MIN(F33,1000000)-500000)*20%+MAX(0,F33-1000000)*30%,IF(OR(B33="2020-21",B33="2021-22",B33="2022-23"),MAX(0,MIN(F33,500000)-250000)*5%+MAX(0,MIN(F33,750000)-500000)*10%+MAX(0,MIN(F33,1000000)-750000)*15%+MAX(0,MIN(F33,1250000)-1000000)*20%+MAX(0,MIN(F33,1500000)-1250000)*25%+MAX(0,F33-1500000)*30%,IF(B33="2023-24",MAX(0,MIN(F33,600000)-300000)*5%+MAX(0,MIN(F33,900000)-600000)*10%+MAX(0,MIN(F33,1200000)-900000)*15%+MAX(0,MIN(F33,1500000)-1200000)*20%+MAX(0,F33-1500000)*30%,IF(B33="2024-25",MAX(0,MIN(F33,700000)-300000)*5%+MAX(0,MIN(F33,1000000)-700000)*10%+MAX(0,MIN(F33,1200000)-1000000)*15%+MAX(0,MIN(F33,1500000)-1200000)*20%+MAX(0,F33-1500000)*30%,IF(B33="2025-26",MAX(0,MIN(F33,800000)-400000)*5%+MAX(0,MIN(F33,1200000)-800000)*10%+MAX(0,MIN(F33,1600000)-1200000)*15%+MAX(0,MIN(F33,2000000)-1600000)*20%+MAX(0,MIN(F33,2400000)-2000000)*25%+MAX(0,F33-2400000)*30%,0))))),2) -> 0 | M33: =ROUND(MAX(IF(C33="OLD",IF(F33<=IF(OR(B33="2014-15",B33="2015-16",B33="2016-17"),500000,IF(OR(B33="2017-18",B33="2018-19"),350000,500000)),MIN(L33,IF(OR(B33="2014-15",B33="2015-16"),2000,IF(B33="2016-17",5000,IF(OR(B33="2017-18",B33="2018-19"),2500,12500)))),0),IF(F33<=IF(OR(B33="2023-24",B33="2024-25"),700000,IF(B33="2025-26",1200000,500000)),MIN(L33,IF(OR(B33="2023-24",B33="2024-25"),25000,IF(B33="2025-26",60000,12500))),0)),IF(AND(C33="NEW",B33="2025-26",F33>1200000),MAX(0,L33-(F33-1200000)),0)),2) -> 0 | N33: =ROUND(IF(C33="OLD",IF(OR(B33="2014-15",B33="2016-17"),IF(F33<=10000000,0,MIN((L33-M33)*15%,MAX(0,(L33-M33)*0%+(F33-10000000)*(70%-30%*0%)))),IF(B33="2015-16",IF(F33<=10000000,0,MIN((L33-M33)*12%,MAX(0,(L33-M33)*0%+(F33-10000000)*(70%-30%*0%)))),IF(OR(B33="2017-18",B33="2018-19"),IF(F33<=5000000,0,IF(F33<=10000000,MIN((L33-M33)*10%,MAX(0,(L33-M33)*0%+(F33-5000000)*(70%-30%*0%))),MIN((L33-M33)*15%,MAX(0,(L33-M33)*10%+(F33-10000000)*(70%-30%*10%))))),IF(F33<=5000000,0,IF(F33<=10000000,MIN((L33-M33)*10%,MAX(0,(L33-M33)*0%+(F33-5000000)*(70%-30%*0%))),IF(F33<=20000000,MIN((L33-M33)*15%,MAX(0,(L33-M33)*10%+(F33-10000000)*(70%-30%*10%))),IF(F33<=50000000,MIN((L33-M33)*25%,MAX(0,(L33-M33)*15%+(F33-20000000)*(70%-30%*15%))),MIN((L33-M33)*37%,MAX(0,(L33-M33)*25%+(F33-50000000)*(70%-30%*25%)))))))))),IF(OR(B33="2023-24",B33="2024-25",B33="2025-26"),IF(F33<=5000000,0,IF(F33<=10000000,MIN((L33-M33)*10%,MAX(0,(L33-M33)*0%+(F33-5000000)*(70%-30%*0%))),IF(F33<=20000000,MIN((L33-M33)*15%,MAX(0,(L33-M33)*10%+(F33-10000000)*(70%-30%*10%))),MIN((L33-M33)*25%,MAX(0,(L33-M33)*15%+(F33-20000000)*(70%-30%*15%)))))),IF(F33<=5000000,0,IF(F33<=10000000,MIN((L33-M33)*10%,MAX(0,(L33-M33)*0%+(F33-5000000)*(70%-30%*0%))),IF(F33<=20000000,MIN((L33-M33)*15%,MAX(0,(L33-M33)*10%+(F33-10000000)*(70%-30%*10%))),IF(F33<=50000000,MIN((L33-M33)*25%,MAX(0,(L33-M33)*15%+(F33-20000000)*(70%-30%*15%))),MIN((L33-M33)*37%,MAX(0,(L33-M33)*25%+(F33-50000000)*(70%-30%*25%))))))))),2) -> 0 | O33: =ROUND((L33-M33+N33)*IF(OR(B33="2014-15",B33="2015-16",B33="2016-17",B33="2017-18"),3%,4%),2) -> 0 | P33: =ROUND(L33-M33+N33+O33,2) -> 0 | Q33: =ROUND(P33-K33,2) -> 0
A34: =6 -> 6 | B34: =Source_Data!A6 -> 2016-17 | C34: ="NEW" -> NEW | D34: =Source_Data!F6 -> Resident-Senior Citizen | E34: =Source_Data!B6 -> 0 | F34: =Source_Data!D6 -> 0 | G34: =ROUND(IF(C34="OLD",MAX(0,MIN(E34,500000)-IF(D34="Resident-Senior Citizen",300000,250000))*IF(B34="2016-17",10%,5%)+MAX(0,MIN(E34,1000000)-500000)*20%+MAX(0,E34-1000000)*30%,IF(OR(B34="2020-21",B34="2021-22",B34="2022-23"),MAX(0,MIN(E34,500000)-250000)*5%+MAX(0,MIN(E34,750000)-500000)*10%+MAX(0,MIN(E34,1000000)-750000)*15%+MAX(0,MIN(E34,1250000)-1000000)*20%+MAX(0,MIN(E34,1500000)-1250000)*25%+MAX(0,E34-1500000)*30%,IF(B34="2023-24",MAX(0,MIN(E34,600000)-300000)*5%+MAX(0,MIN(E34,900000)-600000)*10%+MAX(0,MIN(E34,1200000)-900000)*15%+MAX(0,MIN(E34,1500000)-1200000)*20%+MAX(0,E34-1500000)*30%,IF(B34="2024-25",MAX(0,MIN(E34,700000)-300000)*5%+MAX(0,MIN(E34,1000000)-700000)*10%+MAX(0,MIN(E34,1200000)-1000000)*15%+MAX(0,MIN(E34,1500000)-1200000)*20%+MAX(0,E34-1500000)*30%,IF(B34="2025-26",MAX(0,MIN(E34,800000)-400000)*5%+MAX(0,MIN(E34,1200000)-800000)*10%+MAX(0,MIN(E34,1600000)-1200000)*15%+MAX(0,MIN(E34,2000000)-1600000)*20%+MAX(0,MIN(E34,2400000)-2000000)*25%+MAX(0,E34-2400000)*30%,0))))),2) -> 0 | H34: =ROUND(MAX(IF(C34="OLD",IF(E34<=IF(OR(B34="2014-15",B34="2015-16",B34="2016-17"),500000,IF(OR(B34="2017-18",B34="2018-19"),350000,500000)),MIN(G34,IF(OR(B34="2014-15",B34="2015-16"),2000,IF(B34="2016-17",5000,IF(OR(B34="2017-18",B34="2018-19"),2500,12500)))),0),IF(E34<=IF(OR(B34="2023-24",B34="2024-25"),700000,IF(B34="2025-26",1200000,500000)),MIN(G34,IF(OR(B34="2023-24",B34="2024-25"),25000,IF(B34="2025-26",60000,12500))),0)),IF(AND(C34="NEW",B34="2025-26",E34>1200000),MAX(0,G34-(E34-1200000)),0)),2) -> 0 | I34: =ROUND(IF(C34="OLD",IF(OR(B34="2014-15",B34="2016-17"),IF(E34<=10000000,0,MIN((G34-H34)*15%,MAX(0,(G34-H34)*0%+(E34-10000000)*(70%-30%*0%)))),IF(B34="2015-16",IF(E34<=10000000,0,MIN((G34-H34)*12%,MAX(0,(G34-H34)*0%+(E34-10000000)*(70%-30%*0%)))),IF(OR(B34="2017-18",B34="2018-19"),IF(E34<=5000000,0,IF(E34<=10000000,MIN((G34-H34)*10%,MAX(0,(G34-H34)*0%+(E34-5000000)*(70%-30%*0%))),MIN((G34-H34)*15%,MAX(0,(G34-H34)*10%+(E34-10000000)*(70%-30%*10%))))),IF(E34<=5000000,0,IF(E34<=10000000,MIN((G34-H34)*10%,MAX(0,(G34-H34)*0%+(E34-5000000)*(70%-30%*0%))),IF(E34<=20000000,MIN((G34-H34)*15%,MAX(0,(G34-H34)*10%+(E34-10000000)*(70%-30%*10%))),IF(E34<=50000000,MIN((G34-H34)*25%,MAX(0,(G34-H34)*15%+(E34-20000000)*(70%-30%*15%))),MIN((G34-H34)*37%,MAX(0,(G34-H34)*25%+(E34-50000000)*(70%-30%*25%)))))))))),IF(OR(B34="2023-24",B34="2024-25",B34="2025-26"),IF(E34<=5000000,0,IF(E34<=10000000,MIN((G34-H34)*10%,MAX(0,(G34-H34)*0%+(E34-5000000)*(70%-30%*0%))),IF(E34<=20000000,MIN((G34-H34)*15%,MAX(0,(G34-H34)*10%+(E34-10000000)*(70%-30%*10%))),MIN((G34-H34)*25%,MAX(0,(G34-H34)*15%+(E34-20000000)*(70%-30%*15%)))))),IF(E34<=5000000,0,IF(E34<=10000000,MIN((G34-H34)*10%,MAX(0,(G34-H34)*0%+(E34-5000000)*(70%-30%*0%))),IF(E34<=20000000,MIN((G34-H34)*15%,MAX(0,(G34-H34)*10%+(E34-10000000)*(70%-30%*10%))),IF(E34<=50000000,MIN((G34-H34)*25%,MAX(0,(G34-H34)*15%+(E34-20000000)*(70%-30%*15%))),MIN((G34-H34)*37%,MAX(0,(G34-H34)*25%+(E34-50000000)*(70%-30%*25%))))))))),2) -> 0 | J34: =ROUND((G34-H34+I34)*IF(OR(B34="2014-15",B34="2015-16",B34="2016-17",B34="2017-18"),3%,4%),2) -> 0 | K34: =ROUND(G34-H34+I34+J34,2) -> 0 | L34: =ROUND(IF(C34="OLD",MAX(0,MIN(F34,500000)-IF(D34="Resident-Senior Citizen",300000,250000))*IF(B34="2016-17",10%,5%)+MAX(0,MIN(F34,1000000)-500000)*20%+MAX(0,F34-1000000)*30%,IF(OR(B34="2020-21",B34="2021-22",B34="2022-23"),MAX(0,MIN(F34,500000)-250000)*5%+MAX(0,MIN(F34,750000)-500000)*10%+MAX(0,MIN(F34,1000000)-750000)*15%+MAX(0,MIN(F34,1250000)-1000000)*20%+MAX(0,MIN(F34,1500000)-1250000)*25%+MAX(0,F34-1500000)*30%,IF(B34="2023-24",MAX(0,MIN(F34,600000)-300000)*5%+MAX(0,MIN(F34,900000)-600000)*10%+MAX(0,MIN(F34,1200000)-900000)*15%+MAX(0,MIN(F34,1500000)-1200000)*20%+MAX(0,F34-1500000)*30%,IF(B34="2024-25",MAX(0,MIN(F34,700000)-300000)*5%+MAX(0,MIN(F34,1000000)-700000)*10%+MAX(0,MIN(F34,1200000)-1000000)*15%+MAX(0,MIN(F34,1500000)-1200000)*20%+MAX(0,F34-1500000)*30%,IF(B34="2025-26",MAX(0,MIN(F34,800000)-400000)*5%+MAX(0,MIN(F34,1200000)-800000)*10%+MAX(0,MIN(F34,1600000)-1200000)*15%+MAX(0,MIN(F34,2000000)-1600000)*20%+MAX(0,MIN(F34,2400000)-2000000)*25%+MAX(0,F34-2400000)*30%,0))))),2) -> 0 | M34: =ROUND(MAX(IF(C34="OLD",IF(F34<=IF(OR(B34="2014-15",B34="2015-16",B34="2016-17"),500000,IF(OR(B34="2017-18",B34="2018-19"),350000,500000)),MIN(L34,IF(OR(B34="2014-15",B34="2015-16"),2000,IF(B34="2016-17",5000,IF(OR(B34="2017-18",B34="2018-19"),2500,12500)))),0),IF(F34<=IF(OR(B34="2023-24",B34="2024-25"),700000,IF(B34="2025-26",1200000,500000)),MIN(L34,IF(OR(B34="2023-24",B34="2024-25"),25000,IF(B34="2025-26",60000,12500))),0)),IF(AND(C34="NEW",B34="2025-26",F34>1200000),MAX(0,L34-(F34-1200000)),0)),2) -> 0 | N34: =ROUND(IF(C34="OLD",IF(OR(B34="2014-15",B34="2016-17"),IF(F34<=10000000,0,MIN((L34-M34)*15%,MAX(0,(L34-M34)*0%+(F34-10000000)*(70%-30%*0%)))),IF(B34="2015-16",IF(F34<=10000000,0,MIN((L34-M34)*12%,MAX(0,(L34-M34)*0%+(F34-10000000)*(70%-30%*0%)))),IF(OR(B34="2017-18",B34="2018-19"),IF(F34<=5000000,0,IF(F34<=10000000,MIN((L34-M34)*10%,MAX(0,(L34-M34)*0%+(F34-5000000)*(70%-30%*0%))),MIN((L34-M34)*15%,MAX(0,(L34-M34)*10%+(F34-10000000)*(70%-30%*10%))))),IF(F34<=5000000,0,IF(F34<=10000000,MIN((L34-M34)*10%,MAX(0,(L34-M34)*0%+(F34-5000000)*(70%-30%*0%))),IF(F34<=20000000,MIN((L34-M34)*15%,MAX(0,(L34-M34)*10%+(F34-10000000)*(70%-30%*10%))),IF(F34<=50000000,MIN((L34-M34)*25%,MAX(0,(L34-M34)*15%+(F34-20000000)*(70%-30%*15%))),MIN((L34-M34)*37%,MAX(0,(L34-M34)*25%+(F34-50000000)*(70%-30%*25%)))))))))),IF(OR(B34="2023-24",B34="2024-25",B34="2025-26"),IF(F34<=5000000,0,IF(F34<=10000000,MIN((L34-M34)*10%,MAX(0,(L34-M34)*0%+(F34-5000000)*(70%-30%*0%))),IF(F34<=20000000,MIN((L34-M34)*15%,MAX(0,(L34-M34)*10%+(F34-10000000)*(70%-30%*10%))),MIN((L34-M34)*25%,MAX(0,(L34-M34)*15%+(F34-20000000)*(70%-30%*15%)))))),IF(F34<=5000000,0,IF(F34<=10000000,MIN((L34-M34)*10%,MAX(0,(L34-M34)*0%+(F34-5000000)*(70%-30%*0%))),IF(F34<=20000000,MIN((L34-M34)*15%,MAX(0,(L34-M34)*10%+(F34-10000000)*(70%-30%*10%))),IF(F34<=50000000,MIN((L34-M34)*25%,MAX(0,(L34-M34)*15%+(F34-20000000)*(70%-30%*15%))),MIN((L34-M34)*37%,MAX(0,(L34-M34)*25%+(F34-50000000)*(70%-30%*25%))))))))),2) -> 0 | O34: =ROUND((L34-M34+N34)*IF(OR(B34="2014-15",B34="2015-16",B34="2016-17",B34="2017-18"),3%,4%),2) -> 0 | P34: =ROUND(L34-M34+N34+O34,2) -> 0 | Q34: =ROUND(P34-K34,2) -> 0
